Workbook

Sheet Monthly Summary
A2: Month | B2: P3 | C2: P4 | D2: P5 | E2: P6 | F2: P7 | G2: P8 | H2: P9 | I2: P10 | J2: P11 | K2: P12 | M2: FY 2026
A4: SD Ramp Plan | B4: =SUMIF('Weekly Summary'!$2:$2,B$2,'Weekly Summary'!6:6) -> 0 | C4: =SUMIF('Weekly Summary'!$2:$2,C$2,'Weekly Summary'!6:6) -> 230400 | D4: =SUMIF('Weekly Summary'!$2:$2,D$2,'Weekly Summary'!6:6) -> 540000 | E4: =SUMIF('Weekly Summary'!$2:$2,E$2,'Weekly Summary'!6:6) -> 1152000 | F4: =SUMIF('Weekly Summary'!$2:$2,F$2,'Weekly Summary'!6:6) -> 1592524.8 | G4: =SUMIF('Weekly Summary'!$2:$2,G$2,'Weekly Summary'!6:6) -> 1728000 | H4: =SUMIF('Weekly Summary'!$2:$2,H$2,'Weekly Summary'!6:6) -> 1871424 | I4: =SUMIF('Weekly Summary'!$2:$2,I$2,'Weekly Summary'!6:6) -> 2592000 | ... K4: =SUMIF('Weekly Summary'!$2:$2,K$2,'Weekly Summary'!6:6) -> 1772928 | M4: =SUM(C4:L4) -> 13252205
A5: New SD Plant Plan | B5: =SUMIF('Weekly Summary'!$2:$2,B$2,'Weekly Summary'!7:7) -> 0 | C5: =SUMIF('Weekly Summary'!$2:$2,C$2,'Weekly Summary'!7:7) -> 0 | D5: =SUMIF('Weekly Summary'!$2:$2,D$2,'Weekly Summary'!7:7) -> 0 | E5: =SUMIF('Weekly Summary'!$2:$2,E$2,'Weekly Summary'!7:7) -> 0 | F5: =SUMIF('Weekly Summary'!$2:$2,F$2,'Weekly Summary'!7:7) -> 0 | G5: =SUMIF('Weekly Summary'!$2:$2,G$2,'Weekly Summary'!7:7) -> 1120000 | H5: =SUMIF('Weekly Summary'!$2:$2,H$2,'Weekly Summary'!7:7) -> 1920000 | I5: =SUMIF('Weekly Summary'!$2:$2,I$2,'Weekly Summary'!7:7) -> 3000000 | ... K5: =SUMIF('Weekly Summary'!$2:$2,K$2,'Weekly Summary'!7:7) -> 2880000 | M5: =SUM(C5:L5) -> 11800000
A7: SD Produced | B7: =SUMIF('Weekly Summary'!$2:$2,B$2,'Weekly Summary'!9:9) -> 76320 | C7: =SUMIF('Weekly Summary'!$2:$2,C$2,'Weekly Summary'!9:9) -> 1122876.2 | D7: =SUMIF('Weekly Summary'!$2:$2,D$2,'Weekly Summary'!9:9) -> 908334.12 | E7: =SUMIF('Weekly Summary'!$2:$2,E$2,'Weekly Summary'!9:9) -> 1025020.6 | F7: =SUMIF('Weekly Summary'!$2:$2,F$2,'Weekly Summary'!9:9) -> 1092496.1 | G7: =SUMIF('Weekly Summary'!$2:$2,G$2,'Weekly Summary'!9:9) -> 1073207.1 | H7: =SUMIF('Weekly Summary'!$2:$2,H$2,'Weekly Summary'!9:9) -> 460981.17 | I7: =SUMIF('Weekly Summary'!$2:$2,I$2,'Weekly Summary'!9:9) -> 0 | ... K7: =SUMIF('Weekly Summary'!$2:$2,K$2,'Weekly Summary'!9:9) -> 0 | M7: =SUM(C7:L7) -> 5682915.2
A8: SD Packed | B8: =SUMIF('Weekly Summary'!$2:$2,B$2,'Weekly Summary'!10:10) -> 76320 | C8: =SUMIF('Weekly Summary'!$2:$2,C$2,'Weekly Summary'!10:10) -> 996390 | D8: =SUMIF('Weekly Summary'!$2:$2,D$2,'Weekly Summary'!10:10) -> 801000 | E8: =SUMIF('Weekly Summary'!$2:$2,E$2,'Weekly Summary'!10:10) -> 1090392 | F8: =SUMIF('Weekly Summary'!$2:$2,F$2,'Weekly Summary'!10:10) -> 909570 | G8: =SUMIF('Weekly Summary'!$2:$2,G$2,'Weekly Summary'!10:10) -> 867120 | H8: =SUMIF('Weekly Summary'!$2:$2,H$2,'Weekly Summary'!10:10) -> 457460 | I8: =SUMIF('Weekly Summary'!$2:$2,I$2,'Weekly Summary'!10:10) -> 0 | ... K8: =SUMIF('Weekly Summary'!$2:$2,K$2,'Weekly Summary'!10:10) -> 0 | M8: =SUM(C8:L8) -> 5121932
A11: Produced v Ramp Plan | B11: =+B7-B4 -> 76320 | C11: =+C7-C4 -> 892476.17 | D11: =+D7-D4 -> 368334.12 | E11: =+E7-E4 -> -126979.41 | F11: =+F7-F4 -> -500028.75 | G11: =+G7-G4 -> -654792.89 | H11: =+H7-H4 -> -1410442.8 | M11: =SUM(B11:L11) -> -1355113.6
A12: Packed v Ramp Plan | B12: =+B8-B4 -> 76320 | C12: =+C8-C4 -> 765990 | D12: =+D8-D4 -> 261000 | E12: =+E8-E4 -> -61608 | F12: =+F8-F4 -> -682954.8 | G12: =+G8-G4 -> -860880 | H12: =+H8-H4 -> -1413964 | M12: =SUM(B12:L12) -> -1916096.8
A13: Produced v New Plant Plan | G13: =+G7-G5 -> -46792.889 | H13: =+H7-H5 -> -1459018.8 | M13: =SUM(B13:L13) -> -1505811.7
A14: Packed v New Plant Plan | G14: =+G8-G5 -> -252880 | H14: =+H8-H5 -> -1462540 | M14: =SUM(B14:L14) -> -1715420
A16: Waste Pcs Production | B16: =SUMIF('Weekly Summary'!$2:$2,B$2,'Weekly Summary'!18:18) -> 0 | C16: =SUMIF('Weekly Summary'!$2:$2,C$2,'Weekly Summary'!18:18) -> 59346.173 | D16: =SUMIF('Weekly Summary'!$2:$2,D$2,'Weekly Summary'!18:18) -> 54550.123 | E16: =SUMIF('Weekly Summary'!$2:$2,E$2,'Weekly Summary'!18:18) -> 40912.593 | F16: =SUMIF('Weekly Summary'!$2:$2,F$2,'Weekly Summary'!18:18) -> 87938.054 | G16: =SUMIF('Weekly Summary'!$2:$2,G$2,'Weekly Summary'!18:18) -> 90311.111 | H16: =SUMIF('Weekly Summary'!$2:$2,H$2,'Weekly Summary'!18:18) -> 37910.123 | I16: =SUMIF('Weekly Summary'!$2:$2,I$2,'Weekly Summary'!18:18) -> 0 | ... K16: =SUMIF('Weekly Summary'!$2:$2,K$2,'Weekly Summary'!18:18) -> 0 | M16: =SUM(C16:K16) -> 370968.18 | N16: =+M16/SUM(M16:M17) -> 0.90260813
A17: Waste Pcs Packing | B17: =SUMIF('Weekly Summary'!$2:$2,B$2,'Weekly Summary'!19:19) -> 0 | C17: =SUMIF('Weekly Summary'!$2:$2,C$2,'Weekly Summary'!19:19) -> 0 | D17: =SUMIF('Weekly Summary'!$2:$2,D$2,'Weekly Summary'!19:19) -> 3950.6173 | E17: =SUMIF('Weekly Summary'!$2:$2,E$2,'Weekly Summary'!19:19) -> 4456.2963 | F17: =SUMIF('Weekly Summary'!$2:$2,F$2,'Weekly Summary'!19:19) -> 13921.975 | G17: =SUMIF('Weekly Summary'!$2:$2,G$2,'Weekly Summary'!19:19) -> 11093.333 | H17: =SUMIF('Weekly Summary'!$2:$2,H$2,'Weekly Summary'!19:19) -> 6605.4321 | I17: =SUMIF('Weekly Summary'!$2:$2,I$2,'Weekly Summary'!19:19) -> 0 | ... K17: =SUMIF('Weekly Summary'!$2:$2,K$2,'Weekly Summary'!19:19) -> 0 | M17: =SUM(C17:K17) -> 40027.654 | N17: =+M17/SUM(M16:M17) -> 0.097391874
A18: Waste % (v Produced) | B18: =IFERROR(SUM(B16:B17)/B7,"") -> 0 | C18: =IFERROR(SUM(C16:C17)/C7,"") -> 0.05285193 | D18: =IFERROR(SUM(D16:D17)/D7,"") -> 0.064404429 | E18: =IFERROR(SUM(E16:E17)/E7,"") -> 0.044261441 | F18: =IFERROR(SUM(F16:F17)/F7,"") -> 0.093236062 | G18: =IFERROR(SUM(G16:G17)/G7,"") -> 0.094487302 | H18: =IFERROR(SUM(H16:H17)/H7,"") -> 0.096566971 | I18: =IFERROR(SUM(I16:I17)/I7,"") | ... K18: =IFERROR(SUM(K16:K17)/K7,"") | L18: =+IFERROR(L16/L8,"") | M18: =IFERROR(SUM(M16:M17)/M7,"") -> 0.072321303
A20: Bao Ramp Plan | B20: =SUMIF('Weekly Summary'!$2:$2,B$2,'Weekly Summary'!22:22) -> 0 | C20: =SUMIF('Weekly Summary'!$2:$2,C$2,'Weekly Summary'!22:22) -> 311107.5 | D20: =SUMIF('Weekly Summary'!$2:$2,D$2,'Weekly Summary'!22:22) -> 493762.5 | E20: =SUMIF('Weekly Summary'!$2:$2,E$2,'Weekly Summary'!22:22) -> 1287000 | F20: =SUMIF('Weekly Summary'!$2:$2,F$2,'Weekly Summary'!22:22) -> 2200770 | G20: =SUMIF('Weekly Summary'!$2:$2,G$2,'Weekly Summary'!22:22) -> 2316600 | H20: =SUMIF('Weekly Summary'!$2:$2,H$2,'Weekly Summary'!22:22) -> 542953.12 | I20: =SUMIF('Weekly Summary'!$2:$2,I$2,'Weekly Summary'!22:22) -> 0 | ... K20: =SUMIF('Weekly Summary'!$2:$2,K$2,'Weekly Summary'!22:22) -> 0 | M20: =SUM(B20:L20) -> 7152193.1
A21: New Bao Plant Plan | B21: =SUMIF('Weekly Summary'!$2:$2,B$2,'Weekly Summary'!23:23) -> 0 | C21: =SUMIF('Weekly Summary'!$2:$2,C$2,'Weekly Summary'!23:23) -> 0 | D21: =SUMIF('Weekly Summary'!$2:$2,D$2,'Weekly Summary'!23:23) -> 0 | E21: =SUMIF('Weekly Summary'!$2:$2,E$2,'Weekly Summary'!23:23) -> 0 | F21: =SUMIF('Weekly Summary'!$2:$2,F$2,'Weekly Summary'!23:23) -> 0 | G21: =SUMIF('Weekly Summary'!$2:$2,G$2,'Weekly Summary'!23:23) -> 210000 | H21: =SUMIF('Weekly Summary'!$2:$2,H$2,'Weekly Summary'!23:23) -> 1350000 | I21: =SUMIF('Weekly Summary'!$2:$2,I$2,'Weekly Summary'!23:23) -> 1875000 | ... K21: =SUMIF('Weekly Summary'!$2:$2,K$2,'Weekly Summary'!23:23) -> 1350000 | M21: =SUM(C21:L21) -> 6135000
A23: Bao Produced | B23: =SUMIF('Weekly Summary'!$2:$2,B$2,'Weekly Summary'!25:25) -> 0 | C23: =SUMIF('Weekly Summary'!$2:$2,C$2,'Weekly Summary'!25:25) -> 0 | D23: =SUMIF('Weekly Summary'!$2:$2,D$2,'Weekly Summary'!25:25) -> 92130.4 | E23: =SUMIF('Weekly Summary'!$2:$2,E$2,'Weekly Summary'!25:25) -> 95424 | F23: =SUMIF('Weekly Summary'!$2:$2,F$2,'Weekly Summary'!25:25) -> 317158.5 | G23: =SUMIF('Weekly Summary'!$2:$2,G$2,'Weekly Summary'!25:25) -> 507382.3 | H23: =SUMIF('Weekly Summary'!$2:$2,H$2,'Weekly Summary'!25:25) -> 95164.6 | I23: =SUMIF('Weekly Summary'!$2:$2,I$2,'Weekly Summary'!25:25) -> 0 | ... K23: =SUMIF('Weekly Summary'!$2:$2,K$2,'Weekly Summary'!25:25) -> 0 | M23: =SUM(C23:L23) -> 1107259.8
A24: Bao Packed | B24: =SUMIF('Weekly Summary'!$2:$2,B$2,'Weekly Summary'!26:26) -> 0 | C24: =SUMIF('Weekly Summary'!$2:$2,C$2,'Weekly Summary'!26:26) -> 0 | D24: =SUMIF('Weekly Summary'!$2:$2,D$2,'Weekly Summary'!26:26) -> 35152 | E24: =SUMIF('Weekly Summary'!$2:$2,E$2,'Weekly Summary'!26:26) -> 86600 | F24: =SUMIF('Weekly Summary'!$2:$2,F$2,'Weekly Summary'!26:26) -> 267869 | G24: =SUMIF('Weekly Summary'!$2:$2,G$2,'Weekly Summary'!26:26) -> 393402 | H24: =SUMIF('Weekly Summary'!$2:$2,H$2,'Weekly Summary'!26:26) -> 42104 | I24: =SUMIF('Weekly Summary'!$2:$2,I$2,'Weekly Summary'!26:26) -> 0 | ... K24: =SUMIF('Weekly Summary'!$2:$2,K$2,'Weekly Summary'!26:26) -> 0 | M24: =SUM(C24:L24) -> 825127
A27: Produced v Ramp Plan | B27: =+B23-B20 -> 0 | C27: =+C23-C20 -> -311107.5 | D27: =+D23-D20 -> -401632.1 | E27: =+E23-E20 -> -1191576 | F27: =+F23-F20 -> -1883611.5 | G27: =+G23-G20 -> -1809217.7 | H27: =+H23-H20 -> -447788.53 | M27: =SUM(B27:L27) -> -6044933.3
A28: Packed v Ramp Plan | B28: =+B24-B20 -> 0 | C28: =+C24-C20 -> -311107.5 | D28: =+D24-D20 -> -458610.5 | E28: =+E24-E20 -> -1200400 | F28: =+F24-F20 -> -1932901 | G28: =+G24-G20 -> -1923198 | H28: =+H24-H20 -> -500849.12 | M28: =SUM(B28:L28) -> -6327066.1
A29: Produced v New Plant Plan | B29: =+B23-B21 -> 0 | C29: =+C23-C21 -> 0 | D29: =+D23-D21 -> 92130.4 | E29: =+E23-E21 -> 95424 | F29: =+F23-F21 -> 317158.5 | G29: =+G23-G21 -> 297382.3 | H29: =+H23-H21 -> -1254835.4 | M29: =SUM(B29:L29) -> -452740.2
A30: Packed v New Plant Plan | B30: =+B24-B21 -> 0 | C30: =+C24-C21 -> 0 | D30: =+D24-D21 -> 35152 | E30: =+E24-E21 -> 86600 | F30: =+F24-F21 -> 267869 | G30: =+G24-G21 -> 183402 | H30: =+H24-H21 -> -1307896 | M30: =SUM(B30:L30) -> -734873
A32: Waste Pcs Production | B32: =SUMIF('Weekly Summary'!$2:$2,B$2,'Weekly Summary'!34:34) -> 0 | C32: =SUMIF('Weekly Summary'!$2:$2,C$2,'Weekly Summary'!34:34) -> 0 | D32: =SUMIF('Weekly Summary'!$2:$2,D$2,'Weekly Summary'!34:34) -> 9318.4 | E32: =SUMIF('Weekly Summary'!$2:$2,E$2,'Weekly Summary'!34:34) -> 12736 | F32: =SUMIF('Weekly Summary'!$2:$2,F$2,'Weekly Summary'!34:34) -> 27520 | G32: =SUMIF('Weekly Summary'!$2:$2,G$2,'Weekly Summary'!34:34) -> 34444.8 | H32: =SUMIF('Weekly Summary'!$2:$2,H$2,'Weekly Summary'!34:34) -> 15609.6 | I32: =SUMIF('Weekly Summary'!$2:$2,I$2,'Weekly Summary'!34:34) -> 0 | ... K32: =SUMIF('Weekly Summary'!$2:$2,K$2,'Weekly Summary'!34:34) -> 0 | M32: =SUM(C32:K32) -> 99628.8 | N32: =+M32/SUM(M32:M33) -> 0.83084929
A33: Waste Pcs Packing | B33: =SUMIF('Weekly Summary'!$2:$2,B$2,'Weekly Summary'!35:35) -> 0 | C33: =SUMIF('Weekly Summary'!$2:$2,C$2,'Weekly Summary'!35:35) -> 0 | D33: =SUMIF('Weekly Summary'!$2:$2,D$2,'Weekly Summary'!35:35) -> 0 | E33: =SUMIF('Weekly Summary'!$2:$2,E$2,'Weekly Summary'!35:35) -> 332.8 | F33: =SUMIF('Weekly Summary'!$2:$2,F$2,'Weekly Summary'!35:35) -> 8705.6 | G33: =SUMIF('Weekly Summary'!$2:$2,G$2,'Weekly Summary'!35:35) -> 9881.6 | H33: =SUMIF('Weekly Summary'!$2:$2,H$2,'Weekly Summary'!35:35) -> 1363.2 | I33: =SUMIF('Weekly Summary'!$2:$2,I$2,'Weekly Summary'!35:35) -> 0 | ... K33: =SUMIF('Weekly Summary'!$2:$2,K$2,'Weekly Summary'!35:35) -> 0 | M33: =SUM(C33:K33) -> 20283.2 | N33: =+M33/SUM(M32:M33) -> 0.16915071
A34: Waste % (v Produced) | B34: =IFERROR(SUM(B32:B33)/B23,"") | C34: =IFERROR(SUM(C32:C33)/C23,"") | D34: =IFERROR(SUM(D32:D33)/D23,"") -> 0.1011436 | E34: =IFERROR(SUM(E32:E33)/E23,"") -> 0.13695506 | F34: =IFERROR(SUM(F32:F33)/F23,"") -> 0.11421923 | G34: =IFERROR(SUM(G32:G33)/G23,"") -> 0.087362921 | H34: =IFERROR(SUM(H32:H33)/H23,"") -> 0.17835203 | I34: =IFERROR(SUM(I32:I33)/I23,"") | ... K34: =IFERROR(SUM(K32:K33)/K23,"") | L34: =+IFERROR(L32/L24,"") | M34: =IFERROR(SUM(M32:M33)/M23,"") -> 0.10829617
A36: Total Pieces Packed | C36: =+C8+C24 -> 996390 | D36: =+D8+D24 -> 836152 | E36: =+E8+E24 -> 1176992 | F36: =+F8+F24 -> 1177439 | G36: =+G8+G24 -> 1260522 | H36: =+H8+H24 -> 499564 | I36: =+I8+I24 -> 0 | J36: =+J8+J24 -> 0 | K36: =+K8+K24 -> 0

Sheet Weekly Summary
A2: Month | B2: P3 | C2: P4 | D2: P4 | E2: P4 | F2: P4 | G2: P4 | H2: P5 | I2: P5 | J2: P5 | K2: P5 | L2: P6 | M2: P6 | N2: P6 | O2: P6 | P2: P7 | Q2: P7 | R2: P7 | S2: P7 | T2: P7 | U2: P8 | V2: P8 | W2: P8 | X2: P8 | Y2: P9 | Z2: P9 | AA2: P9 | AB2: P9 | AC2: P10 | AD2: P10 | AE2: P10 | AF2: P10 | AG2: P10 | AH2: P11 | AI2: P11 | AJ2: P11 | AK2: P11 | AL2: P12 | AM2: P12 | AN2: P12 | AO2: P12 | AP2: P12
A3: Week | B3: 46104 | C3: 46111 | D3: =+C3+7 -> 46118 | E3: =+D3+7 -> 46125 | F3: =+E3+7 -> 46132 | G3: =+F3+7 -> 46139 | H3: =+G3+7 -> 46146 | I3: =+H3+7 -> 46153 | J3: =+I3+7 -> 46160 | K3: =+J3+7 -> 46167 | ... AP3: =+AO3+7 -> 46384 | AR3: FY 2026
A4: Week # | B4: =+WEEKNUM(B3) -> 13 | C4: =+WEEKNUM(C3) -> 14 | D4: =+WEEKNUM(D3) -> 15 | E4: =+WEEKNUM(E3) -> 16 | F4: =+WEEKNUM(F3) -> 17 | G4: =+WEEKNUM(G3) -> 18 | H4: =+WEEKNUM(H3) -> 19 | I4: =+WEEKNUM(I3) -> 20 | ... AP4: =+WEEKNUM(AP3) -> 53
A6: SD Ramp Plan | B6: =SUMIF('Daily Summary New'!$3:$3,B$4,'Daily Summary New'!6:6) -> 0 | C6: =SUMIF('Daily Summary New'!$3:$3,C$4,'Daily Summary New'!6:6) -> 46080 | D6: =SUMIF('Daily Summary New'!$3:$3,D$4,'Daily Summary New'!6:6) -> 46080 | E6: =SUMIF('Daily Summary New'!$3:$3,E$4,'Daily Summary New'!6:6) -> 46080 | F6: =SUMIF('Daily Summary New'!$3:$3,F$4,'Daily Summary New'!6:6) -> 46080 | G6: =SUMIF('Daily Summary New'!$3:$3,G$4,'Daily Summary New'!6:6) -> 46080 | H6: =SUMIF('Daily Summary New'!$3:$3,H$4,'Daily Summary New'!6:6) -> 144000 | I6: =SUMIF('Daily Summary New'!$3:$3,I$4,'Daily Summary New'!6:6) -> 144000 | ... AP6: =SUMIF('Daily Summary New'!$3:$3,AP$4,'Daily Summary New'!6:6) -> 0 | AR6: =SUM(C6:AQ6) -> 13252205
A7: New SD Plant Plan | B7: =SUMIF('Daily Summary New'!$3:$3,B$4,'Daily Summary New'!7:7) -> 0 | C7: =SUMIF('Daily Summary New'!$3:$3,C$4,'Daily Summary New'!7:7) -> 0 | D7: =SUMIF('Daily Summary New'!$3:$3,D$4,'Daily Summary New'!7:7) -> 0 | E7: =SUMIF('Daily Summary New'!$3:$3,E$4,'Daily Summary New'!7:7) -> 0 | F7: =SUMIF('Daily Summary New'!$3:$3,F$4,'Daily Summary New'!7:7) -> 0 | G7: =SUMIF('Daily Summary New'!$3:$3,G$4,'Daily Summary New'!7:7) -> 0 | H7: =SUMIF('Daily Summary New'!$3:$3,H$4,'Daily Summary New'!7:7) -> 0 | I7: =SUMIF('Daily Summary New'!$3:$3,I$4,'Daily Summary New'!7:7) -> 0 | ... AP7: =SUMIF('Daily Summary New'!$3:$3,AP$4,'Daily Summary New'!7:7) -> 0 | AR7: =SUM(C7:AQ7) -> 11800000
A9: SD Produced | B9: =SUMIF('Daily Summary New'!$3:$3,B$4,'Daily Summary New'!9:9) -> 76320 | C9: =SUMIF('Daily Summary New'!$3:$3,C$4,'Daily Summary New'!9:9) -> 155040 | D9: =SUMIF('Daily Summary New'!$3:$3,D$4,'Daily Summary New'!9:9) -> 171840 | E9: =SUMIF('Daily Summary New'!$3:$3,E$4,'Daily Summary New'!9:9) -> 216919.01 | F9: =SUMIF('Daily Summary New'!$3:$3,F$4,'Daily Summary New'!9:9) -> 259877.04 | G9: =SUMIF('Daily Summary New'!$3:$3,G$4,'Daily Summary New'!9:9) -> 319200.12 | H9: =SUMIF('Daily Summary New'!$3:$3,H$4,'Daily Summary New'!9:9) -> 251410.37 | I9: =SUMIF('Daily Summary New'!$3:$3,I$4,'Daily Summary New'!9:9) -> 266266.17 | ... AP9: =SUMIF('Daily Summary New'!$3:$3,AP$4,'Daily Summary New'!9:9) -> 0 | AR9: =SUM(C9:AQ9) -> 5682915.2
A10: SD Packed | B10: =SUMIF('Daily Summary New'!$3:$3,B$4,'Daily Summary New'!10:10) -> 76320 | C10: =SUMIF('Daily Summary New'!$3:$3,C$4,'Daily Summary New'!10:10) -> 155040 | D10: =SUMIF('Daily Summary New'!$3:$3,D$4,'Daily Summary New'!10:10) -> 171840 | E10: =SUMIF('Daily Summary New'!$3:$3,E$4,'Daily Summary New'!10:10) -> 189960 | F10: =SUMIF('Daily Summary New'!$3:$3,F$4,'Daily Summary New'!10:10) -> 246840 | G10: =SUMIF('Daily Summary New'!$3:$3,G$4,'Daily Summary New'!10:10) -> 232710 | H10: =SUMIF('Daily Summary New'!$3:$3,H$4,'Daily Summary New'!10:10) -> 235500 | I10: =SUMIF('Daily Summary New'!$3:$3,I$4,'Daily Summary New'!10:10) -> 229320 | ... AP10: =SUMIF('Daily Summary New'!$3:$3,AP$4,'Daily Summary New'!10:10) -> 0 | AR10: =SUM(C10:AQ10) -> 5121932
A13: Produced v Ramp Plan | B13: =+B9-B6 -> 76320 | C13: =+C9-C6 -> 108960 | D13: =+D9-D6 -> 125760 | E13: =+E9-E6 -> 170839.01 | F13: =+F9-F6 -> 213797.04 | G13: =+G9-G6 -> 273120.12 | H13: =+H9-H6 -> 107410.37 | I13: =+I9-I6 -> 122266.17 | ... Z13: =+Z9-Z6 -> -393984 | AR13: =SUM(C13:AQ13) -> -446473.57
A14: Packed v Ramp Plan | B14: =+B10-B6 -> 76320 | C14: =+C10-C6 -> 108960 | D14: =+D10-D6 -> 125760 | E14: =+E10-E6 -> 143880 | F14: =+F10-F6 -> 200760 | G14: =+G10-G6 -> 186630 | H14: =+H10-H6 -> 91500 | I14: =+I10-I6 -> 85320 | ... Z14: =+Z10-Z6 -> -300624 | AR14: =SUM(C14:AQ14) -> -1007456.8
A15: Produced v New Plant Plan | U15: =+U9-U7 -> 4129.7778 | V15: =+V9-V7 -> -63036.84 | W15: =+W9-W7 -> -43112.296 | X15: =+X9-X7 -> 55226.469 | Y15: =+Y9-Y7 -> 100981.17 | Z15: =+Z9-Z7 -> -360000 | AR15: =SUM(C15:AQ15) -> -305811.72
A16: Packed v New Plant Plan | U16: =+U10-U7 -> -84800 | V16: =+V10-V7 -> -122360 | W16: =+W10-W7 -> -15340 | X16: =+X10-X7 -> -30380 | Y16: =+Y10-Y7 -> 4100 | Z16: =+Z10-Z7 -> -266640 | AR16: =SUM(C16:AQ16) -> -515420
A18: Waste Pcs Production | B18: =SUMIF('Daily Summary New'!$3:$3,B$4,'Daily Summary New'!18:18) -> 0 | C18: =SUMIF('Daily Summary New'!$3:$3,C$4,'Daily Summary New'!18:18) -> 0 | D18: =SUMIF('Daily Summary New'!$3:$3,D$4,'Daily Summary New'!18:18) -> 0 | E18: =SUMIF('Daily Summary New'!$3:$3,E$4,'Daily Summary New'!18:18) -> 26959.012 | F18: =SUMIF('Daily Summary New'!$3:$3,F$4,'Daily Summary New'!18:18) -> 13037.037 | G18: =SUMIF('Daily Summary New'!$3:$3,G$4,'Daily Summary New'!18:18) -> 19350.123 | H18: =SUMIF('Daily Summary New'!$3:$3,H$4,'Daily Summary New'!18:18) -> 25410.37 | I18: =SUMIF('Daily Summary New'!$3:$3,I$4,'Daily Summary New'!18:18) -> 19026.173 | ... AP18: =SUMIF('Daily Summary New'!$3:$3,AP$4,'Daily Summary New'!18:18) -> 0 | AR18: =SUM(C18:AP18) -> 370968.18 | AS18: =+AR18/SUM(AR18:AR19) -> 0.90260813
A19: Waste Pcs Packing | B19: =SUMIF('Daily Summary New'!$3:$3,B$4,'Daily Summary New'!19:19) -> 0 | C19: =SUMIF('Daily Summary New'!$3:$3,C$4,'Daily Summary New'!19:19) -> 0 | D19: =SUMIF('Daily Summary New'!$3:$3,D$4,'Daily Summary New'!19:19) -> 0 | E19: =SUMIF('Daily Summary New'!$3:$3,E$4,'Daily Summary New'!19:19) -> 0 | F19: =SUMIF('Daily Summary New'!$3:$3,F$4,'Daily Summary New'!19:19) -> 0 | G19: =SUMIF('Daily Summary New'!$3:$3,G$4,'Daily Summary New'!19:19) -> 0 | H19: =SUMIF('Daily Summary New'!$3:$3,H$4,'Daily Summary New'!19:19) -> 0 | I19: =SUMIF('Daily Summary New'!$3:$3,I$4,'Daily Summary New'!19:19) -> 0 | ... AP19: =SUMIF('Daily Summary New'!$3:$3,AP$4,'Daily Summary New'!19:19) -> 0 | AR19: =SUM(C19:AP19) -> 40027.654 | AS19: =+AR19/SUM(AR18:AR19) -> 0.097391874
A20: Waste % (v Produced) | B20: =IFERROR(SUM(B18:B19)/B9,"") -> 0 | C20: =IFERROR(SUM(C18:C19)/C9,"") -> 0 | D20: =IFERROR(SUM(D18:D19)/D9,"") -> 0 | E20: =IFERROR(SUM(E18:E19)/E9,"") -> 0.12428146 | F20: =IFERROR(SUM(F18:F19)/F9,"") -> 0.050166175 | G20: =IFERROR(SUM(G18:G19)/G9,"") -> 0.060620664 | H20: =IFERROR(SUM(H18:H19)/H9,"") -> 0.10107129 | I20: =IFERROR(SUM(I18:I19)/I9,"") -> 0.071455464 | ... AP20: =IFERROR(SUM(AP18:AP19)/AP9,"") | AR20: =IFERROR(SUM(AR18:AR19)/AR9,"") -> 0.072321303
A22: Bao Ramp Plan | B22: =SUMIF('Daily Summary New'!$3:$3,B$4,'Daily Summary New'!22:22) -> 0 | C22: =SUMIF('Daily Summary New'!$3:$3,C$4,'Daily Summary New'!22:22) -> 59400 | D22: =SUMIF('Daily Summary New'!$3:$3,D$4,'Daily Summary New'!22:22) -> 59400 | E22: =SUMIF('Daily Summary New'!$3:$3,E$4,'Daily Summary New'!22:22) -> 59400 | F22: =SUMIF('Daily Summary New'!$3:$3,F$4,'Daily Summary New'!22:22) -> 59400 | G22: =SUMIF('Daily Summary New'!$3:$3,G$4,'Daily Summary New'!22:22) -> 73507.5 | H22: =SUMIF('Daily Summary New'!$3:$3,H$4,'Daily Summary New'!22:22) -> 129937.5 | I22: =SUMIF('Daily Summary New'!$3:$3,I$4,'Daily Summary New'!22:22) -> 129937.5 | ... AP22: =SUMIF('Daily Summary New'!$3:$3,AP$4,'Daily Summary New'!22:22) -> 0 | AR22: =SUM(C22:AQ22) -> 7152193.1
A23: New Bao Plant Plan | B23: =SUMIF('Daily Summary New'!$3:$3,B$4,'Daily Summary New'!23:23) -> 0 | C23: =SUMIF('Daily Summary New'!$3:$3,C$4,'Daily Summary New'!23:23) -> 0 | D23: =SUMIF('Daily Summary New'!$3:$3,D$4,'Daily Summary New'!23:23) -> 0 | E23: =SUMIF('Daily Summary New'!$3:$3,E$4,'Daily Summary New'!23:23) -> 0 | F23: =SUMIF('Daily Summary New'!$3:$3,F$4,'Daily Summary New'!23:23) -> 0 | G23: =SUMIF('Daily Summary New'!$3:$3,G$4,'Daily Summary New'!23:23) -> 0 | H23: =SUMIF('Daily Summary New'!$3:$3,H$4,'Daily Summary New'!23:23) -> 0 | I23: =SUMIF('Daily Summary New'!$3:$3,I$4,'Daily Summary New'!23:23) -> 0 | ... AP23: =SUMIF('Daily Summary New'!$3:$3,AP$4,'Daily Summary New'!23:23) -> 0 | AR23: =SUM(C23:AQ23) -> 6135000
A25: Bao Produced | B25: =SUMIF('Daily Summary New'!$3:$3,B$4,'Daily Summary New'!25:25) -> 0 | C25: =SUMIF('Daily Summary New'!$3:$3,C$4,'Daily Summary New'!25:25) -> 0 | D25: =SUMIF('Daily Summary New'!$3:$3,D$4,'Daily Summary New'!25:25) -> 0 | E25: =SUMIF('Daily Summary New'!$3:$3,E$4,'Daily Summary New'!25:25) -> 0 | F25: =SUMIF('Daily Summary New'!$3:$3,F$4,'Daily Summary New'!25:25) -> 0 | G25: =SUMIF('Daily Summary New'!$3:$3,G$4,'Daily Summary New'!25:25) -> 0 | H25: =SUMIF('Daily Summary New'!$3:$3,H$4,'Daily Summary New'!25:25) -> 192 | I25: =SUMIF('Daily Summary New'!$3:$3,I$4,'Daily Summary New'!25:25) -> 18192.4 | ... AP25: =SUMIF('Daily Summary New'!$3:$3,AP$4,'Daily Summary New'!25:25) -> 0 | AR25: =SUM(C25:AQ25) -> 1107259.8
A26: Bao Packed | B26: =SUMIF('Daily Summary New'!$3:$3,B$4,'Daily Summary New'!26:26) -> 0 | C26: =SUMIF('Daily Summary New'!$3:$3,C$4,'Daily Summary New'!26:26) -> 0 | D26: =SUMIF('Daily Summary New'!$3:$3,D$4,'Daily Summary New'!26:26) -> 0 | E26: =SUMIF('Daily Summary New'!$3:$3,E$4,'Daily Summary New'!26:26) -> 0 | F26: =SUMIF('Daily Summary New'!$3:$3,F$4,'Daily Summary New'!26:26) -> 0 | G26: =SUMIF('Daily Summary New'!$3:$3,G$4,'Daily Summary New'!26:26) -> 0 | H26: =SUMIF('Daily Summary New'!$3:$3,H$4,'Daily Summary New'!26:26) -> 0 | I26: =SUMIF('Daily Summary New'!$3:$3,I$4,'Daily Summary New'!26:26) -> 0 | ... AP26: =SUMIF('Daily Summary New'!$3:$3,AP$4,'Daily Summary New'!26:26) -> 0 | AR26: =SUM(C26:AQ26) -> 825127
A29: Produced v Ramp Plan | B29: =+B25-B22 -> 0 | C29: =+C25-C22 -> -59400 | D29: =+D25-D22 -> -59400 | E29: =+E25-E22 -> -59400 | F29: =+F25-F22 -> -59400 | G29: =+G25-G22 -> -73507.5 | H29: =+H25-H22 -> -129745.5 | I29: =+I25-I22 -> -111745.1 | ... Z29: =+Z25-Z22 -> 0 | AR29: =SUM(C29:AQ29) -> -6044933.3
A30: Packed v Ramp Plan | B30: =+B26-B22 -> 0 | C30: =+C26-C22 -> -59400 | D30: =+D26-D22 -> -59400 | E30: =+E26-E22 -> -59400 | F30: =+F26-F22 -> -59400 | G30: =+G26-G22 -> -73507.5 | H30: =+H26-H22 -> -129937.5 | I30: =+I26-I22 -> -129937.5 | ... Z30: =+Z26-Z22 -> 0 | AR30: =SUM(C30:AQ30) -> -6327066.1
A31: Produced v New Plant Plan | U31: =+U25-U23 -> 163389.6 | V31: =+V25-V23 -> 139180.8 | W31: =+W25-W23 -> 53970.4 | X31: =+X25-X23 -> -59158.5 | Y31: =+Y25-Y23 -> -204835.4 | Z31: =+Z25-Z23 -> -300000 | AR31: =SUM(C31:AQ31) -> -207453.1
A32: Packed v New Plant Plan | U32: =+U26-U23 -> 99360 | V32: =+V26-V23 -> 118018 | W32: =+W26-W23 -> 53056 | X32: =+X26-X23 -> -87032 | Y32: =+Y26-Y23 -> -257896 | Z32: =+Z26-Z23 -> -300000 | AR32: =SUM(C32:AQ32) -> -374494
A34: Waste Pcs Production | B34: =SUMIF('Daily Summary New'!$3:$3,B$4,'Daily Summary New'!34:34) -> 0 | C34: =SUMIF('Daily Summary New'!$3:$3,C$4,'Daily Summary New'!34:34) -> 0 | D34: =SUMIF('Daily Summary New'!$3:$3,D$4,'Daily Summary New'!34:34) -> 0 | E34: =SUMIF('Daily Summary New'!$3:$3,E$4,'Daily Summary New'!34:34) -> 0 | F34: =SUMIF('Daily Summary New'!$3:$3,F$4,'Daily Summary New'!34:34) -> 0 | G34: =SUMIF('Daily Summary New'!$3:$3,G$4,'Daily Summary New'!34:34) -> 0 | H34: =SUMIF('Daily Summary New'!$3:$3,H$4,'Daily Summary New'!34:34) -> 192 | I34: =SUMIF('Daily Summary New'!$3:$3,I$4,'Daily Summary New'!34:34) -> 742.4 | ... AP34: =SUMIF('Daily Summary New'!$3:$3,AP$4,'Daily Summary New'!34:34) -> 0 | AR34: =SUM(C34:AP34) -> 99628.8 | AS34: =+AR34/SUM(AR34:AR35) -> 0.83084929
A35: Waste Pcs Packing | B35: =SUMIF('Daily Summary New'!$3:$3,B$4,'Daily Summary New'!35:35) -> 0 | C35: =SUMIF('Daily Summary New'!$3:$3,C$4,'Daily Summary New'!35:35) -> 0 | D35: =SUMIF('Daily Summary New'!$3:$3,D$4,'Daily Summary New'!35:35) -> 0 | E35: =SUMIF('Daily Summary New'!$3:$3,E$4,'Daily Summary New'!35:35) -> 0 | F35: =SUMIF('Daily Summary New'!$3:$3,F$4,'Daily Summary New'!35:35) -> 0 | G35: =SUMIF('Daily Summary New'!$3:$3,G$4,'Daily Summary New'!35:35) -> 0 | H35: =SUMIF('Daily Summary New'!$3:$3,H$4,'Daily Summary New'!35:35) -> 0 | I35: =SUMIF('Daily Summary New'!$3:$3,I$4,'Daily Summary New'!35:35) -> 0 | ... AP35: =SUMIF('Daily Summary New'!$3:$3,AP$4,'Daily Summary New'!35:35) -> 0 | AR35: =SUM(C35:AP35) -> 20283.2 | AS35: =+AR35/SUM(AR34:AR35) -> 0.16915071
A36: Waste % (v Produced) | B36: =IFERROR(SUM(B34:B35)/B25,"") | C36: =IFERROR(SUM(C34:C35)/C25,"") | D36: =IFERROR(SUM(D34:D35)/D25,"") | E36: =IFERROR(SUM(E34:E35)/E25,"") | F36: =IFERROR(SUM(F34:F35)/F25,"") | G36: =IFERROR(SUM(G34:G35)/G25,"") | H36: =IFERROR(SUM(H34:H35)/H25,"") -> 1 | I36: =IFERROR(SUM(I34:I35)/I25,"") -> 0.04080825 | ... AP36: =IFERROR(SUM(AP34:AP35)/AP25,"") | AR36: =IFERROR(SUM(AR34:AR35)/AR25,"") -> 0.10829617
A38: SD Backlog | Y38: ='Daily Summary New'!DM38 -> 115441.17
A39: Bao Backlog | Y39: ='Daily Summary New'!DM39 -> 34922.5
A43: Total OH
A44: Chicken SD | X44: =+X56+X68 -> 155640
A45: Pork SD | X45: =+X57+X69 -> 167700
A46: Chili Crisp SD | X46: =+X58+X70 -> 0
A47: Saucy Chicken SD | X47: =+X59+X71 -> 60000
A48: BBQ Pork Bao FS | X48: =+X60+X72 -> 38950
A49: BBQ Pork Bao 2-Pack | X49: =+X61+X73 -> 0
A50: BBQ Pork Bao 4-Pack | X50: =+X62+X74 -> 186752
A51: Teriyaki Chicken Bao 4-Pack | X51: =+X63+X75 -> 0
A52: Honey Chicken Mini Bao | X52: =+X64+X76 -> 37400
A53: Chili Crisp Mini Bao | X53: =+X65+X77 -> 33992
A55: FG OH (End Week) | C55: Cases | D55: Pieces
A56: Chicken SD | C56: =+D56/60 -> 3029 | D56: =+S56 -> 181740 | L56: =38*126*60+24*60+125*60+1032*60 -> 358140 | M56: 448620 | N56: =1792*60+(30*126*60) -> 334320 | O56: =1792*60 -> 107520 | P56: 263580 | R56: =4393*60 -> 263580 | S56: =3029*60 -> 181740 | U56: =3710*60 -> 222600 | V56: =4051*60 -> 243060 | W56: =6382*60 -> 382920 | X56: 155640
A57: Pork SD | C57: =+D57/60 -> 1217 | D57: =+S57 -> 73020 | L57: =31*126*60+123*60+110*60 -> 248340 | M57: 248340 | N57: =5381*60 -> 322860 | O57: =10289*60 -> 617340 | P57: 277140 | R57: =1343*60+3276*60 -> 277140 | S57: =1217*60 -> 73020 | U57: =2215*60 -> 132900 | V57: =1207*60 -> 72420 | W57: =1292*60 -> 77520 | X57: 167700
A58: Chili Crisp SD | C58: =+D58/60 -> 761 | D58: =+S58 -> 45660 | N58: =762*60 -> 45720 | O58: 45660 | P58: 45660 | R58: =761*60 -> 45660 | S58: =761*60 -> 45660 | U58: 0 | V58: 0 | W58: 0 | X58: 0
A59: Saucy Chicken SD | C59: =+D59/225 -> 719 | D59: =+S59+102*225 -> 161775 | P59: 0 | R59: =370*225 -> 83250 | S59: =617*225 -> 138825 | U59: 14200 | V59: 0 | W59: 0
A60: BBQ Pork Bao FS | D60: =+S60 -> 0 | L60: =43*50+21*50+180*50+73*50+100 -> 15950 | M60: =252*50 -> 12600 | N60: =406*50 -> 20300 | O60: =406*50 -> 20300 | P60: 0 | V60: =779*50 -> 38950 | W60: =779*50 -> 38950 | X60: 38950
A61: BBQ Pork Bao 2-Pack
A62: BBQ Pork Bao 4-Pack | C62: =+D62/32 -> 5838 | D62: =+S62 -> 186816 | L62: =2*32+96*32+100*32+69*32+135*32+135*32 -> 17184 | M62: =+(2+96+100+69+135+135)*32 -> 17184 | N62: =1657*32 -> 53024 | O62: =2539*32 -> 81248 | P62: 136160 | R62: =3328*32 -> 106496 | S62: =5838*32 -> 186816 | U62: =5905*32 -> 188960 | V62: =7298*32 -> 233536 | W62: =8956*32 -> 286592 | X62: 186752
A63: Teriyaki Chicken Bao 4-Pack | D63: =+S63 -> 0 | N63: =60*32 -> 1920 | O63: =60*32 -> 1920 | P63: 0
A64: Honey Chicken Mini Bao | X64: 22400
A65: Chili Crisp Mini Bao | X65: 33992
A67: Left to Pack (EOW)
A68: Chicken SD | L68: =65*15*96 -> 93600 | M68: 0 | N68: 0 | O68: 0 | P68: 0 | U68: 15037
A69: Pork SD | L69: 0 | M69: 0 | N69: 0 | O69: 0 | P69: 0 | U69: 0
A70: Chili Crisp SD | M70: 78136 | N70: 0 | O70: 0 | P70: 0 | U70: 0
A71: Saucy Chicken SD | P71: 83250 | S71: 74979 | U71: 0 | X71: 60000
A72: BBQ Pork Bao FS | L72: 0 | M72: 4000 | N72: 0 | O72: 0 | P72: 0 | U72: 0
A73: BBQ Pork Bao 2-Pack
A74: BBQ Pork Bao 4-Pack | L74: =20*15*35+(50*35) -> 12250 | M74: 20150 | N74: 0 | O74: 1632 | P74: 15000 | U74: 28829
A75: Teriyaki Chicken Bao 4-Pack | N75: 0 | O75: 0 | P75: 0 | U75: 0
A76: Honey Chicken Mini Bao | X76: 15000
A77: Chili Crisp Mini Bao

Sheet Daily Summary New
B1: =+TEXT(B4,"ddd") -> Mon | C1: =+TEXT(C4,"ddd") -> Tue | D1: =+TEXT(D4,"ddd") -> Wed | E1: =+TEXT(E4,"ddd") -> Thu | F1: =+TEXT(F4,"ddd") -> Mon | G1: =+TEXT(G4,"ddd") -> Tue | H1: =+TEXT(H4,"ddd") -> Wed | I1: =+TEXT(I4,"ddd") -> Thu | ... GK1: =+TEXT(GK4,"ddd") -> Wed
B2: 3 | C2: 3 | D2: 3 | E2: 3 | F2: 4 | G2: 4 | H2: 4 | I2: 4 | J2: 4 | K2: 4 | L2: 4 | M2: 4 | N2: 4 | O2: 4 | P2: 4 | Q2: 4 | R2: 4 | S2: 4 | T2: 4 | U2: 4 | V2: 4 | W2: 4 | X2: 4 | Y2: 4 | Z2: 4 | AA2: 4 | AB2: 4 | AC2: 4 | AD2: 5 | AE2: 5 | AF2: 5 | AG2: 5 | AH2: 5 | AI2: 5 | AJ2: 5 | AK2: 5 | AL2: 5 | AM2: 5 | AN2: 5 | AO2: 5 | AP2: 5 | AQ2: 5 | AR2: 5 | AS2: 5 | AT2: 5 | AU2: 5 | AV2: 5 | AW2: 5 | AX2: 6 | AY2: 6 | AZ2: 6 | BA2: 6 | BB2: 6 | BC2: 6 | BD2: 6 | BE2: 6 | BF2: 6 | BG2: 6 | BH2: 6 | BI2: 6 | BJ2: 6 | BK2: 6 | BL2: 6 | BM2: 6 | BN2: 6 | BO2: 6 | BP2: 6 | BQ2: 6 | BR2: 7 | BS2: 7 | BT2: 7 | BU2: 7 | BV2: 7 | BW2: 7 | BX2: 7 | BY2: 7 | BZ2: 7 | CA2: 7 | CB2: 7 | CC2: 7 | CD2: 7 | CE2: 7 | CF2: 7 | CG2: 7 | CH2: 7 | CI2: 7 | CJ2: 7 | CK2: 7 | CL2: 7 | CM2: 7 | CN2: 7 | CO2: 7 | CP2: 8 | CQ2: 8 | CR2: 8 | CS2: 8 | CT2: 8 | CU2: 8 | CV2: 8 | CW2: 8 | CX2: 8 | CY2: 8 | CZ2: 8 | DA2: 8 | DB2: 8 | DC2: 8 | DD2: 8 | DE2: 8 | DF2: 8 | DG2: 8 | DH2: 8 | DI2: 8 | DJ2: 9 | DK2: 9 | DL2: 9 | DM2: 9 | DN2: 9 | DO2: 9 | DP2: 9 | DQ2: 9 | DR2: 9 | DS2: 9 | DT2: 9 | DU2: 9 | DV2: 9 | DW2: 9 | DX2: 9 | DY2: 9 | DZ2: 9 | EA2: 9 | EB2: 9 | EC2: 10 | ED2: 10 | EE2: 10 | EF2: 10 | EG2: 10 | EH2: 10 | EI2: 10 | EJ2: 10 | EK2: 10 | EL2: 10 | EM2: 10 | EN2: 10 | EO2: 10 | EP2: 10 | EQ2: 10 | ER2: 10 | ES2: 10 | ET2: 10 | EU2: 10 | EV2: 10 | EW2: 10 | EX2: 10 | EY2: 10 | EZ2: 10 | FA2: 10 | FB2: 11 | FC2: 11 | FD2: 11 | FE2: 11 | FF2: 11 | FG2: 11 | FH2: 11 | FI2: 11 | FJ2: 11 | FK2: 11 | FL2: 11 | FM2: 11 | FN2: 11 | FO2: 11 | FP2: 11 | FQ2: 11 | FR2: 11 | FS2: 11 | FT2: 12 | FU2: 12 | FV2: 12 | FW2: 12 | FX2: 12 | FY2: 12 | FZ2: 12 | GA2: 12 | GB2: 12 | GC2: 12 | GD2: 12 | GE2: 12 | GF2: 12 | GG2: 12 | GH2: 12 | GI2: 12 | GJ2: 12 | GK2: 12
B3: =+WEEKNUM(B4) -> 13 | C3: =+WEEKNUM(C4) -> 13 | D3: =+WEEKNUM(D4) -> 13 | E3: =+WEEKNUM(E4) -> 13 | F3: =+WEEKNUM(F4) -> 14 | G3: =+WEEKNUM(G4) -> 14 | H3: =+WEEKNUM(H4) -> 14 | I3: =+WEEKNUM(I4) -> 14 | ... GK3: =+WEEKNUM(GK4) -> 52
B4: 46104 | C4: 46105 | D4: 46106 | E4: 46107 | F4: 46111 | G4: =WORKDAY.INTL(F4,1,,'Don''t Change'!$A$2:$A$7) -> 46112 | H4: =WORKDAY.INTL(G4,1,,'Don''t Change'!$A$2:$A$7) -> 46113 | I4: =WORKDAY.INTL(H4,1,,'Don''t Change'!$A$2:$A$7) -> 46114 | J4: =WORKDAY.INTL(I4,1,,'Don''t Change'!$A$2:$A$7) -> 46115 | K4: =WORKDAY.INTL(J4,1,,'Don''t Change'!$A$2:$A$7) -> 46118 | L4: =WORKDAY.INTL(K4,1,,'Don''t Change'!$A$2:$A$7) -> 46119 | M4: =WORKDAY.INTL(L4,1,,'Don''t Change'!$A$2:$A$7) -> 46120 | N4: =WORKDAY.INTL(M4,1,,'Don''t Change'!$A$2:$A$7) -> 46121 | ... GK4: =WORKDAY.INTL(GJ4,1,,'Don''t Change'!$A$2:$A$7) -> 46379
A6: SD Ramp Plan | B6: =IF(B1="Fri",0,SUMIF('Ramp Up Plan'!$3:$3,B$2,'Ramp Up Plan'!96:96)) -> 0 | C6: =IF(C1="Fri",0,SUMIF('Ramp Up Plan'!$3:$3,C$2,'Ramp Up Plan'!96:96)) -> 0 | D6: =IF(D1="Fri",0,SUMIF('Ramp Up Plan'!$3:$3,D$2,'Ramp Up Plan'!96:96)) -> 0 | E6: =IF(E1="Fri",0,SUMIF('Ramp Up Plan'!$3:$3,E$2,'Ramp Up Plan'!96:96)) -> 0 | F6: =IF(F1="Fri",0,SUMIF('Ramp Up Plan'!$3:$3,F$2,'Ramp Up Plan'!96:96)) -> 11520 | G6: =IF(G1="Fri",0,SUMIF('Ramp Up Plan'!$3:$3,G2,'Ramp Up Plan'!96:96)) -> 11520 | H6: =IF(H1="Fri",0,SUMIF('Ramp Up Plan'!$3:$3,H2,'Ramp Up Plan'!96:96)) -> 11520 | I6: =IF(I1="Fri",0,SUMIF('Ramp Up Plan'!$3:$3,I2,'Ramp Up Plan'!96:96)) -> 11520 | J6: =IF(J1="Fri",0,SUMIF('Ramp Up Plan'!$3:$3,J2,'Ramp Up Plan'!96:96)) -> 0 | K6: =IF(K1="Fri",0,SUMIF('Ramp Up Plan'!$3:$3,K2,'Ramp Up Plan'!96:96)) -> 11520 | L6: =IF(L1="Fri",0,SUMIF('Ramp Up Plan'!$3:$3,L2,'Ramp Up Plan'!96:96)) -> 11520 | M6: =IF(M1="Fri",0,SUMIF('Ramp Up Plan'!$3:$3,M2,'Ramp Up Plan'!96:96)) -> 11520 | N6: =IF(N1="Fri",0,SUMIF('Ramp Up Plan'!$3:$3,N2,'Ramp Up Plan'!96:96)) -> 11520 | ... AW6: =IF(AW1="Fri",0,SUMIF('Ramp Up Plan'!$3:$3,AW2,'Ramp Up Plan'!96:96)) -> 0 | AX6: =SUMIF('Ramp Up Plan'!$3:$3,AX2,'Ramp Up Plan'!96:96) -> 57600 | AY6: =SUMIF('Ramp Up Plan'!$3:$3,AY2,'Ramp Up Plan'!96:96) -> 57600 | AZ6: =SUMIF('Ramp Up Plan'!$3:$3,AZ2,'Ramp Up Plan'!96:96) -> 57600 | BA6: =SUMIF('Ramp Up Plan'!$3:$3,BA2,'Ramp Up Plan'!96:96) -> 57600 | BB6: =SUMIF('Ramp Up Plan'!$3:$3,BB2,'Ramp Up Plan'!96:96) -> 57600 | BC6: =SUMIF('Ramp Up Plan'!$3:$3,BC2,'Ramp Up Plan'!96:96) -> 57600 | BD6: =SUMIF('Ramp Up Plan'!$3:$3,BD2,'Ramp Up Plan'!96:96) -> 57600 | BE6: =SUMIF('Ramp Up Plan'!$3:$3,BE2,'Ramp Up Plan'!96:96) -> 57600 | ... GK6: =SUMIF('Ramp Up Plan'!$3:$3,GK2,'Ramp Up Plan'!96:96) -> 98496
A7: New SD Plant Plan | B7: =+B6 -> 0 | C7: =+C6 -> 0 | D7: =+D6 -> 0 | E7: =+E6 -> 0 | CP7: =SUMIF('New Plant SD Plan'!$A:$A,CP4,'New Plant SD Plan'!$E:$E) -> 80000 | CQ7: =SUMIF('New Plant SD Plan'!$A:$A,CQ4,'New Plant SD Plan'!$E:$E) -> 80000 | CR7: =SUMIF('New Plant SD Plan'!$A:$A,CR4,'New Plant SD Plan'!$E:$E) -> 80000 | CS7: =SUMIF('New Plant SD Plan'!$A:$A,CS4,'New Plant SD Plan'!$E:$E) -> 80000 | CT7: =SUMIF('New Plant SD Plan'!$A:$A,CT4,'New Plant SD Plan'!$E:$E) -> 0 | CU7: =SUMIF('New Plant SD Plan'!$A:$A,CU4,'New Plant SD Plan'!$E:$E) -> 80000 | CV7: =SUMIF('New Plant SD Plan'!$A:$A,CV4,'New Plant SD Plan'!$E:$E) -> 80000 | CW7: =SUMIF('New Plant SD Plan'!$A:$A,CW4,'New Plant SD Plan'!$E:$E) -> 80000 | ... GK7: =SUMIF('New Plant SD Plan'!$A:$A,GK4,'New Plant SD Plan'!$E:$E) -> 160000
A9: SD Produced | B9: =SUMIF('Raw Data - Production'!$A:$A,B$4,'Raw Data - Production'!$D:$D)+SUMIF('Raw Data - Production'!$A:$A,B$4,'Raw Data - Production'!$E:$E)+SUMIF('Raw Data - Production'!$A:$A,B$4,'Raw Data - Production'!$F:$F)+SUMIF('Raw Data - Production'!$A:$A,B4,'Raw Data - Production'!$Q:$Q) -> 10200 | C9: =SUMIF('Raw Data - Production'!$A:$A,C$4,'Raw Data - Production'!$D:$D)+SUMIF('Raw Data - Production'!$A:$A,C$4,'Raw Data - Production'!$E:$E)+SUMIF('Raw Data - Production'!$A:$A,C$4,'Raw Data - Production'!$F:$F)+SUMIF('Raw Data - Production'!$A:$A,C4,'Raw Data - Production'!$Q:$Q) -> 23340 | D9: =SUMIF('Raw Data - Production'!$A:$A,D$4,'Raw Data - Production'!$D:$D)+SUMIF('Raw Data - Production'!$A:$A,D$4,'Raw Data - Production'!$E:$E)+SUMIF('Raw Data - Production'!$A:$A,D$4,'Raw Data - Production'!$F:$F)+SUMIF('Raw Data - Production'!$A:$A,D4,'Raw Data - Production'!$Q:$Q) -> 9420 | E9: =SUMIF('Raw Data - Production'!$A:$A,E$4,'Raw Data - Production'!$D:$D)+SUMIF('Raw Data - Production'!$A:$A,E$4,'Raw Data - Production'!$E:$E)+SUMIF('Raw Data - Production'!$A:$A,E$4,'Raw Data - Production'!$F:$F)+SUMIF('Raw Data - Production'!$A:$A,E4,'Raw Data - Production'!$Q:$Q) -> 33360 | F9: =SUMIF('Raw Data - Production'!$A:$A,F$4,'Raw Data - Production'!$D:$D)+SUMIF('Raw Data - Production'!$A:$A,F$4,'Raw Data - Production'!$E:$E)+SUMIF('Raw Data - Production'!$A:$A,F$4,'Raw Data - Production'!$F:$F)+SUMIF('Raw Data - Production'!$A:$A,F4,'Raw Data - Production'!$Q:$Q) -> 34860 | G9: =SUMIF('Raw Data - Production'!$A:$A,G$4,'Raw Data - Production'!$D:$D)+SUMIF('Raw Data - Production'!$A:$A,G$4,'Raw Data - Production'!$E:$E)+SUMIF('Raw Data - Production'!$A:$A,G$4,'Raw Data - Production'!$F:$F)+SUMIF('Raw Data - Production'!$A:$A,G4,'Raw Data - Production'!$Q:$Q) -> 33480 | H9: =SUMIF('Raw Data - Production'!$A:$A,H$4,'Raw Data - Production'!$D:$D)+SUMIF('Raw Data - Production'!$A:$A,H$4,'Raw Data - Production'!$E:$E)+SUMIF('Raw Data - Production'!$A:$A,H$4,'Raw Data - Production'!$F:$F)+SUMIF('Raw Data - Production'!$A:$A,H4,'Raw Data - Production'!$Q:$Q) -> 52620 | I9: =SUMIF('Raw Data - Production'!$A:$A,I$4,'Raw Data - Production'!$D:$D)+SUMIF('Raw Data - Production'!$A:$A,I$4,'Raw Data - Production'!$E:$E)+SUMIF('Raw Data - Production'!$A:$A,I$4,'Raw Data - Production'!$F:$F)+SUMIF('Raw Data - Production'!$A:$A,I4,'Raw Data - Production'!$Q:$Q) -> 34080 | ... DL9: =SUMIF('Raw Data - Production'!$A:$A,DL$4,'Raw Data - Production'!$D:$D)+SUMIF('Raw Data - Production'!$A:$A,DL$4,'Raw Data - Production'!$E:$E)+SUMIF('Raw Data - Production'!$A:$A,DL$4,'Raw Data - Production'!$F:$F)+SUMIF('Raw Data - Production'!$A:$A,DL4,'Raw Data - Production'!$Q:$Q) -> 50850.37 | DM9: =SUMIF('Raw Data - Production'!$A:$A,DM$4,'Raw Data - Production'!$D:$D)+SUMIF('Raw Data - Production'!$A:$A,DM$4,'Raw Data - Production'!$E:$E)+SUMIF('Raw Data - Production'!$A:$A,DM$4,'Raw Data - Production'!$F:$F) -> 168387 | DN9: =SUMIF('Raw Data - Production'!$A:$A,DN$4,'Raw Data - Production'!$D:$D)+SUMIF('Raw Data - Production'!$A:$A,DN$4,'Raw Data - Production'!$E:$E)+SUMIF('Raw Data - Production'!$A:$A,DN$4,'Raw Data - Production'!$F:$F) -> 0 | DO9: =SUMIF('Raw Data - Production'!$A:$A,DO$4,'Raw Data - Production'!$D:$D)+SUMIF('Raw Data - Production'!$A:$A,DO$4,'Raw Data - Production'!$E:$E)+SUMIF('Raw Data - Production'!$A:$A,DO$4,'Raw Data - Production'!$F:$F) -> 0 | DP9: =SUMIF('Raw Data - Production'!$A:$A,DP$4,'Raw Data - Production'!$D:$D)+SUMIF('Raw Data - Production'!$A:$A,DP$4,'Raw Data - Production'!$E:$E)+SUMIF('Raw Data - Production'!$A:$A,DP$4,'Raw Data - Production'!$F:$F) -> 0 | DQ9: =SUMIF('Raw Data - Production'!$A:$A,DQ$4,'Raw Data - Production'!$D:$D)+SUMIF('Raw Data - Production'!$A:$A,DQ$4,'Raw Data - Production'!$E:$E)+SUMIF('Raw Data - Production'!$A:$A,DQ$4,'Raw Data - Production'!$F:$F) -> 0 | DR9: =SUMIF('Raw Data - Production'!$A:$A,DR$4,'Raw Data - Production'!$D:$D)+SUMIF('Raw Data - Production'!$A:$A,DR$4,'Raw Data - Production'!$E:$E)+SUMIF('Raw Data - Production'!$A:$A,DR$4,'Raw Data - Production'!$F:$F) -> 0 | DS9: =SUMIF('Raw Data - Production'!$A:$A,DS$4,'Raw Data - Production'!$D:$D)+SUMIF('Raw Data - Production'!$A:$A,DS$4,'Raw Data - Production'!$E:$E)+SUMIF('Raw Data - Production'!$A:$A,DS$4,'Raw Data - Production'!$F:$F) -> 0 | DT9: =SUMIF('Raw Data - Production'!$A:$A,DT$4,'Raw Data - Production'!$D:$D)+SUMIF('Raw Data - Production'!$A:$A,DT$4,'Raw Data - Production'!$E:$E)+SUMIF('Raw Data - Production'!$A:$A,DT$4,'Raw Data - Production'!$F:$F) -> 0 | ... GK9: =SUMIF('Raw Data - Production'!$A:$A,GK$4,'Raw Data - Production'!$D:$D)+SUMIF('Raw Data - Production'!$A:$A,GK$4,'Raw Data - Production'!$E:$E)+SUMIF('Raw Data - Production'!$A:$A,GK$4,'Raw Data - Production'!$F:$F) -> 0 | GL9: =SUM(F9:GK9) -> 5682915.2
A10: SD Packed | B10: =SUMIF('Raw Data - Packing'!$A:$A,B$4,'Raw Data - Packing'!$D:$D) -> 10200 | C10: =SUMIF('Raw Data - Packing'!$A:$A,C$4,'Raw Data - Packing'!$D:$D) -> 23340 | D10: =SUMIF('Raw Data - Packing'!$A:$A,D$4,'Raw Data - Packing'!$D:$D) -> 9420 | E10: =SUMIF('Raw Data - Packing'!$A:$A,E$4,'Raw Data - Packing'!$D:$D) -> 33360 | F10: =SUMIF('Raw Data - Packing'!$A:$A,F$4,'Raw Data - Packing'!$D:$D) -> 34860 | G10: =SUMIF('Raw Data - Packing'!$A:$A,G$4,'Raw Data - Packing'!$D:$D) -> 33480 | H10: =SUMIF('Raw Data - Packing'!$A:$A,H$4,'Raw Data - Packing'!$D:$D) -> 52620 | I10: =SUMIF('Raw Data - Packing'!$A:$A,I$4,'Raw Data - Packing'!$D:$D) -> 34080 | ... GK10: =SUMIF('Raw Data - Packing'!$A:$A,GK$4,'Raw Data - Packing'!$D:$D) -> 0 | GL10: =SUM(F10:GK10) -> 5121932
A13: Produced v Ramp Plan | B13: =+B9-B6 -> 10200 | C13: =+C9-C6 -> 23340 | D13: =+D9-D6 -> 9420 | E13: =+E9-E6 -> 33360 | F13: =+F9-F6 -> 23340 | G13: =+G9-G6 -> 21960 | H13: =+H9-H6 -> 41100 | I13: =+I9-I6 -> 22560 | ... DJ13: =+DJ9-DJ6 -> 15801.086 | GL13: =SUM(B13:GK13) -> 71130.341
A14: Packed v Ramp Plan | B14: =+B10-B6 -> 10200 | C14: =+C10-C6 -> 23340 | D14: =+D10-D6 -> 9420 | E14: =+E10-E6 -> 33360 | F14: =+F10-F6 -> 23340 | G14: =+G10-G6 -> 21960 | H14: =+H10-H6 -> 41100 | I14: =+I10-I6 -> 22560 | ... DJ14: =+DJ10-DJ6 -> -74746 | GL14: =SUM(B14:GK14) -> -576878.8
A15: Produced v New Plant Plan | CP15: =+CP9-CP7 -> -4566.5185 | CQ15: =+CQ9-CQ7 -> 18551.704 | CR15: =+CR9-CR7 -> 11701.136 | CS15: =+CS9-CS7 -> -21556.543 | CT15: =+CT9-CT7 -> 0 | CU15: =+CU9-CU7 -> -7977.0864 | CV15: =+CV9-CV7 -> 10269.63 | CW15: =+CW9-CW7 -> 14670.617 | ... DJ15: =+DJ9-DJ7 -> 114297.09 | GL15: =SUM(B15:GK15) -> 67504.198
A16: Packed v New Plant Plan | CP16: =+CP10-CP7 -> -20060 | CQ16: =+CQ10-CQ7 -> -1220 | CR16: =+CR10-CR7 -> -27080 | CS16: =+CS10-CS7 -> -36440 | CT16: =+CT10-CT7 -> 0 | CU16: =+CU10-CU7 -> -16220 | CV16: =+CV10-CV7 -> -31940 | CW16: =+CW10-CW7 -> -19520 | ... DJ16: =+DJ10-DJ7 -> 23750 | GL16: =SUM(B16:GK16) -> -229130
A18: Waste Pcs Production | B18: =SUMIF('Raw Data - Production'!$A:$A,B$4,'Raw Data - Production'!$Q:$Q) -> 0 | C18: =SUMIF('Raw Data - Production'!$A:$A,C$4,'Raw Data - Production'!$Q:$Q) -> 0 | D18: =SUMIF('Raw Data - Production'!$A:$A,D$4,'Raw Data - Production'!$Q:$Q) -> 0 | E18: =SUMIF('Raw Data - Production'!$A:$A,E$4,'Raw Data - Production'!$Q:$Q) -> 0 | F18: =SUMIF('Raw Data - Production'!$A:$A,F$4,'Raw Data - Production'!$Q:$Q) -> 0 | G18: =SUMIF('Raw Data - Production'!$A:$A,G$4,'Raw Data - Production'!$Q:$Q) -> 0 | H18: =SUMIF('Raw Data - Production'!$A:$A,H$4,'Raw Data - Production'!$Q:$Q) -> 0 | I18: =SUMIF('Raw Data - Production'!$A:$A,I$4,'Raw Data - Production'!$Q:$Q) -> 0 | ... GK18: =SUMIF('Raw Data - Production'!$A:$A,GK$4,'Raw Data - Production'!$Q:$Q) -> 0 | GL18: =SUM(F18:GK18) -> 370968.18 | GM18: =+GL18/SUM($GL$18:$GL$19) -> 0.90260813
A19: Waste Pcs Packing | B19: =+SUMIF('Raw Data - Packing'!$A:$A,B$4,'Raw Data - Packing'!$R:$R) -> 0 | C19: =+SUMIF('Raw Data - Packing'!$A:$A,C$4,'Raw Data - Packing'!$R:$R) -> 0 | D19: =+SUMIF('Raw Data - Packing'!$A:$A,D$4,'Raw Data - Packing'!$R:$R) -> 0 | E19: =+SUMIF('Raw Data - Packing'!$A:$A,E$4,'Raw Data - Packing'!$R:$R) -> 0 | F19: =+SUMIF('Raw Data - Packing'!$A:$A,F$4,'Raw Data - Packing'!$R:$R) -> 0 | G19: =+SUMIF('Raw Data - Packing'!$A:$A,G$4,'Raw Data - Packing'!$R:$R) -> 0 | H19: =+SUMIF('Raw Data - Packing'!$A:$A,H$4,'Raw Data - Packing'!$R:$R) -> 0 | I19: =+SUMIF('Raw Data - Packing'!$A:$A,I$4,'Raw Data - Packing'!$R:$R) -> 0 | ... GK19: =+SUMIF('Raw Data - Packing'!$A:$A,GK$4,'Raw Data - Packing'!$R:$R) -> 0 | GL19: =SUM(F19:GK19) -> 40027.654 | GM19: =+GL19/SUM($GL$18:$GL$19) -> 0.097391874
A20: Waste % (v Produced) | B20: =IFERROR(SUM(B18:B19)/B9,"") -> 0 | C20: =IFERROR(SUM(C18:C19)/C9,"") -> 0 | D20: =IFERROR(SUM(D18:D19)/D9,"") -> 0 | E20: =IFERROR(SUM(E18:E19)/E9,"") -> 0 | F20: =IFERROR(SUM(F18:F19)/F9,"") -> 0 | G20: =IFERROR(SUM(G18:G19)/G9,"") -> 0 | H20: =IFERROR(SUM(H18:H19)/H9,"") -> 0 | I20: =IFERROR(SUM(I18:I19)/I9,"") -> 0 | ... GL20: =IFERROR(SUM(GL18:GL19)/GL9,"") -> 0.072321303
A22: Bao Ramp Plan | B22: =IF(B15="Fri",0,SUMIF('Ramp Up Plan'!$3:$3,B$2,'Ramp Up Plan'!84:84)) -> 0 | C22: =IF(C15="Fri",0,SUMIF('Ramp Up Plan'!$3:$3,C$2,'Ramp Up Plan'!84:84)) -> 0 | D22: =IF(D15="Fri",0,SUMIF('Ramp Up Plan'!$3:$3,D$2,'Ramp Up Plan'!84:84)) -> 0 | E22: =IF(E15="Fri",0,SUMIF('Ramp Up Plan'!$3:$3,E$2,'Ramp Up Plan'!84:84)) -> 0 | F22: =IF(F15="Fri",0,SUMIF('Ramp Up Plan'!$3:$3,F$2,'Ramp Up Plan'!84:84)) -> 11880 | G22: =IF(G15="Fri",0,SUMIF('Ramp Up Plan'!$3:$3,G$2,'Ramp Up Plan'!84:84)) -> 11880 | H22: =IF(H15="Fri",0,SUMIF('Ramp Up Plan'!$3:$3,H$2,'Ramp Up Plan'!84:84)) -> 11880 | I22: =IF(I15="Fri",0,SUMIF('Ramp Up Plan'!$3:$3,I$2,'Ramp Up Plan'!84:84)) -> 11880 | ... DN22: =IF(DN15="Fri",0,SUMIF('Ramp Up Plan'!$3:$3,DN$2,'Ramp Up Plan'!84:84)) -> 108590.62
A23: New Bao Plant Plan | CM23: =SUMIF('New Plant SD Plan'!$A:$A,CM20,'New Plant SD Plan'!$E:$E) -> 0 | CN23: =SUMIF('New Plant Bao Plan'!$A:$A,CN4,'New Plant Bao Plan'!$E:$E) -> 0 | CO23: =SUMIF('New Plant Bao Plan'!$A:$A,CO4,'New Plant Bao Plan'!$E:$E) -> 0 | CP23: =SUMIF('New Plant Bao Plan'!$A:$A,CP4,'New Plant Bao Plan'!$E:$E) -> 0 | CQ23: =SUMIF('New Plant Bao Plan'!$A:$A,CQ4,'New Plant Bao Plan'!$E:$E) -> 0 | CR23: =SUMIF('New Plant Bao Plan'!$A:$A,CR4,'New Plant Bao Plan'!$E:$E) -> 0 | CS23: =SUMIF('New Plant Bao Plan'!$A:$A,CS4,'New Plant Bao Plan'!$E:$E) -> 0 | CT23: =SUMIF('New Plant Bao Plan'!$A:$A,CT4,'New Plant Bao Plan'!$E:$E) -> 0 | CU23: =SUMIF('New Plant Bao Plan'!$A:$A,CU4,'New Plant Bao Plan'!$E:$E) -> 0 | ... GK23: =SUMIF('New Plant Bao Plan'!$A:$A,GK4,'New Plant Bao Plan'!$E:$E) -> 75000 | GL23: =SUM(CM23:GK23) -> 6135000
A25: Bao Produced | B25: =SUMIF('Raw Data - Production'!$A:$A,B$4,'Raw Data - Production'!$G:$G)+SUMIF('Raw Data - Production'!$A:$A,B$4,'Raw Data - Production'!$H:$H)+SUMIF('Raw Data - Production'!$A:$A,B$4,'Raw Data - Production'!$I:$I)+SUMIF('Raw Data - Production'!$A:$A,B4,'Raw Data - Production'!$R:$R) -> 0 | C25: =SUMIF('Raw Data - Production'!$A:$A,C$4,'Raw Data - Production'!$G:$G)+SUMIF('Raw Data - Production'!$A:$A,C$4,'Raw Data - Production'!$H:$H)+SUMIF('Raw Data - Production'!$A:$A,C$4,'Raw Data - Production'!$I:$I)+SUMIF('Raw Data - Production'!$A:$A,C4,'Raw Data - Production'!$R:$R) -> 0 | D25: =SUMIF('Raw Data - Production'!$A:$A,D$4,'Raw Data - Production'!$G:$G)+SUMIF('Raw Data - Production'!$A:$A,D$4,'Raw Data - Production'!$H:$H)+SUMIF('Raw Data - Production'!$A:$A,D$4,'Raw Data - Production'!$I:$I)+SUMIF('Raw Data - Production'!$A:$A,D4,'Raw Data - Production'!$R:$R) -> 0 | E25: =SUMIF('Raw Data - Production'!$A:$A,E$4,'Raw Data - Production'!$G:$G)+SUMIF('Raw Data - Production'!$A:$A,E$4,'Raw Data - Production'!$H:$H)+SUMIF('Raw Data - Production'!$A:$A,E$4,'Raw Data - Production'!$I:$I)+SUMIF('Raw Data - Production'!$A:$A,E4,'Raw Data - Production'!$R:$R) -> 0 | F25: =SUMIF('Raw Data - Production'!$A:$A,F$4,'Raw Data - Production'!$G:$G)+SUMIF('Raw Data - Production'!$A:$A,F$4,'Raw Data - Production'!$H:$H)+SUMIF('Raw Data - Production'!$A:$A,F$4,'Raw Data - Production'!$I:$I)+SUMIF('Raw Data - Production'!$A:$A,F4,'Raw Data - Production'!$R:$R) -> 0 | G25: =SUMIF('Raw Data - Production'!$A:$A,G$4,'Raw Data - Production'!$G:$G)+SUMIF('Raw Data - Production'!$A:$A,G$4,'Raw Data - Production'!$H:$H)+SUMIF('Raw Data - Production'!$A:$A,G$4,'Raw Data - Production'!$I:$I)+SUMIF('Raw Data - Production'!$A:$A,G4,'Raw Data - Production'!$R:$R) -> 0 | H25: =SUMIF('Raw Data - Production'!$A:$A,H$4,'Raw Data - Production'!$G:$G)+SUMIF('Raw Data - Production'!$A:$A,H$4,'Raw Data - Production'!$H:$H)+SUMIF('Raw Data - Production'!$A:$A,H$4,'Raw Data - Production'!$I:$I)+SUMIF('Raw Data - Production'!$A:$A,H4,'Raw Data - Production'!$R:$R) -> 0 | I25: =SUMIF('Raw Data - Production'!$A:$A,I$4,'Raw Data - Production'!$G:$G)+SUMIF('Raw Data - Production'!$A:$A,I$4,'Raw Data - Production'!$H:$H)+SUMIF('Raw Data - Production'!$A:$A,I$4,'Raw Data - Production'!$I:$I)+SUMIF('Raw Data - Production'!$A:$A,I4,'Raw Data - Production'!$R:$R) -> 0 | ... DL25: =SUMIF('Raw Data - Production'!$A:$A,DL$4,'Raw Data - Production'!$G:$G)+SUMIF('Raw Data - Production'!$A:$A,DL$4,'Raw Data - Production'!$H:$H)+SUMIF('Raw Data - Production'!$A:$A,DL$4,'Raw Data - Production'!$I:$I)+SUMIF('Raw Data - Production'!$A:$A,DL4,'Raw Data - Production'!$R:$R) -> 1995 | DM25: =SUMIF('Raw Data - Production'!$A:$A,DM$4,'Raw Data - Production'!$G:$G)+SUMIF('Raw Data - Production'!$A:$A,DM$4,'Raw Data - Production'!$H:$H)+SUMIF('Raw Data - Production'!$A:$A,DM$4,'Raw Data - Production'!$I:$I) -> 0 | DN25: =SUMIF('Raw Data - Production'!$A:$A,DN$4,'Raw Data - Production'!$G:$G)+SUMIF('Raw Data - Production'!$A:$A,DN$4,'Raw Data - Production'!$H:$H)+SUMIF('Raw Data - Production'!$A:$A,DN$4,'Raw Data - Production'!$I:$I) -> 0 | DO25: =SUMIF('Raw Data - Production'!$A:$A,DO$4,'Raw Data - Production'!$G:$G)+SUMIF('Raw Data - Production'!$A:$A,DO$4,'Raw Data - Production'!$H:$H)+SUMIF('Raw Data - Production'!$A:$A,DO$4,'Raw Data - Production'!$I:$I) -> 0 | DP25: =SUMIF('Raw Data - Production'!$A:$A,DP$4,'Raw Data - Production'!$G:$G)+SUMIF('Raw Data - Production'!$A:$A,DP$4,'Raw Data - Production'!$H:$H)+SUMIF('Raw Data - Production'!$A:$A,DP$4,'Raw Data - Production'!$I:$I) -> 0 | DQ25: =SUMIF('Raw Data - Production'!$A:$A,DQ$4,'Raw Data - Production'!$G:$G)+SUMIF('Raw Data - Production'!$A:$A,DQ$4,'Raw Data - Production'!$H:$H)+SUMIF('Raw Data - Production'!$A:$A,DQ$4,'Raw Data - Production'!$I:$I) -> 0 | DR25: =SUMIF('Raw Data - Production'!$A:$A,DR$4,'Raw Data - Production'!$G:$G)+SUMIF('Raw Data - Production'!$A:$A,DR$4,'Raw Data - Production'!$H:$H)+SUMIF('Raw Data - Production'!$A:$A,DR$4,'Raw Data - Production'!$I:$I) -> 0 | DS25: =SUMIF('Raw Data - Production'!$A:$A,DS$4,'Raw Data - Production'!$G:$G)+SUMIF('Raw Data - Production'!$A:$A,DS$4,'Raw Data - Production'!$H:$H)+SUMIF('Raw Data - Production'!$A:$A,DS$4,'Raw Data - Production'!$I:$I) -> 0 | DT25: =SUMIF('Raw Data - Production'!$A:$A,DT$4,'Raw Data - Production'!$G:$G)+SUMIF('Raw Data - Production'!$A:$A,DT$4,'Raw Data - Production'!$H:$H)+SUMIF('Raw Data - Production'!$A:$A,DT$4,'Raw Data - Production'!$I:$I) -> 0 | ... GK25: =SUMIF('Raw Data - Production'!$A:$A,GK$4,'Raw Data - Production'!$G:$G)+SUMIF('Raw Data - Production'!$A:$A,GK$4,'Raw Data - Production'!$H:$H)+SUMIF('Raw Data - Production'!$A:$A,GK$4,'Raw Data - Production'!$I:$I) -> 0 | GL25: =SUM(F25:GK25) -> 1107259.8
A26: Bao Packed | B26: =SUMIF('Raw Data - Packing'!$A:$A,B4,'Raw Data - Packing'!$F:$F) -> 0 | C26: =SUMIF('Raw Data - Packing'!$A:$A,C4,'Raw Data - Packing'!$F:$F) -> 0 | D26: =SUMIF('Raw Data - Packing'!$A:$A,D4,'Raw Data - Packing'!$F:$F) -> 0 | E26: =SUMIF('Raw Data - Packing'!$A:$A,E4,'Raw Data - Packing'!$F:$F) -> 0 | F26: =SUMIF('Raw Data - Packing'!$A:$A,F4,'Raw Data - Packing'!$F:$F) -> 0 | G26: =SUMIF('Raw Data - Packing'!$A:$A,G4,'Raw Data - Packing'!$F:$F) -> 0 | H26: =SUMIF('Raw Data - Packing'!$A:$A,H4,'Raw Data - Packing'!$F:$F) -> 0 | I26: =SUMIF('Raw Data - Packing'!$A:$A,I4,'Raw Data - Packing'!$F:$F) -> 0 | ... GK26: =SUMIF('Raw Data - Packing'!$A:$A,GK4,'Raw Data - Packing'!$F:$F) -> 0 | GL26: =SUM(F26:GK26) -> 825127
A29: Produced v Ramp Plan | B29: =+B25-B22 -> 0 | C29: =+C25-C22 -> 0 | D29: =+D25-D22 -> 0 | E29: =+E25-E22 -> 0 | F29: =+F25-F22 -> -11880 | G29: =+G25-G22 -> -11880 | H29: =+H25-H22 -> -11880 | I29: =+I25-I22 -> -11880 | ... DJ29: =+DJ25-DJ22 -> -58644.625 | GL29: =SUM(B29:GK29) -> -5655789.4
A30: Packed v Ramp Plan | B30: =+B26-B22 -> 0 | C30: =+C26-C22 -> 0 | D30: =+D26-D22 -> 0 | E30: =+E26-E22 -> 0 | F30: =+F26-F22 -> -11880 | G30: =+G26-G22 -> -11880 | H30: =+H26-H22 -> -11880 | I30: =+I26-I22 -> -11880 | ... DJ30: =+DJ26-DJ22 -> -97390.625 | GL30: =SUM(B30:GK30) -> -5923607.6
A31: Produced v New Plant Plan | CP31: =+CP25-CP23 -> 49680.2 | CQ31: =+CQ25-CQ23 -> 37224 | CR31: =+CR25-CR23 -> 38270 | CS31: =+CS25-CS23 -> 38215.4 | CT31: =+CT25-CT23 -> 0 | CU31: =+CU25-CU23 -> 51938 | CV31: =+CV25-CV23 -> 45468.2 | CW31: =+CW25-CW23 -> 41774.6 | ... DJ31: =+DJ25-DJ23 -> -25054 | GL31: =SUM(B31:GK31) -> 272328.3
A32: Packed v New Plant Plan | CP32: =+CP26-CP23 -> 21600 | CQ32: =+CQ26-CQ23 -> 25920 | CR32: =+CR26-CR23 -> 21600 | CS32: =+CS26-CS23 -> 30240 | CT32: =+CT26-CT23 -> 0 | CU32: =+CU26-CU23 -> 30336 | CV32: =+CV26-CV23 -> 40550 | CW32: =+CW26-CW23 -> 28800 | ... DJ32: =+DJ26-DJ23 -> -63800 | GL32: =SUM(B32:GK32) -> 119602
A34: Waste Pcs Production | B34: =SUMIF('Raw Data - Production'!$A:$A,B$4,'Raw Data - Production'!$R:$R) -> 0 | C34: =SUMIF('Raw Data - Production'!$A:$A,C$4,'Raw Data - Production'!$R:$R) -> 0 | D34: =SUMIF('Raw Data - Production'!$A:$A,D$4,'Raw Data - Production'!$R:$R) -> 0 | E34: =SUMIF('Raw Data - Production'!$A:$A,E$4,'Raw Data - Production'!$R:$R) -> 0 | F34: =SUMIF('Raw Data - Production'!$A:$A,F$4,'Raw Data - Production'!$R:$R) -> 0 | G34: =SUMIF('Raw Data - Production'!$A:$A,G$4,'Raw Data - Production'!$R:$R) -> 0 | H34: =SUMIF('Raw Data - Production'!$A:$A,H$4,'Raw Data - Production'!$R:$R) -> 0 | I34: =SUMIF('Raw Data - Production'!$A:$A,I$4,'Raw Data - Production'!$R:$R) -> 0 | ... GK34: =SUMIF('Raw Data - Production'!$A:$A,GK$4,'Raw Data - Production'!$R:$R) -> 0 | GL34: =SUM(F34:GK34) -> 99628.8 | GM34: =+GL34/SUM($GL$34:$GL$35) -> 0.83084929
A35: Waste Pcs Packing | B35: =+SUMIF('Raw Data - Packing'!$A:$A,B$4,'Raw Data - Packing'!$S:$S) -> 0 | C35: =+SUMIF('Raw Data - Packing'!$A:$A,C$4,'Raw Data - Packing'!$S:$S) -> 0 | D35: =+SUMIF('Raw Data - Packing'!$A:$A,D$4,'Raw Data - Packing'!$S:$S) -> 0 | E35: =+SUMIF('Raw Data - Packing'!$A:$A,E$4,'Raw Data - Packing'!$S:$S) -> 0 | F35: =+SUMIF('Raw Data - Packing'!$A:$A,F$4,'Raw Data - Packing'!$S:$S) -> 0 | G35: =+SUMIF('Raw Data - Packing'!$A:$A,G$4,'Raw Data - Packing'!$S:$S) -> 0 | H35: =+SUMIF('Raw Data - Packing'!$A:$A,H$4,'Raw Data - Packing'!$S:$S) -> 0 | I35: =+SUMIF('Raw Data - Packing'!$A:$A,I$4,'Raw Data - Packing'!$S:$S) -> 0 | ... GK35: =+SUMIF('Raw Data - Packing'!$A:$A,GK$4,'Raw Data - Packing'!$S:$S) -> 0 | GL35: =SUM(F35:GK35) -> 20283.2 | GM35: =+GL35/SUM($GL$34:$GL$35) -> 0.16915071
A36: Waste % (v Produced) | B36: =IFERROR(SUM(B34:B35)/B25,"") | C36: =IFERROR(SUM(C34:C35)/C25,"") | D36: =IFERROR(SUM(D34:D35)/D25,"") | E36: =IFERROR(SUM(E34:E35)/E25,"") | F36: =IFERROR(SUM(F34:F35)/F25,"") | G36: =IFERROR(SUM(G34:G35)/G25,"") | H36: =IFERROR(SUM(H34:H35)/H25,"") | I36: =IFERROR(SUM(I34:I35)/I25,"") | ... GL36: =IFERROR(SUM(GL34:GL35)/GL25,"") -> 0.10829617
A38: SD To Pack | DL38: =SUMIF('Daily Summary Old'!$A:$A,DL4,'Daily Summary Old'!$L:$L) -> 187118.12 | DM38: =+DL38+DM9-DM10-DM18-DM19 -> 115441.17 | DN38: =+DM38+DN9-DN10-DN18-DN19 -> 115441.17 | DO38: =+DN38+DO9-DO10-DO18-DO19 -> 20848.58
A39: Bao To Pack | DL39: =SUMIF('Daily Summary Old'!$A:$A,DL4,'Daily Summary Old'!$M:$M) -> 42482.5 | DM39: =+DL39-DM25-DM26-DM34-DM35 -> 34922.5 | DN39: =+DM39-DN25-DN26-DN34-DN35 -> 34922.5 | DO39: =+DN39-DO25-DO26-DO34-DO35 -> 34922.5

Sheet Raw Data - Production
D1: # Individual Pieces Formed | K1: Total Waste in #'s | Q1: Pieces SD | R1: Pieces Bao | S1: SD % | T1: Bao % | U1: Downtime Tracker in Minutes | AF1: Daily Goal #
A2: Date | B2: Week # | C2: Month | D2: JBM #1 | E2: JBM #2 | F2: JBM #3 | G2: Rheon #1 | H2: Rheon #2 | I2: Rheon #3 | K2: JBM #1 | L2: JBM #2 | M2: JBM #3 | N2: Rheon #1 | O2: Rheon #2 | P2: Rheon #3 | U2: JBM #1 | V2: JBM #2 | W2: JBM #3 | X2: Rheon #1 | Y2: Rheon #2 | Z2: Rheon #3 | AA2: PFM #1 | AB2: PFM #2 | AC2: Adco #1 | AD2: Adco #2 | AF2: JBM | AG2: Rheon
A3: 46104 | B3: =+WEEKNUM(A3) -> 13 | C3: =+TEXT(A3,"mmmm") -> March | D3: =170*30 -> 5100 | E3: =+D3 -> 5100 | Q3: =+SUM(K3:M3)/Weights!$B$2 -> 0 | R3: =+SUM(N3:O3)/Weights!$B$4 -> 0 | S3: =IFERROR(Q3/SUM(D3:F3),"") -> 0
A4: 46105 | B4: =+WEEKNUM(A4) -> 13 | C4: =+TEXT(A4,"mmmm") -> March | D4: =389*30 -> 11670 | E4: =+D4 -> 11670 | Q4: =+SUM(K4:M4)/Weights!$B$2 -> 0 | R4: =+SUM(N4:O4)/Weights!$B$4 -> 0 | S4: =IFERROR(Q4/SUM(D4:F4),"") -> 0
A5: 46106 | B5: =+WEEKNUM(A5) -> 13 | C5: =+TEXT(A5,"mmmm") -> March | D5: =157*30 -> 4710 | E5: =+D5 -> 4710 | Q5: =+SUM(K5:M5)/Weights!$B$2 -> 0 | R5: =+SUM(N5:O5)/Weights!$B$4 -> 0 | S5: =IFERROR(Q5/SUM(D5:F5),"") -> 0
A6: 46107 | B6: =+WEEKNUM(A6) -> 13 | C6: =+TEXT(A6,"mmmm") -> March | D6: =556*30 -> 16680 | E6: =+D6 -> 16680 | Q6: =+SUM(K6:M6)/Weights!$B$2 -> 0 | R6: =+SUM(N6:O6)/Weights!$B$4 -> 0 | S6: =IFERROR(Q6/SUM(D6:F6),"") -> 0
A7: 46111 | B7: =+WEEKNUM(A7) -> 14 | C7: =+TEXT(A7,"mmmm") -> March | D7: =581*30 -> 17430 | E7: =+D7 -> 17430 | Q7: =+SUM(K7:M7)/Weights!$B$2 -> 0 | R7: =+SUM(N7:P7)/Weights!$B$4 -> 0 | S7: =IFERROR(Q7/SUM(D7:F7),"") -> 0 | AF7: =226800/4 -> 56700 | AG7: 0
A8: 46112 | B8: =+WEEKNUM(A8) -> 14 | C8: =+TEXT(A8,"mmmm") -> March | D8: =558*30 -> 16740 | E8: =+D8 -> 16740 | Q8: =+SUM(K8:M8)/Weights!$B$2 -> 0 | R8: =+SUM(N8:P8)/Weights!$B$4 -> 0 | S8: =IFERROR(Q8/SUM(D8:F8),"") -> 0 | AF8: =226800/4 -> 56700 | AG8: 0
A9: 46113 | B9: =+WEEKNUM(A9) -> 14 | C9: =+TEXT(A9,"mmmm") -> April | D9: =877*30 -> 26310 | E9: =+D9 -> 26310 | Q9: =+SUM(K9:M9)/Weights!$B$2 -> 0 | R9: =+SUM(N9:P9)/Weights!$B$4 -> 0 | S9: =IFERROR(Q9/SUM(D9:F9),"") -> 0 | AF9: =226800/4 -> 56700 | AG9: 0
A10: 46114 | B10: =+WEEKNUM(A10) -> 14 | C10: =+TEXT(A10,"mmmm") -> April | D10: =568*30 -> 17040 | E10: =+D10 -> 17040 | Q10: =+SUM(K10:M10)/Weights!$B$2 -> 0 | R10: =+SUM(N10:P10)/Weights!$B$4 -> 0 | S10: =IFERROR(Q10/SUM(D10:F10),"") -> 0 | AF10: =226800/4 -> 56700 | AG10: 0
A11: 46118 | B11: =+WEEKNUM(A11) -> 15 | C11: =+TEXT(A11,"mmmm") -> April | D11: =537*30 -> 16110 | E11: =+D11 -> 16110 | Q11: =+SUM(K11:M11)/Weights!$B$2 -> 0 | R11: =+SUM(N11:P11)/Weights!$B$4 -> 0 | S11: =IFERROR(Q11/SUM(D11:F11),"") -> 0 | AF11: =226800/4 -> 56700 | AG11: =181440/4 -> 45360
A12: 46119 | B12: =+WEEKNUM(A12) -> 15 | C12: =+TEXT(A12,"mmmm") -> April | D12: =773*30 -> 23190 | E12: =+D12 -> 23190 | Q12: =+SUM(K12:M12)/Weights!$B$2 -> 0 | R12: =+SUM(N12:P12)/Weights!$B$4 -> 0 | S12: =IFERROR(Q12/SUM(D12:F12),"") -> 0 | T12: =IFERROR(R12/SUM(G12:I12),"") | AF12: =226800/4 -> 56700 | AG12: =181440/4 -> 45360
A13: 46120 | B13: =+WEEKNUM(A13) -> 15 | C13: =+TEXT(A13,"mmmm") -> April | D13: =787*30 -> 23610 | E13: =+D13 -> 23610 | Q13: =+SUM(K13:M13)/Weights!$B$2 -> 0 | R13: =+SUM(N13:P13)/Weights!$B$4 -> 0 | S13: =IFERROR(Q13/SUM(D13:F13),"") -> 0 | T13: =IFERROR(R13/SUM(G13:I13),"") | AF13: =226800/4 -> 56700 | AG13: =181440/4 -> 45360
A14: 46121 | B14: =+WEEKNUM(A14) -> 15 | C14: =+TEXT(A14,"mmmm") -> April | D14: =767*30 -> 23010 | E14: =+D14 -> 23010 | Q14: =+SUM(K14:M14)/Weights!$B$2 -> 0 | R14: =+SUM(N14:P14)/Weights!$B$4 -> 0 | S14: =IFERROR(Q14/SUM(D14:F14),"") -> 0 | T14: =IFERROR(R14/SUM(G14:I14),"") | AF14: =226800/4 -> 56700 | AG14: =181440/4 -> 45360
A15: 46125 | B15: =+WEEKNUM(A15) -> 16 | C15: =+TEXT(A15,"mmmm") -> April | D15: =704*30 -> 21120 | E15: =+D15 -> 21120 | Q15: =+SUM(K15:M15)/Weights!$B$2 -> 0 | R15: =+SUM(N15:P15)/Weights!$B$4 -> 0 | S15: =IFERROR(Q15/SUM(D15:F15),"") -> 0 | T15: =IFERROR(R15/SUM(G15:I15),"") | AF15: =226800/4 -> 56700 | AG15: =181440/4 -> 45360
A16: 46126 | B16: =+WEEKNUM(A16) -> 16 | C16: =+TEXT(A16,"mmmm") -> April | D16: =966*30 -> 28980 | E16: =+D16 -> 28980 | K16: 95 | L16: 95 | Q16: =+SUM(K16:M16)/Weights!$B$2 -> 3002.4691 | R16: =+SUM(N16:P16)/Weights!$B$4 -> 0 | S16: =IFERROR(Q16/SUM(D16:F16),"") -> 0.051802435 | T16: =IFERROR(R16/SUM(G16:I16),"") | AF16: =226800/4 -> 56700 | AG16: =181440/4 -> 45360
A17: 46127 | B17: =+WEEKNUM(A17) -> 16 | C17: =+TEXT(A17,"mmmm") -> April | D17: =916*30 -> 27480 | E17: =+D17 -> 27480 | K17: 758 | L17: 758 | Q17: =+SUM(K17:M17)/Weights!$B$2 -> 23956.543 | R17: =+SUM(N17:P17)/Weights!$B$4 -> 0 | S17: =IFERROR(Q17/SUM(D17:F17),"") -> 0.43589052 | T17: =IFERROR(R17/SUM(G17:I17),"") | AF17: =226800/4 -> 56700 | AG17: =181440/4 -> 45360
A18: 46128 | B18: =+WEEKNUM(A18) -> 16 | C18: =+TEXT(A18,"mmmm") -> April | D18: =580*30 -> 17400 | E18: =+D18 -> 17400 | Q18: =+SUM(K18:M18)/Weights!$B$2 -> 0 | R18: =+SUM(N18:P18)/Weights!$B$4 -> 0 | S18: =IFERROR(Q18/SUM(D18:F18),"") -> 0 | T18: =IFERROR(R18/SUM(G18:I18),"") | AF18: =226800/4 -> 56700 | AG18: =181440/4 -> 45360
A19: 46132 | B19: =+WEEKNUM(A19) -> 17 | C19: =+TEXT(A19,"mmmm") -> April | D19: =938*30 -> 28140 | E19: =+D19 -> 28140 | K19: 169 | L19: =+K19 -> 169 | Q19: =+SUM(K19:M19)/Weights!$B$2 -> 5341.2346 | R19: =+SUM(N19:P19)/Weights!$B$4 -> 0 | S19: =IFERROR(Q19/SUM(D19:F19),"") -> 0.094904665 | T19: =IFERROR(R19/SUM(G19:I19),"") | AF19: =226800/4 -> 56700 | AG19: =181440/4 -> 45360
A20: 46133 | B20: =+WEEKNUM(A20) -> 17 | C20: =+TEXT(A20,"mmmm") -> April | D20: =878*30 -> 26340 | E20: =+D20 -> 26340 | K20: 89.5 | L20: =+K20 -> 89.5 | Q20: =+SUM(K20:M20)/Weights!$B$2 -> 2828.642 | R20: =+SUM(N20:P20)/Weights!$B$4 -> 0 | S20: =IFERROR(Q20/SUM(D20:F20),"") -> 0.053694798 | T20: =IFERROR(R20/SUM(G20:I20),"") | AF20: =226800/4 -> 56700 | AG20: =181440/4 -> 45360
A21: 46134 | B21: =+WEEKNUM(A21) -> 17 | C21: =+TEXT(A21,"mmmm") -> April | D21: =1128*30 -> 33840 | E21: =+D21 -> 33840 | K21: 154 | L21: 154 | Q21: =+SUM(K21:M21)/Weights!$B$2 -> 4867.1605 | R21: =+SUM(N21:P21)/Weights!$B$4 -> 0 | S21: =IFERROR(Q21/SUM(D21:F21),"") -> 0.07191431 | T21: =IFERROR(R21/SUM(G21:I21),"") | AF21: =226800/4 -> 56700 | AG21: =181440/4 -> 45360
A22: 46135 | B22: =+WEEKNUM(A22) -> 17 | C22: =+TEXT(A22,"mmmm") -> April | D22: =1170*30 -> 35100 | E22: =+D22 -> 35100 | Q22: =+SUM(K22:M22)/Weights!$B$2 -> 0 | R22: =+SUM(N22:P22)/Weights!$B$4 -> 0 | S22: =IFERROR(Q22/SUM(D22:F22),"") -> 0 | T22: =IFERROR(R22/SUM(G22:I22),"") | AF22: =226800/4 -> 56700 | AG22: =181440/4 -> 45360
A23: 46139 | B23: =+WEEKNUM(A23) -> 18 | C23: =+TEXT(A23,"mmmm") -> April | D23: =1108*30 -> 33240 | E23: =+D23 -> 33240 | K23: 163 | L23: 163 | Q23: =+SUM(K23:M23)/Weights!$B$2 -> 5151.6049 | R23: =+SUM(N23:P23)/Weights!$B$4 -> 0 | S23: =IFERROR(Q23/SUM(D23:F23),"") -> 0.077491049 | T23: =IFERROR(R23/SUM(G23:I23),"") | AF23: =226800/4 -> 56700 | AG23: =181440/4 -> 45360
A24: 46140 | B24: =+WEEKNUM(A24) -> 18 | C24: =+TEXT(A24,"mmmm") -> April | D24: =1119*30 -> 33570 | E24: =+D24 -> 33570 | Q24: =+SUM(K24:M24)/Weights!$B$2 -> 0 | R24: =+SUM(N24:P24)/Weights!$B$4 -> 0 | S24: =IFERROR(Q24/SUM(D24:F24),"") -> 0 | T24: =IFERROR(R24/SUM(G24:I24),"") | AF24: =226800/4 -> 56700 | AG24: =181440/4 -> 45360
A25: 46141 | B25: =+WEEKNUM(A25) -> 18 | C25: =+TEXT(A25,"mmmm") -> April | D25: =1266*30 -> 37980 | E25: =+D25 -> 37980 | K25: =538.5/2 -> 269.25 | L25: =+K25 -> 269.25 | Q25: =+SUM(K25:M25)/Weights!$B$2 -> 8509.6296 | R25: =+SUM(N25:P25)/Weights!$B$4 -> 0 | S25: =IFERROR(Q25/SUM(D25:F25),"") -> 0.11202777 | T25: =IFERROR(R25/SUM(G25:I25),"") | AF25: =226800/4 -> 56700 | AG25: =181440/4 -> 45360
A26: 46142 | B26: =+WEEKNUM(A26) -> 18 | C26: =+TEXT(A26,"mmmm") -> April | D26: =1504.5*30 -> 45135 | E26: =+D26 -> 45135 | K26: 180 | L26: 180 | Q26: =+SUM(K26:M26)/Weights!$B$2 -> 5688.8889 | R26: =+SUM(N26:P26)/Weights!$B$4 -> 0 | S26: =IFERROR(Q26/SUM(D26:F26),"") -> 0.063020814 | T26: =IFERROR(R26/SUM(G26:I26),"") | AF26: =226800/4 -> 56700 | AG26: =181440/4 -> 45360
A27: 46146 | B27: =+WEEKNUM(A27) -> 19 | C27: =+TEXT(A27,"mmmm") -> May | D27: 0 | E27: =+D27 -> 0 | K27: 491 | L27: =+K27 -> 491 | Q27: =+SUM(K27:M27)/Weights!$B$2 -> 15518.025 | R27: =+SUM(N27:P27)/Weights!$B$4 -> 0 | S27: =IFERROR(Q27/SUM(D27:F27),"") | T27: =IFERROR(R27/SUM(G27:I27),"") | AF27: =288000/4 -> 72000 | AG27: =33120/4 -> 8280
A28: 46147 | B28: =+WEEKNUM(A28) -> 19 | C28: =+TEXT(A28,"mmmm") -> May | D28: =50400/2 -> 25200 | E28: =+D28 -> 25200 | K28: 140 | L28: 140 | Q28: =+SUM(K28:M28)/Weights!$B$2 -> 4424.6914 | R28: =+SUM(N28:P28)/Weights!$B$4 -> 0 | S28: =IFERROR(Q28/SUM(D28:F28),"") -> 0.087791495 | T28: =IFERROR(R28/SUM(G28:I28),"") | AF28: =288000/4 -> 72000 | AG28: =33120/4 -> 8280
A29: 46148 | B29: =+WEEKNUM(A29) -> 19 | C29: =+TEXT(A29,"mmmm") -> May | D29: =72000/2 -> 36000 | E29: =+D29 -> 36000 | K29: 13 | L29: 13 | Q29: =+SUM(K29:M29)/Weights!$B$2 -> 410.8642 | R29: =+SUM(N29:P29)/Weights!$B$4 -> 0 | S29: =IFERROR(Q29/SUM(D29:F29),"") -> 0.0057064472 | T29: =IFERROR(R29/SUM(G29:I29),"") | AF29: =288000/4 -> 72000 | AG29: =33120/4 -> 8280
A30: 46149 | B30: =+WEEKNUM(A30) -> 19 | C30: =+TEXT(A30,"mmmm") -> May | D30: =103600/2 -> 51800 | E30: =+D30 -> 51800 | K30: 160 | L30: 160 | O30: 30 | Q30: =+SUM(K30:M30)/Weights!$B$2 -> 5056.7901 | R30: =+SUM(N30:P30)/Weights!$B$4 -> 192 | S30: =IFERROR(Q30/SUM(D30:F30),"") -> 0.048810715 | T30: =IFERROR(R30/SUM(G30:I30),"") | AF30: =288000/4 -> 72000 | AG30: =33120/4 -> 8280
A31: 46153 | B31: =+WEEKNUM(A31) -> 20 | C31: =+TEXT(A31,"mmmm") -> May | D31: =48960/2 -> 24480 | E31: =+D31 -> 24480 | K31: 45 | L31: 45 | Q31: =+SUM(K31:M31)/Weights!$B$2 -> 1422.2222 | R31: =+SUM(N31:P31)/Weights!$B$4 -> 0 | S31: =IFERROR(Q31/SUM(D31:F31),"") -> 0.029048656 | T31: =IFERROR(R31/SUM(G31:I31),"") | AF31: =360000/4 -> 90000 | AG31: =34560/4 -> 8640
A32: 46154 | B32: =+WEEKNUM(A32) -> 20 | C32: =+TEXT(A32,"mmmm") -> May | D32: =64320/2 -> 32160 | E32: =+D32 -> 32160 | H32: 3800 | K32: 75 | L32: 75 | O32: 50 | Q32: =+SUM(K32:M32)/Weights!$B$2 -> 2370.3704 | R32: =+SUM(N32:P32)/Weights!$B$4 -> 320 | S32: =IFERROR(Q32/SUM(D32:F32),"") -> 0.036852773 | T32: =IFERROR(R32/SUM(G32:I32),"") -> 0.084210526 | AF32: =360000/4 -> 90000 | AG32: =34560/4 -> 8640
A33: 46155 | B33: =+WEEKNUM(A33) -> 20 | C33: =+TEXT(A33,"mmmm") -> May | D33: =68700/2 -> 34350 | E33: =+D33 -> 34350 | H33: 13650 | K33: 130 | L33: 130 | O33: 66 | Q33: =+SUM(K33:M33)/Weights!$B$2 -> 4108.642 | R33: =+SUM(N33:P33)/Weights!$B$4 -> 422.4 | S33: =IFERROR(Q33/SUM(D33:F33),"") -> 0.05980556 | T33: =IFERROR(R33/SUM(G33:I33),"") -> 0.030945055 | AF33: =360000/4 -> 90000 | AG33: =34560/4 -> 8640
A34: 46156 | B34: =+WEEKNUM(A34) -> 20 | C34: =+TEXT(A34,"mmmm") -> May | D34: =65260/2 -> 32630 | E34: =+D34 -> 32630 | K34: 352 | L34: 352 | Q34: =+SUM(K34:M34)/Weights!$B$2 -> 11124.938 | R34: =+SUM(N34:P34)/Weights!$B$4 -> 0 | S34: =IFERROR(Q34/SUM(D34:F34),"") -> 0.17047101 | T34: =IFERROR(R34/SUM(G34:I34),"") | AF34: =360000/4 -> 90000 | AG34: =34560/4 -> 8640
A35: 46160 | B35: =+WEEKNUM(A35) -> 21 | C35: =+TEXT(A35,"mmmm") -> May | D35: =22*15*96 -> 31680 | E35: =21*15*96 -> 30240 | H35: =21*13*35 -> 9555 | K35: 70 | L35: 90 | O35: 152 | Q35: =+SUM(K35:M35)/Weights!$B$2 -> 2528.3951 | R35: =+SUM(N35:P35)/Weights!$B$4 -> 972.8 | S35: =IFERROR(Q35/SUM(D35:F35),"") -> 0.040833254 | T35: =IFERROR(R35/SUM(G35:I35),"") -> 0.10181057 | AF35: =360000/4 -> 90000 | AG35: =34560/4 -> 8640
A36: =WORKDAY.INTL(A35,1,,'Don''t Change'!$A$2:$A$7) -> 46161 | B36: =+WEEKNUM(A36) -> 21 | C36: =+TEXT(A36,"mmmm") -> May | D36: =29*15*96+26*96+14*96 -> 45600 | E36: =15*15*96+12*96 -> 22752 | H36: =15*13*35 -> 6825 | K36: 50 | L36: 30 | Q36: =+SUM(K36:M36)/Weights!$B$2 -> 1264.1975 | R36: =+SUM(N36:P36)/Weights!$B$4 -> 0 | S36: =IFERROR(Q36/SUM(D36:F36),"") -> 0.018495399 | T36: =IFERROR(R36/SUM(G36:I36),"") -> 0 | U36: =24+23 -> 47 | V36: =28+38 -> 66 | Y36: 15 | AF36: =360000/4 -> 90000 | AG36: =34560/4 -> 8640
A37: =WORKDAY.INTL(A36,1,,'Don''t Change'!$A$2:$A$7) -> 46162 | B37: =+WEEKNUM(A37) -> 21 | C37: =+TEXT(A37,"mmmm") -> May | D37: =28*15*96+13*96+5*96 -> 42048 | E37: =17*15*96 -> 24480 | H37: =13*13*35+30*35+14*12*35+14.5*12*35 -> 18935 | K37: 50 | L37: 30 | O37: =138+128+30 -> 296 | Q37: =+SUM(K37:M37)/Weights!$B$2 -> 1264.1975 | R37: =+SUM(N37:P37)/Weights!$B$4 -> 1894.4 | S37: =IFERROR(Q37/SUM(D37:F37),"") -> 0.019002488 | T37: =IFERROR(R37/SUM(G37:I37),"") -> 0.10004753 | U37: 42 | V37: 42 | AF37: =360000/4 -> 90000 | AG37: =34560/4 -> 8640
A38: =WORKDAY.INTL(A37,1,,'Don''t Change'!$A$2:$A$7) -> 46163 | B38: =+WEEKNUM(A38) -> 21 | C38: =+TEXT(A38,"mmmm") -> May | D38: =26*15*96+4*15*72 -> 41760 | E38: =6*15*96+12*72 -> 9504 | G38: =14*35+30*35 -> 1540 | H38: =3*14*35+11*15*35+20*35 -> 7945 | N38: 90 | O38: 504 | Q38: =+SUM(K38:M38)/Weights!$B$2 -> 0 | R38: =+SUM(N38:P38)/Weights!$B$4 -> 3801.6 | S38: =IFERROR(Q38/SUM(D38:F38),"") -> 0 | T38: =IFERROR(R38/SUM(G38:I38),"") -> 0.40080127 | U38: 75 | Y38: 18 | AF38: =360000/4 -> 90000 | AG38: =34560/4 -> 8640
A39: =WORKDAY.INTL(A38,1,,'Don''t Change'!$A$2:$A$7) -> 46164 | B39: =+WEEKNUM(A39) -> 21 | C39: =+TEXT(A39,"mmmm") -> May | Q39: =+SUM(K39:M39)/Weights!$B$2 -> 0 | R39: =+SUM(N39:P39)/Weights!$B$4 -> 0 | S39: =IFERROR(Q39/SUM(D39:F39),"") | T39: =IFERROR(R39/SUM(G39:I39),"")
A40: =WORKDAY.INTL(A39,1,,'Don''t Change'!$A$2:$A$7) -> 46168 | B40: =+WEEKNUM(A40) -> 22 | C40: =+TEXT(A40,"mmmm") -> May | D40: =22*15*96+30*72+26*72 -> 35712 | E40: =22*15*96+6*96 -> 32256 | K40: 80 | L40: 160 | Q40: =+SUM(K40:M40)/Weights!$B$2 -> 3792.5926 | R40: =+SUM(N40:P40)/Weights!$B$4 -> 0 | S40: =IFERROR(Q40/SUM(D40:F40),"") -> 0.055799679 | T40: =IFERROR(R40/SUM(G40:I40),"") | AF40: =360000/4 -> 90000 | AG40: =44800/4 -> 11200
A41: =WORKDAY.INTL(A40,1,,'Don''t Change'!$A$2:$A$7) -> 46169 | B41: =+WEEKNUM(A41) -> 22 | C41: =+TEXT(A41,"mmmm") -> May | Q41: =+SUM(K41:M41)/Weights!$B$2 -> 0 | R41: =+SUM(N41:P41)/Weights!$B$4 -> 0 | S41: =IFERROR(Q41/SUM(D41:F41),"") | T41: =IFERROR(R41/SUM(G41:I41),"") | AF41: =360000/4 -> 90000 | AG41: =44800/4 -> 11200
A42: =WORKDAY.INTL(A41,1,,'Don''t Change'!$A$2:$A$7) -> 46170 | B42: =+WEEKNUM(A42) -> 22 | C42: =+TEXT(A42,"mmmm") -> May | H42: =21*14*35+10*35 -> 10640 | I42: 9922 | O42: 122 | P42: 146 | Q42: =+SUM(K42:M42)/Weights!$B$2 -> 0 | R42: =+SUM(N42:P42)/Weights!$B$4 -> 1715.2 | S42: =IFERROR(Q42/SUM(D42:F42),"") | T42: =IFERROR(R42/SUM(G42:I42),"") -> 0.08341601 | AF42: =360000/4 -> 90000 | AG42: =44800/4 -> 11200
A43: =WORKDAY.INTL(A42,1,,'Don''t Change'!$A$2:$A$7) -> 46171 | B43: =+WEEKNUM(A43) -> 22 | C43: =+TEXT(A43,"mmmm") -> May | D43: =22*15*96+12*96 -> 32832 | E43: =22*15*96 -> 31680 | K43: 40 | L43: 40 | Q43: =+SUM(K43:M43)/Weights!$B$2 -> 1264.1975 | R43: =+SUM(N43:P43)/Weights!$B$4 -> 0 | S43: =IFERROR(Q43/SUM(D43:F43),"") -> 0.019596316 | T43: =IFERROR(R43/SUM(G43:I43),"") | AF43: =360000/4 -> 90000 | AG43: =44800/4 -> 11200
A44: =WORKDAY.INTL(A43,1,,'Don''t Change'!$A$2:$A$7) -> 46174 | B44: =+WEEKNUM(A44) -> 23 | C44: =+TEXT(A44,"mmmm") -> June | D44: 27360 | E44: 48960 | K44: 46 | L44: 280 | Q44: =+SUM(K44:M44)/Weights!$B$2 -> 5151.6049 | R44: =+SUM(N44:P44)/Weights!$B$4 -> 0 | S44: =IFERROR(Q44/SUM(D44:F44),"") -> 0.067500065 | T44: =IFERROR(R44/SUM(G44:I44),"") | AF44: 70000 | AG44: 15000
A45: =WORKDAY.INTL(A44,1,,'Don''t Change'!$A$2:$A$7) -> 46175 | B45: =+WEEKNUM(A45) -> 23 | C45: =+TEXT(A45,"mmmm") -> June | D45: 44640 | E45: 44640 | K45: 96 | L45: 72 | Q45: =+SUM(K45:M45)/Weights!$B$2 -> 2654.8148 | R45: =+SUM(N45:P45)/Weights!$B$4 -> 0 | S45: =IFERROR(Q45/SUM(D45:F45),"") -> 0.029735829 | T45: =IFERROR(R45/SUM(G45:I45),"") | AF45: 70000 | AG45: 15000
A46: =WORKDAY.INTL(A45,1,,'Don''t Change'!$A$2:$A$7) -> 46176 | B46: =+WEEKNUM(A46) -> 23 | C46: =+TEXT(A46,"mmmm") -> June | D46: 17280 | E46: =21*15*96+6*96+7*15*72 -> 38376 | K46: 121 | L46: 45 | O46: 60 | Q46: =+SUM(K46:M46)/Weights!$B$2 -> 2623.2099 | R46: =+SUM(N46:P46)/Weights!$B$4 -> 384 | S46: =IFERROR(Q46/SUM(D46:F46),"") -> 0.047132562 | T46: =IFERROR(R46/SUM(G46:I46),"") | AF46: 70000 | AG46: 15000
A47: =WORKDAY.INTL(A46,1,,'Don''t Change'!$A$2:$A$7) -> 46177 | B47: =+WEEKNUM(A47) -> 23 | C47: =+TEXT(A47,"mmmm") -> June | D47: =7*15*96+14*96+15*72 -> 12504 | E47: =22*15*96+15*72+11*96 -> 33816 | H47: =15*16*35+13*35+15*35 -> 9380 | K47: 36 | L47: 37 | O47: =38+18+32+44 -> 132 | Q47: =+SUM(K47:M47)/Weights!$B$2 -> 1153.5802 | R47: =+SUM(N47:P47)/Weights!$B$4 -> 844.8 | S47: =IFERROR(Q47/SUM(D47:F47),"") -> 0.024904582 | T47: =IFERROR(R47/SUM(G47:I47),"") -> 0.090063966 | AF47: 90000 | AG47: 15000
A48: =WORKDAY.INTL(A47,1,,'Don''t Change'!$A$2:$A$7) -> 46178 | B48: =+WEEKNUM(A48) -> 23 | C48: =+TEXT(A48,"mmmm") -> June | Q48: =+SUM(K48:M48)/Weights!$B$2 -> 0 | R48: =+SUM(N48:P48)/Weights!$B$4 -> 0 | S48: =IFERROR(Q48/SUM(D48:F48),"") | T48: =IFERROR(R48/SUM(G48:I48),"")
A49: =WORKDAY.INTL(A48,1,,'Don''t Change'!$A$2:$A$7) -> 46181 | B49: =+WEEKNUM(A49) -> 24 | C49: =+TEXT(A49,"mmmm") -> June | Q49: =+SUM(K49:M49)/Weights!$B$2 -> 0 | R49: =+SUM(N49:P49)/Weights!$B$4 -> 0 | S49: =IFERROR(Q49/SUM(D49:F49),"") | T49: =IFERROR(R49/SUM(G49:I49),"")
A50: =WORKDAY.INTL(A49,1,,'Don''t Change'!$A$2:$A$7) -> 46182 | B50: =+WEEKNUM(A50) -> 24 | C50: =+TEXT(A50,"mmmm") -> June | D50: 49168 | E50: 34352 | H50: 7315 | K50: 229 | L50: 203 | O50: 32 | Q50: =+SUM(K50:M50)/Weights!$B$2 -> 6826.6667 | R50: =+SUM(N50:P50)/Weights!$B$4 -> 204.8 | S50: =IFERROR(Q50/SUM(D50:F50),"") -> 0.081736909 | T50: =IFERROR(R50/SUM(G50:I50),"") -> 0.027997266
A51: =WORKDAY.INTL(A50,1,,'Don''t Change'!$A$2:$A$7) -> 46183 | B51: =+WEEKNUM(A51) -> 24 | C51: =+TEXT(A51,"mmmm") -> June | D51: =18720+25200 -> 43920 | H51: 10500 | K51: =62+36 -> 98 | O51: 62 | Q51: =+SUM(K51:M51)/Weights!$B$2 -> 1548.642 | R51: =+SUM(N51:P51)/Weights!$B$4 -> 396.8 | S51: =IFERROR(Q51/SUM(D51:F51),"") -> 0.035260519 | T51: =IFERROR(R51/SUM(G51:I51),"") -> 0.037790476
A52: =WORKDAY.INTL(A51,1,,'Don''t Change'!$A$2:$A$7) -> 46184 | B52: =+WEEKNUM(A52) -> 24 | C52: =+TEXT(A52,"mmmm") -> June | D52: 61488 | E52: 2765 | H52: 9975 | K52: 101 | L52: 31 | O52: 122 | Q52: =+SUM(K52:M52)/Weights!$B$2 -> 2085.9259 | R52: =+SUM(N52:P52)/Weights!$B$4 -> 780.8 | S52: =IFERROR(Q52/SUM(D52:F52),"") -> 0.032464257 | T52: =IFERROR(R52/SUM(G52:I52),"") -> 0.078275689
A53: =WORKDAY.INTL(A52,1,,'Don''t Change'!$A$2:$A$7) -> 46185 | B53: =+WEEKNUM(A53) -> 24 | C53: =+TEXT(A53,"mmmm") -> June | Q53: =+SUM(K53:M53)/Weights!$B$2 -> 0 | R53: =+SUM(N53:P53)/Weights!$B$4 -> 0 | S53: =IFERROR(Q53/SUM(D53:F53),"") | T53: =IFERROR(R53/SUM(G53:I53),"")
A54: =WORKDAY.INTL(A53,1,,'Don''t Change'!$A$2:$A$7) -> 46188 | B54: =+WEEKNUM(A54) -> 25 | C54: =+TEXT(A54,"mmmm") -> June | D54: =23*15*96 -> 33120 | K54: 68 | Q54: =+SUM(K54:M54)/Weights!$B$2 -> 1074.5679 | R54: =+SUM(N54:P54)/Weights!$B$4 -> 0 | S54: =IFERROR(Q54/SUM(D54:F54),"") -> 0.032444683 | T54: =IFERROR(R54/SUM(G54:I54),"")
A55: =WORKDAY.INTL(A54,1,,'Don''t Change'!$A$2:$A$7) -> 46189 | B55: =+WEEKNUM(A55) -> 25 | C55: =+TEXT(A55,"mmmm") -> June | D55: =24*96*15 -> 34560 | E55: =23*15*96 -> 33120 | K55: 48 | L55: 61 | Q55: =+SUM(K55:M55)/Weights!$B$2 -> 1722.4691 | R55: =+SUM(N55:P55)/Weights!$B$4 -> 0 | S55: =IFERROR(Q55/SUM(D55:F55),"") -> 0.025450194 | T55: =IFERROR(R55/SUM(G55:I55),"")
A56: =WORKDAY.INTL(A55,1,,'Don''t Change'!$A$2:$A$7) -> 46190 | B56: =+WEEKNUM(A56) -> 25 | C56: =+TEXT(A56,"mmmm") -> June | D56: =17*15*96+38.5*96 -> 28176 | E56: =18*15*96+7.5*96 -> 26640 | H56: =40*35 -> 1400 | K56: =18+5 -> 23 | L56: 206 | O56: 14 | Q56: =+SUM(K56:M56)/Weights!$B$2 -> 3618.7654 | R56: =+SUM(N56:P56)/Weights!$B$4 -> 89.6 | S56: =IFERROR(Q56/SUM(D56:F56),"") -> 0.066016591 | T56: =IFERROR(R56/SUM(G56:I56),"") -> 0.064
A57: =WORKDAY.INTL(A56,1,,'Don''t Change'!$A$2:$A$7) -> 46191 | B57: =+WEEKNUM(A57) -> 25 | C57: =+TEXT(A57,"mmmm") -> June | D57: =20*15*96+11.5*96 -> 29904 | E57: =22*15*96+8*96 -> 32448 | H57: =12*15*35 -> 6300 | K57: 50 | L57: 84 | O57: 23 | Q57: =+SUM(K57:M57)/Weights!$B$2 -> 2117.5309 | R57: =+SUM(N57:P57)/Weights!$B$4 -> 147.2 | S57: =IFERROR(Q57/SUM(D57:F57),"") -> 0.033960913 | T57: =IFERROR(R57/SUM(G57:I57),"") -> 0.023365079
A58: =WORKDAY.INTL(A57,1,,'Don''t Change'!$A$2:$A$7) -> 46192 | B58: =+WEEKNUM(A58) -> 25 | C58: =+TEXT(A58,"mmmm") -> June | Q58: =+SUM(K58:M58)/Weights!$B$2 -> 0 | R58: =+SUM(N58:P58)/Weights!$B$4 -> 0 | S58: =IFERROR(Q58/SUM(D58:F58),"") | T58: =IFERROR(R58/SUM(G58:I58),"")
A59: =WORKDAY.INTL(A58,1,,'Don''t Change'!$A$2:$A$7) -> 46195 | B59: =+WEEKNUM(A59) -> 26 | C59: =+TEXT(A59,"mmmm") -> June | D59: =24*15*96+14.5*96-492 -> 35460 | E59: =25*15*96+10*96 -> 36960 | H59: =8313 -> 8313 | K59: 55 | L59: 82 | O59: 279 | Q59: =+SUM(K59:M59)/Weights!$B$2 -> 2164.9383 | R59: =+SUM(N59:P59)/Weights!$B$4 -> 1785.6 | S59: =IFERROR(Q59/SUM(D59:F59),"") -> 0.029894204 | T59: =IFERROR(R59/SUM(G59:I59),"") -> 0.2147961
A60: =WORKDAY.INTL(A59,1,,'Don''t Change'!$A$2:$A$7) -> 46196 | B60: =+WEEKNUM(A60) -> 26 | C60: =+TEXT(A60,"mmmm") -> June | D60: =32*15*96 -> 46080 | E60: 13015 | H60: =18*15*35 -> 9450 | K60: 60 | L60: 122 | O60: 474 | Q60: =+SUM(K60:M60)/Weights!$B$2 -> 2876.0494 | R60: =+SUM(N60:P60)/Weights!$B$4 -> 3033.6 | S60: =IFERROR(Q60/SUM(D60:F60),"") -> 0.048668236 | T60: =IFERROR(R60/SUM(G60:I60),"") -> 0.32101587
A61: =WORKDAY.INTL(A60,1,,'Don''t Change'!$A$2:$A$7) -> 46197 | B61: =+WEEKNUM(A61) -> 26 | C61: =+TEXT(A61,"mmmm") -> June | D61: =20*15*96 -> 28800 | E61: =34*15*96+9*96 -> 49824 | G61: =29*15*35+9*35 -> 15540 | K61: 43 | L61: 79 | N61: =408+106 -> 514 | Q61: =+SUM(K61:M61)/Weights!$B$2 -> 1927.9012 | R61: =+SUM(N61:P61)/Weights!$B$4 -> 3289.6 | S61: =IFERROR(Q61/SUM(D61:F61),"") -> 0.024520518 | T61: =IFERROR(R61/SUM(G61:I61),"") -> 0.21168597
A62: =WORKDAY.INTL(A61,1,,'Don''t Change'!$A$2:$A$7) -> 46198 | B62: =+WEEKNUM(A62) -> 26 | C62: =+TEXT(A62,"mmmm") -> June | D62: =33*15*96+16*96 -> 49056 | E62: =33*15*96+26*6 -> 47676 | G62: =7*15*35+8*35+16*35 -> 4515 | K62: 150 | L62: 63 | N62: 278 | Q62: =+SUM(K62:M62)/Weights!$B$2 -> 3365.9259 | R62: =+SUM(N62:P62)/Weights!$B$4 -> 1779.2 | S62: =IFERROR(Q62/SUM(D62:F62),"") -> 0.034796406 | T62: =IFERROR(R62/SUM(G62:I62),"") -> 0.39406423
A63: =WORKDAY.INTL(A62,1,,'Don''t Change'!$A$2:$A$7) -> 46199 | B63: =+WEEKNUM(A63) -> 26 | C63: =+TEXT(A63,"mmmm") -> June | Q63: =+SUM(K63:M63)/Weights!$B$2 -> 0 | R63: =+SUM(N63:P63)/Weights!$B$4 -> 0 | S63: =IFERROR(Q63/SUM(D63:F63),"") | T63: =IFERROR(R63/SUM(G63:I63),"")
A64: =WORKDAY.INTL(A63,1,,'Don''t Change'!$A$2:$A$7) -> 46202 | B64: =+WEEKNUM(A64) -> 27 | C64: =+TEXT(A64,"mmmm") -> June | D64: =29*15*96+12*96 -> 42912 | E64: =25*15*96+11*96 -> 37056 | G64: =14*15*35+7*35 -> 7595 | H64: =12*15*35 -> 6300 | K64: =74+183 -> 257 | L64: 172 | N64: 120 | O64: 46 | Q64: =+SUM(K64:M64)/Weights!$B$2 -> 6779.2593 | R64: =+SUM(N64:P64)/Weights!$B$4 -> 1062.4 | S64: =IFERROR(Q64/SUM(D64:F64),"") -> 0.084774651 | T64: =IFERROR(R64/SUM(G64:I64),"") -> 0.076459158
A65: =WORKDAY.INTL(A64,1,,'Don''t Change'!$A$2:$A$7) -> 46203 | B65: =+WEEKNUM(A65) -> 27 | C65: =+TEXT(A65,"mmmm") -> June | D65: =21*15*96+11*96 -> 31296 | E65: =35*15*96+5*6 -> 50430 | G65: =70*35 -> 2450 | H65: =25*15*35+70 -> 13195 | K65: 198 | L65: 80 | N65: 100 | O65: =684-288 -> 396 | Q65: =+SUM(K65:M65)/Weights!$B$2 -> 4393.0864 | R65: =+SUM(N65:P65)/Weights!$B$4 -> 3174.4 | S65: =IFERROR(Q65/SUM(D65:F65),"") -> 0.053753841 | T65: =IFERROR(R65/SUM(G65:I65),"") -> 0.20290189
A66: =WORKDAY.INTL(A65,1,,'Don''t Change'!$A$2:$A$7) -> 46204 | B66: =+WEEKNUM(A66) -> 27 | C66: =+TEXT(A66,"mmmm") -> July | D66: =25*15*96 -> 36000 | E66: =25*15*96 -> 36000 | H66: =25*15*35+8*35 -> 13405 | K66: =45+10+34 -> 89 | L66: 96 | O66: =88+96 -> 184 | Q66: =+SUM(K66:M66)/Weights!$B$2 -> 2923.4568 | R66: =+SUM(N66:P66)/Weights!$B$4 -> 1177.6 | S66: =IFERROR(Q66/SUM(D66:F66),"") -> 0.040603567 | T66: =IFERROR(R66/SUM(G66:I66),"") -> 0.087847818
A67: 46205 | B67: =+WEEKNUM(A67) -> 27 | C67: =+TEXT(A67,"mmmm") -> July | D67: =32*15*96+10*96 -> 47040 | E67: =33*15*96+16*96 -> 49056 | G67: =25*15*35 -> 13125 | H67: =25*15*35+9*35 -> 13440 | K67: 238 | L67: 122 | N67: 56 | O67: 56 | Q67: =+SUM(K67:M67)/Weights!$B$2 -> 5688.8889 | R67: =+SUM(N67:P67)/Weights!$B$4 -> 716.8 | S67: =IFERROR(Q67/SUM(D67:F67),"") -> 0.059200059 | T67: =IFERROR(R67/SUM(G67:I67),"") -> 0.026982872
A68: =WORKDAY.INTL(A67,1,,'Don''t Change'!$A$2:$A$7) -> 46206 | B68: =+WEEKNUM(A68) -> 27 | C68: =+TEXT(A68,"mmmm") -> July | Q68: =+SUM(K68:M68)/Weights!$B$2 -> 0 | R68: =+SUM(N68:P68)/Weights!$B$4 -> 0 | S68: =IFERROR(Q68/SUM(D68:F68),"") | T68: =IFERROR(R68/SUM(G68:I68),"")
A69: =WORKDAY.INTL(A68,1,,'Don''t Change'!$A$2:$A$7) -> 46209 | B69: =+WEEKNUM(A69) -> 28 | C69: =+TEXT(A69,"mmmm") -> July | D69: =24*15*96 -> 34560 | E69: =14*15*96+10*96 -> 21120 | G69: =39*35 -> 1365 | I69: =9*15*35 -> 4725 | K69: =308-140+1086-192.02 -> 1061.98 | L69: 172 | N69: =44+184 -> 228 | P69: =42 -> 42 | Q69: =+SUM(K69:M69)/Weights!$B$2 -> 19499.931 | R69: =+SUM(N69:P69)/Weights!$B$4 -> 1728 | S69: =IFERROR(Q69/SUM(D69:F69),"") -> 0.35021428 | T69: =IFERROR(R69/SUM(G69:I69),"") -> 0.28374384
A70: =WORKDAY.INTL(A69,1,,'Don''t Change'!$A$2:$A$7) -> 46210 | B70: =+WEEKNUM(A70) -> 28 | C70: =+TEXT(A70,"mmmm") -> July | D70: 44064 | E70: 41760 | G70: =21*15*35+9*35 -> 11340 | I70: =23*15*35 -> 12075 | K70: 222 | L70: 204 | N70: 71 | P70: 150 | Q70: =+SUM(K70:M70)/Weights!$B$2 -> 6731.8519 | R70: =+SUM(N70:P70)/Weights!$B$4 -> 1414.4 | S70: =IFERROR(Q70/SUM(D70:F70),"") -> 0.078437871 | T70: =IFERROR(R70/SUM(G70:I70),"") -> 0.060405723
A71: =WORKDAY.INTL(A70,1,,'Don''t Change'!$A$2:$A$7) -> 46211 | B71: =+WEEKNUM(A71) -> 28 | C71: =+TEXT(A71,"mmmm") -> July | D71: =31*15*96 -> 44640 | E71: =12*15*96+3.5*96 -> 17616 | G71: =20*15*35+2*35+14 -> 10584 | I71: =19*15*35+10*35 -> 10325 | K71: =28+62 -> 90 | L71: 146 | N71: 84 | P71: =22+58 -> 80 | Q71: =+SUM(K71:M71)/Weights!$B$2 -> 3729.3827 | R71: =+SUM(N71:P71)/Weights!$B$4 -> 1049.6 | S71: =IFERROR(Q71/SUM(D71:F71),"") -> 0.059903989 | T71: =IFERROR(R71/SUM(G71:I71),"") -> 0.050198479
A72: =WORKDAY.INTL(A71,1,,'Don''t Change'!$A$2:$A$7) -> 46212 | B72: =+WEEKNUM(A72) -> 28 | C72: =+TEXT(A72,"mmmm") -> July | D72: =26*15*96+6*96 -> 38016 | E72: =20*15*96 -> 28800 | G72: =29*15*35+11*35 -> 15610 | I72: =30*15*35+10*35 -> 16100 | K72: 192 | L72: 150 | N72: =109+52 -> 161 | P72: 50 | Q72: =+SUM(K72:M72)/Weights!$B$2 -> 5404.4444 | R72: =+SUM(N72:P72)/Weights!$B$4 -> 1350.4 | S72: =IFERROR(Q72/SUM(D72:F72),"") -> 0.080885483 | T72: =IFERROR(R72/SUM(G72:I72),"") -> 0.042585935
A73: =WORKDAY.INTL(A72,1,,'Don''t Change'!$A$2:$A$7) -> 46213 | B73: =+WEEKNUM(A73) -> 28 | C73: =+TEXT(A73,"mmmm") -> July | Q73: =+SUM(K73:M73)/Weights!$B$2 -> 0 | R73: =+SUM(N73:P73)/Weights!$B$4 -> 0 | S73: =IFERROR(Q73/SUM(D73:F73),"") | T73: =IFERROR(R73/SUM(G73:I73),"")
A74: =WORKDAY.INTL(A73,1,,'Don''t Change'!$A$2:$A$7) -> 46216 | B74: =+WEEKNUM(A74) -> 29 | C74: =+TEXT(A74,"mmmm") -> July | Q74: =+SUM(K74:M74)/Weights!$B$2 -> 0 | R74: =+SUM(N74:P74)/Weights!$B$4 -> 0 | S74: =IFERROR(Q74/SUM(D74:F74),"") | T74: =IFERROR(R74/SUM(G74:I74),"")
A75: =WORKDAY.INTL(A74,1,,'Don''t Change'!$A$2:$A$7) -> 46217 | B75: =+WEEKNUM(A75) -> 29 | C75: =+TEXT(A75,"mmmm") -> July | Q75: =+SUM(K75:M75)/Weights!$B$2 -> 0 | R75: =+SUM(N75:P75)/Weights!$B$4 -> 0 | S75: =IFERROR(Q75/SUM(D75:F75),"") | T75: =IFERROR(R75/SUM(G75:I75),"")
A76: =WORKDAY.INTL(A75,1,,'Don''t Change'!$A$2:$A$7) -> 46218 | B76: =+WEEKNUM(A76) -> 29 | C76: =+TEXT(A76,"mmmm") -> July | Q76: =+SUM(K76:M76)/Weights!$B$2 -> 0 | R76: =+SUM(N76:P76)/Weights!$B$4 -> 0 | S76: =IFERROR(Q76/SUM(D76:F76),"") | T76: =IFERROR(R76/SUM(G76:I76),"")
A77: =WORKDAY.INTL(A76,1,,'Don''t Change'!$A$2:$A$7) -> 46219 | B77: =+WEEKNUM(A77) -> 29 | C77: =+TEXT(A77,"mmmm") -> July | Q77: =+SUM(K77:M77)/Weights!$B$2 -> 0 | R77: =+SUM(N77:P77)/Weights!$B$4 -> 0 | S77: =IFERROR(Q77/SUM(D77:F77),"") | T77: =IFERROR(R77/SUM(G77:I77),"")
A78: =WORKDAY.INTL(A77,1,,'Don''t Change'!$A$2:$A$7) -> 46220 | B78: =+WEEKNUM(A78) -> 29 | C78: =+TEXT(A78,"mmmm") -> July | Q78: =+SUM(K78:M78)/Weights!$B$2 -> 0 | R78: =+SUM(N78:P78)/Weights!$B$4 -> 0 | S78: =IFERROR(Q78/SUM(D78:F78),"") | T78: =IFERROR(R78/SUM(G78:I78),"")
A79: =WORKDAY.INTL(A78,1,,'Don''t Change'!$A$2:$A$7) -> 46223 | B79: =+WEEKNUM(A79) -> 30 | C79: =+TEXT(A79,"mmmm") -> July | D79: =18*15*96+3*96 -> 26208 | E79: =18*15*96+7*96 -> 26592 | K79: =82+12 -> 94 | L79: =94+12 -> 106 | Q79: =+SUM(K79:M79)/Weights!$B$2 -> 3160.4938 | R79: =+SUM(N79:P79)/Weights!$B$4 -> 0 | S79: =IFERROR(Q79/SUM(D79:F79),"") -> 0.059857838 | T79: =IFERROR(R79/SUM(G79:I79),"")
A80: =WORKDAY.INTL(A79,1,,'Don''t Change'!$A$2:$A$7) -> 46224 | B80: =+WEEKNUM(A80) -> 30 | C80: =+TEXT(A80,"mmmm") -> July | D80: =34*15*96+2*96 -> 49152 | E80: =22*15*96+10*96+11*96 -> 33696 | G80: =29*15*35+5*35 -> 15400 | I80: =27*15*35+2*35 -> 14245 | K80: =121+26 -> 147 | L80: =104+26 -> 130 | N80: 322 | P80: =64+84 -> 148 | Q80: =+SUM(K80:M80)/Weights!$B$2 -> 4377.284 | R80: =+SUM(N80:P80)/Weights!$B$4 -> 3008 | S80: =IFERROR(Q80/SUM(D80:F80),"") -> 0.052835119 | T80: =IFERROR(R80/SUM(G80:I80),"") -> 0.10146736
A81: =WORKDAY.INTL(A80,1,,'Don''t Change'!$A$2:$A$7) -> 46225 | B81: =+WEEKNUM(A81) -> 30 | C81: =+TEXT(A81,"mmmm") -> July | D81: =7*15*96+14.5*96+20*15*96+12*96 -> 41424 | E81: =5*15*96+13*96+16*15*96+4*96 -> 31872 | G81: =21*15*35+10*35 -> 11375 | I81: =23*15*35+7.5*35+2.5*35 -> 12425 | K81: =54+100+218 -> 372 | L81: =50+88 -> 138 | N81: =78+195 -> 273 | P81: =44+195 -> 239 | Q81: =+SUM(K81:M81)/Weights!$B$2 -> 8059.2593 | R81: =+SUM(N81:P81)/Weights!$B$4 -> 3276.8 | S81: =IFERROR(Q81/SUM(D81:F81),"") -> 0.10995497 | T81: =IFERROR(R81/SUM(G81:I81),"") -> 0.13768067
A82: =WORKDAY.INTL(A81,1,,'Don''t Change'!$A$2:$A$7) -> 46226 | B82: =+WEEKNUM(A82) -> 30 | C82: =+TEXT(A82,"mmmm") -> July | D82: =28*15*96+4*96 -> 40704 | E82: =24*15*96 -> 34560 | G82: =20*15*35+3.5*35 -> 10622.5 | I82: =20*15*35+12*35 -> 10920 | K82: =131+34 -> 165 | L82: =174+34 -> 208 | N82: 97 | P82: 80 | Q82: =+SUM(K82:M82)/Weights!$B$2 -> 5894.321 | R82: =+SUM(N82:P82)/Weights!$B$4 -> 1132.8 | S82: =IFERROR(Q82/SUM(D82:F82),"") -> 0.078315277 | T82: =IFERROR(R82/SUM(G82:I82),"") -> 0.052584426
A83: =WORKDAY.INTL(A82,1,,'Don''t Change'!$A$2:$A$7) -> 46227 | B83: =+WEEKNUM(A83) -> 30 | C83: =+TEXT(A83,"mmmm") -> July | Q83: =+SUM(K83:M83)/Weights!$B$2 -> 0 | R83: =+SUM(N83:P83)/Weights!$B$4 -> 0 | S83: =IFERROR(Q83/SUM(D83:F83),"") | T83: =IFERROR(R83/SUM(G83:I83),"")
A84: =WORKDAY.INTL(A83,1,,'Don''t Change'!$A$2:$A$7) -> 46230 | B84: =+WEEKNUM(A84) -> 31 | C84: =+TEXT(A84,"mmmm") -> July | D84: =23*15*96+3*96 -> 33408 | E84: =16*15*96 -> 23040 | G84: =33*15*35+14.5*35 -> 17832.5 | I84: =14*15*35+210 -> 7560 | K84: 212 | L84: 212 | N84: 75 | P84: 108 | Q84: =+SUM(K84:M84)/Weights!$B$2 -> 6700.2469 | R84: =+SUM(N84:P84)/Weights!$B$4 -> 1171.2 | S84: =IFERROR(Q84/SUM(D84:F84),"") -> 0.11869768 | T84: =IFERROR(R84/SUM(G84:I84),"") -> 0.046123855
A85: =WORKDAY.INTL(A84,1,,'Don''t Change'!$A$2:$A$7) -> 46231 | B85: =+WEEKNUM(A85) -> 31 | C85: =+TEXT(A85,"mmmm") -> July | D85: 23760 | E85: 25128 | G85: 15172 | I85: 14490 | K85: 0 | L85: 0 | N85: 46 | P85: 66 | Q85: =+SUM(K85:M85)/Weights!$B$2 -> 0 | R85: =+SUM(N85:P85)/Weights!$B$4 -> 716.8 | S85: =IFERROR(Q85/SUM(D85:F85),"") -> 0 | T85: =IFERROR(R85/SUM(G85:I85),"") -> 0.024165599
A86: =WORKDAY.INTL(A85,1,,'Don''t Change'!$A$2:$A$7) -> 46232 | B86: =+WEEKNUM(A86) -> 31 | C86: =+TEXT(A86,"mmmm") -> July | D86: =14*1440+8*96+8120 -> 29048 | E86: =27*1440+12*96 -> 40032 | G86: =32*15*35+6*35 -> 17010 | I86: =33*15*35+5.5*35 -> 17517.5 | K86: =84+74 -> 158 | L86: 212.85 | N86: =435+210 -> 645 | P86: =435+54 -> 489 | Q86: =+SUM(K86:M86)/Weights!$B$2 -> 5860.3457 | R86: =+SUM(N86:P86)/Weights!$B$4 -> 7257.6 | S86: =IFERROR(Q86/SUM(D86:F86),"") -> 0.084834188 | T86: =IFERROR(R86/SUM(G86:I86),"") -> 0.21019767
A87: =WORKDAY.INTL(A86,1,,'Don''t Change'!$A$2:$A$7) -> 46233 | B87: =+WEEKNUM(A87) -> 31 | C87: =+TEXT(A87,"mmmm") -> July | D87: =24*15*96+14*96 -> 35904 | E87: =4*15*96 -> 5760 | K87: 202 | L87: 78 | Q87: =+SUM(K87:M87)/Weights!$B$2 -> 4424.6914 | R87: =+SUM(N87:P87)/Weights!$B$4 -> 0 | S87: =IFERROR(Q87/SUM(D87:F87),"") -> 0.10619939 | T87: =IFERROR(R87/SUM(G87:I87),"")
A88: =WORKDAY.INTL(A87,1,,'Don''t Change'!$A$2:$A$7) -> 46234 | B88: =+WEEKNUM(A88) -> 31 | C88: =+TEXT(A88,"mmmm") -> July | Q88: =+SUM(K88:M88)/Weights!$B$2 -> 0 | R88: =+SUM(N88:P88)/Weights!$B$4 -> 0 | S88: =IFERROR(Q88/SUM(D88:F88),"") | T88: =IFERROR(R88/SUM(G88:I88),"")
A89: =WORKDAY.INTL(A88,1,,'Don''t Change'!$A$2:$A$7) -> 46237 | B89: =+WEEKNUM(A89) -> 32 | C89: =+TEXT(A89,"mmmm") -> August | D89: =7*1440+7*96+17*15*96 -> 35232 | E89: =7*15*96+17*15*96 -> 34560 | G89: =41*15*35+19*35 -> 22190 | I89: =43*15*35 -> 22575 | K89: =61+120+16 -> 197 | L89: =24+120+16 -> 160 | N89: =98+303 -> 401 | P89: =64+303 -> 367 | Q89: =+SUM(K89:M89)/Weights!$B$2 -> 5641.4815 | R89: =+SUM(N89:P89)/Weights!$B$4 -> 4915.2 | S89: =IFERROR(Q89/SUM(D89:F89),"") -> 0.080832781 | T89: =IFERROR(R89/SUM(G89:I89),"") -> 0.10980007
A90: =WORKDAY.INTL(A89,1,,'Don''t Change'!$A$2:$A$7) -> 46238 | B90: =+WEEKNUM(A90) -> 32 | C90: =+TEXT(A90,"mmmm") -> August | D90: =30*15*96+13*96 -> 44448 | E90: =30*15*96 -> 43200 | G90: =34*15*35 -> 17850 | I90: =33*15*35+11*35 -> 17710 | K90: =186+140 -> 326 | L90: =186+178 -> 364 | N90: =38+120 -> 158 | P90: =38+64 -> 102 | Q90: =+SUM(K90:M90)/Weights!$B$2 -> 10903.704 | R90: =+SUM(N90:P90)/Weights!$B$4 -> 1664 | S90: =IFERROR(Q90/SUM(D90:F90),"") -> 0.12440334 | T90: =IFERROR(R90/SUM(G90:I90),"") -> 0.046794151
A91: =WORKDAY.INTL(A90,1,,'Don''t Change'!$A$2:$A$7) -> 46239 | B91: =+WEEKNUM(A91) -> 32 | C91: =+TEXT(A91,"mmmm") -> August | D91: =32*15*96+48 -> 46128 | E91: =23*15*96+14*96 -> 34464 | G91: =31*15*35+16*35 -> 16835 | I91: =30*15*35+7*35 -> 15995 | K91: =156+87+304 -> 547 | L91: =156 -> 156 | N91: =214+310 -> 524 | P91: =214+112 -> 326 | Q91: =+SUM(K91:M91)/Weights!$B$2 -> 11109.136 | R91: =+SUM(N91:P91)/Weights!$B$4 -> 5440 | S91: =IFERROR(Q91/SUM(D91:F91),"") -> 0.13784415 | T91: =IFERROR(R91/SUM(G91:I91),"") -> 0.1657021
A92: =WORKDAY.INTL(A91,1,,'Don''t Change'!$A$2:$A$7) -> 46240 | B92: =+WEEKNUM(A92) -> 32 | C92: =+TEXT(A92,"mmmm") -> August | D92: =22*15*96 -> 31680 | E92: =13*15*96 -> 18720 | G92: =34*15*35+5*35 -> 18025 | I92: =31*15*35+23*35 -> 17080 | K92: =94+111 -> 205 | L92: =193+111 -> 304 | N92: =82+136 -> 218 | P92: =82+186 -> 268 | Q92: =+SUM(K92:M92)/Weights!$B$2 -> 8043.4568 | R92: =+SUM(N92:P92)/Weights!$B$4 -> 3110.4 | S92: =IFERROR(Q92/SUM(D92:F92),"") -> 0.1595924 | T92: =IFERROR(R92/SUM(G92:I92),"") -> 0.088602763
A93: =WORKDAY.INTL(A92,1,,'Don''t Change'!$A$2:$A$7) -> 46241 | B93: =+WEEKNUM(A93) -> 32 | C93: =+TEXT(A93,"mmmm") -> August | Q93: =+SUM(K93:M93)/Weights!$B$2 -> 0 | R93: =+SUM(N93:P93)/Weights!$B$4 -> 0 | S93: =IFERROR(Q93/SUM(D93:F93),"") | T93: =IFERROR(R93/SUM(G93:I93),"")
A94: =WORKDAY.INTL(A93,1,,'Don''t Change'!$A$2:$A$7) -> 46244 | B94: =+WEEKNUM(A94) -> 33 | C94: =+TEXT(A94,"mmmm") -> August | D94: =25*15*96+8*96 -> 36768 | E94: =22*15*96+3*96 -> 31968 | G94: =47*15*35 -> 24675 | I94: =41*15*35+14*35 -> 22015 | K94: 54 | L94: 154 | N94: =66+40 -> 106 | P94: =674+40 -> 714 | Q94: =+SUM(K94:M94)/Weights!$B$2 -> 3286.9136 | R94: =+SUM(N94:P94)/Weights!$B$4 -> 5248 | S94: =IFERROR(Q94/SUM(D94:F94),"") -> 0.04781939 | T94: =IFERROR(R94/SUM(G94:I94),"") -> 0.11240094
A95: =WORKDAY.INTL(A94,1,,'Don''t Change'!$A$2:$A$7) -> 46245 | B95: =+WEEKNUM(A95) -> 33 | C95: =+TEXT(A95,"mmmm") -> August | D95: =31*15*96 -> 44640 | E95: =28*15*96 -> 40320 | G95: =37*15*35 -> 19425 | I95: =40*15*35 -> 21000 | K95: =64+82 -> 146 | L95: =108+82 -> 190 | N95: =72+330 -> 402 | P95: =56+330 -> 386 | Q95: =+SUM(K95:M95)/Weights!$B$2 -> 5309.6296 | R95: =+SUM(N95:P95)/Weights!$B$4 -> 5043.2 | S95: =IFERROR(Q95/SUM(D95:F95),"") -> 0.062495641 | T95: =IFERROR(R95/SUM(G95:I95),"") -> 0.12475448
A96: =WORKDAY.INTL(A95,1,,'Don''t Change'!$A$2:$A$7) -> 46246 | B96: =+WEEKNUM(A96) -> 33 | C96: =+TEXT(A96,"mmmm") -> August | D96: =30*15*96 -> 43200 | E96: =33*15*96 -> 47520 | G96: =51*15*35+4*35 -> 26915 | I96: =26*15*35 -> 13650 | K96: =144 -> 144 | L96: =106 -> 106 | N96: =25+66 -> 91 | P96: =32+66 -> 98 | Q96: =+SUM(K96:M96)/Weights!$B$2 -> 3950.6173 | R96: =+SUM(N96:P96)/Weights!$B$4 -> 1209.6 | S96: =IFERROR(Q96/SUM(D96:F96),"") -> 0.043547369 | T96: =IFERROR(R96/SUM(G96:I96),"") -> 0.029818809
A97: =WORKDAY.INTL(A96,1,,'Don''t Change'!$A$2:$A$7) -> 46247 | B97: =+WEEKNUM(A97) -> 33 | C97: =+TEXT(A97,"mmmm") -> August | Q97: =+SUM(K97:M97)/Weights!$B$2 -> 0 | R97: =+SUM(N97:P97)/Weights!$B$4 -> 0 | S97: =IFERROR(Q97/SUM(D97:F97),"") | T97: =IFERROR(R97/SUM(G97:I97),"")
A98: =WORKDAY.INTL(A97,1,,'Don''t Change'!$A$2:$A$7) -> 46248 | B98: =+WEEKNUM(A98) -> 33 | C98: =+TEXT(A98,"mmmm") -> August | Q98: =+SUM(K98:M98)/Weights!$B$2 -> 0 | R98: =+SUM(N98:P98)/Weights!$B$4 -> 0 | S98: =IFERROR(Q98/SUM(D98:F98),"") | T98: =IFERROR(R98/SUM(G98:I98),"")
A99: =WORKDAY.INTL(A98,1,,'Don''t Change'!$A$2:$A$7) -> 46251 | B99: =+WEEKNUM(A99) -> 34 | C99: =+TEXT(A99,"mmmm") -> August | G99: =40*15*35 -> 21000 | I99: =49*15*35+280 -> 26005 | N99: =28+64 -> 92 | P99: =28+38 -> 66 | Q99: =+SUM(K99:M99)/Weights!$B$2 -> 0 | R99: =+SUM(N99:P99)/Weights!$B$4 -> 1011.2 | S99: =IFERROR(Q99/SUM(D99:F99),"") | T99: =IFERROR(R99/SUM(G99:I99),"") -> 0.021512605
A100: =WORKDAY.INTL(A99,1,,'Don''t Change'!$A$2:$A$7) -> 46252 | B100: =+WEEKNUM(A100) -> 34 | C100: =+TEXT(A100,"mmmm") -> August | D100: =23*15*96+7*96 -> 33792 | E100: =28*15*96+12*96 -> 41472 | F100: =24*15*96 -> 34560 | G100: =11*15*35 -> 5775 | K100: 194 | L100: 135 | M100: 118 | N100: 28 | Q100: =+SUM(K100:M100)/Weights!$B$2 -> 7063.7037 | R100: =+SUM(N100:P100)/Weights!$B$4 -> 179.2 | S100: =IFERROR(Q100/SUM(D100:F100),"") -> 0.064318398 | T100: =IFERROR(R100/SUM(G100:I100),"") -> 0.031030303
...

Sheet Raw Data - Packing
D1: # SD Packed | F1: # Bao Packed | I1: SD Waste # | L1: Bao Waste # | O1: Dowtime Minutes | R1: Pieces SD | S1: Pieces Bao
A2: Date | B2: Week # | C2: Month | F2: 0 | I2: Adco #1 | J2: Adco #2 | L2: Adco #1 | M2: Adco #2 | O2: Adco #1 | P2: Adco #2
A3: 46104 | D3: =170*60 -> 10200 | F3: 0
A4: 46105 | D4: =389*60 -> 23340 | F4: 0
A5: 46106 | D5: =157*60 -> 9420 | F5: 0
A6: 46107 | D6: =556*60 -> 33360 | F6: 0
A7: 46111 | B7: =+WEEKNUM(A7) -> 14 | C7: =+TEXT(A7,"mmmm") -> March | D7: 34860 | F7: 0 | R7: =+SUM(I7:J7)/Weights!$B$3 -> 0 | S7: =+SUM(L7:M7)/Weights!$B$4 -> 0
A8: 46112 | B8: =+WEEKNUM(A8) -> 14 | C8: =+TEXT(A8,"mmmm") -> March | D8: 33480 | F8: 0 | R8: =+SUM(I8:J8)/Weights!$B$3 -> 0 | S8: =+SUM(L8:M8)/Weights!$B$4 -> 0
A9: 46113 | B9: =+WEEKNUM(A9) -> 14 | C9: =+TEXT(A9,"mmmm") -> April | D9: 52620 | F9: 0 | R9: =+SUM(I9:J9)/Weights!$B$3 -> 0 | S9: =+SUM(L9:M9)/Weights!$B$4 -> 0
A10: 46114 | B10: =+WEEKNUM(A10) -> 14 | C10: =+TEXT(A10,"mmmm") -> April | D10: 34080 | F10: 0 | R10: =+SUM(I10:J10)/Weights!$B$3 -> 0 | S10: =+SUM(L10:M10)/Weights!$B$4 -> 0
A11: 46118 | B11: =+WEEKNUM(A11) -> 15 | C11: =+TEXT(A11,"mmmm") -> April | D11: 32220 | F11: 0 | R11: =+SUM(I11:J11)/Weights!$B$3 -> 0 | S11: =+SUM(L11:M11)/Weights!$B$4 -> 0
A12: 46119 | B12: =+WEEKNUM(A12) -> 15 | C12: =+TEXT(A12,"mmmm") -> April | D12: 46380 | F12: 0 | R12: =+SUM(I12:J12)/Weights!$B$3 -> 0 | S12: =+SUM(L12:M12)/Weights!$B$4 -> 0
A13: 46120 | B13: =+WEEKNUM(A13) -> 15 | C13: =+TEXT(A13,"mmmm") -> April | D13: 47220 | F13: 0 | R13: =+SUM(I13:J13)/Weights!$B$3 -> 0 | S13: =+SUM(L13:M13)/Weights!$B$4 -> 0
A14: 46121 | B14: =+WEEKNUM(A14) -> 15 | C14: =+TEXT(A14,"mmmm") -> April | D14: 46020 | F14: 0 | R14: =+SUM(I14:J14)/Weights!$B$3 -> 0 | S14: =+SUM(L14:M14)/Weights!$B$4 -> 0
A15: 46125 | B15: =+WEEKNUM(A15) -> 16 | C15: =+TEXT(A15,"mmmm") -> April | D15: 42240 | F15: 0 | R15: =+SUM(I15:J15)/Weights!$B$3 -> 0 | S15: =+SUM(L15:M15)/Weights!$B$4 -> 0
A16: 46126 | B16: =+WEEKNUM(A16) -> 16 | C16: =+TEXT(A16,"mmmm") -> April | D16: 57960 | F16: 0 | R16: =+SUM(I16:J16)/Weights!$B$3 -> 0 | S16: =+SUM(L16:M16)/Weights!$B$4 -> 0
A17: 46127 | B17: =+WEEKNUM(A17) -> 16 | C17: =+TEXT(A17,"mmmm") -> April | D17: 54960 | F17: 0 | R17: =+SUM(I17:J17)/Weights!$B$3 -> 0 | S17: =+SUM(L17:M17)/Weights!$B$4 -> 0
A18: 46128 | B18: =+WEEKNUM(A18) -> 16 | C18: =+TEXT(A18,"mmmm") -> April | D18: 34800 | F18: 0 | R18: =+SUM(I18:J18)/Weights!$B$3 -> 0 | S18: =+SUM(L18:M18)/Weights!$B$4 -> 0
... A35: 46160 | B35: =+WEEKNUM(A35) -> 21 | C35: =+TEXT(A35,"mmmm") -> May | D35: 66480 | F35: 4320 | R35: =+SUM(I35:J35)/Weights!$B$3 -> 0 | S35: =+SUM(L35:M35)/Weights!$B$4 -> 0
A36: =WORKDAY.INTL(A35,1,,'Don''t Change'!$A$2:$A$7) -> 46161 | B36: =+WEEKNUM(A36) -> 21 | C36: =+TEXT(A36,"mmmm") -> May | D36: 30780 | F36: 0 | R36: =+SUM(I36:J36)/Weights!$B$3 -> 0 | S36: =+SUM(L36:M36)/Weights!$B$4 -> 0
A37: =WORKDAY.INTL(A36,1,,'Don''t Change'!$A$2:$A$7) -> 46162 | B37: =+WEEKNUM(A37) -> 21 | C37: =+TEXT(A37,"mmmm") -> May | D37: 49200 | F37: 8640 | R37: =+SUM(I37:J37)/Weights!$B$3 -> 0 | S37: =+SUM(L37:M37)/Weights!$B$4 -> 0
A38: =WORKDAY.INTL(A37,1,,'Don''t Change'!$A$2:$A$7) -> 46163 | B38: =+WEEKNUM(A38) -> 21 | C38: =+TEXT(A38,"mmmm") -> May | D38: 10380 | F38: 13664 | R38: =+SUM(I38:J38)/Weights!$B$3 -> 0 | S38: =+SUM(L38:M38)/Weights!$B$4 -> 0
A39: =WORKDAY.INTL(A38,1,,'Don''t Change'!$A$2:$A$7) -> 46164 | B39: =+WEEKNUM(A39) -> 21 | C39: =+TEXT(A39,"mmmm") -> May | D39: 0 | F39: 0 | R39: =+SUM(I39:J39)/Weights!$B$3 -> 0 | S39: =+SUM(L39:M39)/Weights!$B$4 -> 0
A40: =WORKDAY.INTL(A39,1,,'Don''t Change'!$A$2:$A$7) -> 46168 | B40: =+WEEKNUM(A40) -> 22 | C40: =+TEXT(A40,"mmmm") -> May | D40: 43980 | F40: 2112 | R40: =+SUM(I40:J40)/Weights!$B$3 -> 0 | S40: =+SUM(L40:M40)/Weights!$B$4 -> 0
A41: =WORKDAY.INTL(A40,1,,'Don''t Change'!$A$2:$A$7) -> 46169 | B41: =+WEEKNUM(A41) -> 22 | C41: =+TEXT(A41,"mmmm") -> May | D41: 37800 | F41: 0 | R41: =+SUM(I41:J41)/Weights!$B$3 -> 0 | S41: =+SUM(L41:M41)/Weights!$B$4 -> 0
A42: =WORKDAY.INTL(A41,1,,'Don''t Change'!$A$2:$A$7) -> 46170 | B42: =+WEEKNUM(A42) -> 22 | C42: =+TEXT(A42,"mmmm") -> May | D42: 63480 | F42: 2656 | I42: 250 | R42: =+SUM(I42:J42)/Weights!$B$3 -> 3950.6173 | S42: =+SUM(L42:M42)/Weights!$B$4 -> 0
A43: =WORKDAY.INTL(A42,1,,'Don''t Change'!$A$2:$A$7) -> 46171 | B43: =+WEEKNUM(A43) -> 22 | C43: =+TEXT(A43,"mmmm") -> May | D43: 34080 | F43: 3760 | R43: =+SUM(I43:J43)/Weights!$B$3 -> 0 | S43: =+SUM(L43:M43)/Weights!$B$4 -> 0
A44: =WORKDAY.INTL(A43,1,,'Don''t Change'!$A$2:$A$7) -> 46174 | B44: =+WEEKNUM(A44) -> 23 | C44: =+TEXT(A44,"mmmm") -> June | D44: 96000 | F44: =13*32 -> 416 | R44: =+SUM(I44:J44)/Weights!$B$3 -> 0 | S44: =+SUM(L44:M44)/Weights!$B$4 -> 0
A45: =WORKDAY.INTL(A44,1,,'Don''t Change'!$A$2:$A$7) -> 46175 | B45: =+WEEKNUM(A45) -> 23 | C45: =+TEXT(A45,"mmmm") -> June | D45: =909*60 -> 54540 | F45: 12100 | R45: =+SUM(I45:J45)/Weights!$B$3 -> 0 | S45: =+SUM(L45:M45)/Weights!$B$4 -> 0
A46: =WORKDAY.INTL(A45,1,,'Don''t Change'!$A$2:$A$7) -> 46176 | B46: =+WEEKNUM(A46) -> 23 | C46: =+TEXT(A46,"mmmm") -> June | D46: =792*60 -> 47520 | F46: =73*50 -> 3650 | R46: =+SUM(I46:J46)/Weights!$B$3 -> 0 | S46: =+SUM(L46:M46)/Weights!$B$4 -> 0
A47: =WORKDAY.INTL(A46,1,,'Don''t Change'!$A$2:$A$7) -> 46177 | B47: =+WEEKNUM(A47) -> 23 | C47: =+TEXT(A47,"mmmm") -> June | D47: =630*60 -> 37800 | F47: 0 | R47: =+SUM(I47:J47)/Weights!$B$3 -> 0 | S47: =+SUM(L47:M47)/Weights!$B$4 -> 0
A48: =WORKDAY.INTL(A47,1,,'Don''t Change'!$A$2:$A$7) -> 46178 | B48: =+WEEKNUM(A48) -> 23 | C48: =+TEXT(A48,"mmmm") -> June | D48: =1032*60 -> 61920 | F48: 0 | R48: =+SUM(I48:J48)/Weights!$B$3 -> 0 | S48: =+SUM(L48:M48)/Weights!$B$4 -> 0
A49: =WORKDAY.INTL(A48,1,,'Don''t Change'!$A$2:$A$7) -> 46181 | B49: =+WEEKNUM(A49) -> 24 | C49: =+TEXT(A49,"mmmm") -> June | D49: =1260*60+63*60+66*60 -> 83340 | F49: 0 | I49: 121 | R49: =+SUM(I49:J49)/Weights!$B$3 -> 1912.0988 | S49: =+SUM(L49:M49)/Weights!$B$4 -> 0
A50: =WORKDAY.INTL(A49,1,,'Don''t Change'!$A$2:$A$7) -> 46182 | B50: =+WEEKNUM(A50) -> 24 | C50: =+TEXT(A50,"mmmm") -> June | D50: =6*126*60+122*60 -> 52680 | F50: 0 | R50: =+SUM(I50:J50)/Weights!$B$3 -> 0 | S50: =+SUM(L50:M50)/Weights!$B$4 -> 0
A51: =WORKDAY.INTL(A50,1,,'Don''t Change'!$A$2:$A$7) -> 46183 | B51: =+WEEKNUM(A51) -> 24 | C51: =+TEXT(A51,"mmmm") -> June | D51: 50280 | F51: 0 | R51: =+SUM(I51:J51)/Weights!$B$3 -> 0 | S51: =+SUM(L51:M51)/Weights!$B$4 -> 0
A52: =WORKDAY.INTL(A51,1,,'Don''t Change'!$A$2:$A$7) -> 46184 | B52: =+WEEKNUM(A52) -> 24 | C52: =+TEXT(A52,"mmmm") -> June | D52: =196*60 -> 11760 | F52: =434*32 -> 13888 | R52: =+SUM(I52:J52)/Weights!$B$3 -> 0 | S52: =+SUM(L52:M52)/Weights!$B$4 -> 0
A53: =WORKDAY.INTL(A52,1,,'Don''t Change'!$A$2:$A$7) -> 46185 | B53: =+WEEKNUM(A53) -> 24 | C53: =+TEXT(A53,"mmmm") -> June | D53: 0 | F53: 0 | R53: =+SUM(I53:J53)/Weights!$B$3 -> 0 | S53: =+SUM(L53:M53)/Weights!$B$4 -> 0
A54: =WORKDAY.INTL(A53,1,,'Don''t Change'!$A$2:$A$7) -> 46188 | B54: =+WEEKNUM(A54) -> 25 | C54: =+TEXT(A54,"mmmm") -> June | D54: 29100 | F54: 12514 | R54: =+SUM(I54:J54)/Weights!$B$3 -> 0 | S54: =+SUM(L54:M54)/Weights!$B$4 -> 0
A55: =WORKDAY.INTL(A54,1,,'Don''t Change'!$A$2:$A$7) -> 46189 | B55: =+WEEKNUM(A55) -> 25 | C55: =+TEXT(A55,"mmmm") -> June | D55: =1765*60 -> 105900 | F55: 0 | R55: =+SUM(I55:J55)/Weights!$B$3 -> 0 | S55: =+SUM(L55:M55)/Weights!$B$4 -> 0
A56: =WORKDAY.INTL(A55,1,,'Don''t Change'!$A$2:$A$7) -> 46190 | B56: =+WEEKNUM(A56) -> 25 | C56: =+TEXT(A56,"mmmm") -> June | D56: =1058*60+4*126*60 -> 93720 | F56: =41*32 -> 1312 | R56: =+SUM(I56:J56)/Weights!$B$3 -> 0 | S56: =+SUM(L56:M56)/Weights!$B$4 -> 0
A57: =WORKDAY.INTL(A56,1,,'Don''t Change'!$A$2:$A$7) -> 46191 | B57: =+WEEKNUM(A57) -> 25 | C57: =+TEXT(A57,"mmmm") -> June | D57: 62352 | F57: =338*32 -> 10816 | R57: =+SUM(I57:J57)/Weights!$B$3 -> 0 | S57: =+SUM(L57:M57)/Weights!$B$4 -> 0
A58: =WORKDAY.INTL(A57,1,,'Don''t Change'!$A$2:$A$7) -> 46192 | B58: =+WEEKNUM(A58) -> 25 | C58: =+TEXT(A58,"mmmm") -> June | D58: 0 | F58: =120*32 -> 3840 | R58: =+SUM(I58:J58)/Weights!$B$3 -> 0 | S58: =+SUM(L58:M58)/Weights!$B$4 -> 0
A59: =WORKDAY.INTL(A58,1,,'Don''t Change'!$A$2:$A$7) -> 46195 | B59: =+WEEKNUM(A59) -> 26 | C59: =+TEXT(A59,"mmmm") -> June | D59: =1207*60 -> 72420 | F59: =185*32 -> 5920 | R59: =+SUM(I59:J59)/Weights!$B$3 -> 0 | S59: =+SUM(L59:M59)/Weights!$B$4 -> 0
A60: =WORKDAY.INTL(A59,1,,'Don''t Change'!$A$2:$A$7) -> 46196 | B60: =+WEEKNUM(A60) -> 26 | C60: =+TEXT(A60,"mmmm") -> June | D60: =+(7*126+64)*60 -> 56760 | F60: =241*32 -> 7712 | I60: 161 | L60: 52 | R60: =+SUM(I60:J60)/Weights!$B$3 -> 2544.1975 | S60: =+SUM(L60:M60)/Weights!$B$4 -> 332.8
A61: =WORKDAY.INTL(A60,1,,'Don''t Change'!$A$2:$A$7) -> 46197 | B61: =+WEEKNUM(A61) -> 26 | C61: =+TEXT(A61,"mmmm") -> June | D61: =1289*60 -> 77340 | F61: =391*32 -> 12512 | R61: =+SUM(I61:J61)/Weights!$B$3 -> 0 | S61: =+SUM(L61:M61)/Weights!$B$4 -> 0
A62: =WORKDAY.INTL(A61,1,,'Don''t Change'!$A$2:$A$7) -> 46198 | B62: =+WEEKNUM(A62) -> 26 | C62: =+TEXT(A62,"mmmm") -> June | D62: =1616*60 -> 96960 | F62: =60*32 -> 1920 | R62: =+SUM(I62:J62)/Weights!$B$3 -> 0 | S62: =+SUM(L62:M62)/Weights!$B$4 -> 0
A63: =WORKDAY.INTL(A62,1,,'Don''t Change'!$A$2:$A$7) -> 46199 | B63: =+WEEKNUM(A63) -> 26 | C63: =+TEXT(A63,"mmmm") -> June | D63: 0 | F63: 0 | R63: =+SUM(I63:J63)/Weights!$B$3 -> 0 | S63: =+SUM(L63:M63)/Weights!$B$4 -> 0
A64: =WORKDAY.INTL(A63,1,,'Don''t Change'!$A$2:$A$7) -> 46202 | B64: =+WEEKNUM(A64) -> 27 | C64: =+TEXT(A64,"mmmm") -> June | D64: =1008*60 -> 60480 | F64: =447*32 -> 14304 | R64: =+SUM(I64:J64)/Weights!$B$3 -> 0 | S64: =+SUM(L64:M64)/Weights!$B$4 -> 0
A65: =WORKDAY.INTL(A64,1,,'Don''t Change'!$A$2:$A$7) -> 46203 | B65: =+WEEKNUM(A65) -> 27 | C65: =+TEXT(A65,"mmmm") -> June | D65: =1513*60 -> 90780 | F65: =472*32 -> 15104 | I65: 80 | L65: 95 | R65: =+SUM(I65:J65)/Weights!$B$3 -> 1264.1975 | S65: =+SUM(L65:M65)/Weights!$B$4 -> 608
A66: =WORKDAY.INTL(A65,1,,'Don''t Change'!$A$2:$A$7) -> 46204 | B66: =+WEEKNUM(A66) -> 27 | C66: =+TEXT(A66,"mmmm") -> July | D66: =1134*60 -> 68040 | F66: =356*32 -> 11392 | R66: =+SUM(I66:J66)/Weights!$B$3 -> 0 | S66: =+SUM(L66:M66)/Weights!$B$4 -> 0
A67: 46205 | B67: =+WEEKNUM(A67) -> 27 | C67: =+TEXT(A67,"mmmm") -> July | D67: =1501*60 -> 90060 | F67: =547*32 -> 17504 | R67: =+SUM(I67:J67)/Weights!$B$3 -> 0 | S67: =+SUM(L67:M67)/Weights!$B$4 -> 0
A68: =WORKDAY.INTL(A67,1,,'Don''t Change'!$A$2:$A$7) -> 46206 | B68: =+WEEKNUM(A68) -> 27 | C68: =+TEXT(A68,"mmmm") -> July | D68: 0 | F68: 0 | R68: =+SUM(I68:J68)/Weights!$B$3 -> 0 | S68: =+SUM(L68:M68)/Weights!$B$4 -> 0
A69: =WORKDAY.INTL(A68,1,,'Don''t Change'!$A$2:$A$7) -> 46209 | B69: =+WEEKNUM(A69) -> 28 | C69: =+TEXT(A69,"mmmm") -> July | D69: =743*60 -> 44580 | F69: =242*35 -> 8470 | R69: =+SUM(I69:J69)/Weights!$B$3 -> 0 | S69: =+SUM(L69:M69)/Weights!$B$4 -> 0
A70: =WORKDAY.INTL(A69,1,,'Don''t Change'!$A$2:$A$7) -> 46210 | B70: =+WEEKNUM(A70) -> 28 | C70: =+TEXT(A70,"mmmm") -> July | D70: =1260*60 -> 75600 | F70: =270*32 -> 8640 | R70: =+SUM(I70:J70)/Weights!$B$3 -> 0 | S70: =+SUM(L70:M70)/Weights!$B$4 -> 0
A71: =WORKDAY.INTL(A70,1,,'Don''t Change'!$A$2:$A$7) -> 46211 | B71: =+WEEKNUM(A71) -> 28 | C71: =+TEXT(A71,"mmmm") -> July | D71: =508*60 -> 30480 | F71: =(135+45+108)*32 -> 9216 | I71: 310 | L71: =68+24+156+48 -> 296 | R71: =+SUM(I71:J71)/Weights!$B$3 -> 4898.7654 | S71: =+SUM(L71:M71)/Weights!$B$4 -> 1894.4
A72: =WORKDAY.INTL(A71,1,,'Don''t Change'!$A$2:$A$7) -> 46212 | B72: =+WEEKNUM(A72) -> 28 | C72: =+TEXT(A72,"mmmm") -> July | F72: =765*35 -> 26775 | R72: =+SUM(I72:J72)/Weights!$B$3 -> 0 | S72: =+SUM(L72:M72)/Weights!$B$4 -> 0
A73: =WORKDAY.INTL(A72,1,,'Don''t Change'!$A$2:$A$7) -> 46213 | B73: =+WEEKNUM(A73) -> 28 | C73: =+TEXT(A73,"mmmm") -> July | D73: 0 | F73: 0 | R73: =+SUM(I73:J73)/Weights!$B$3 -> 0 | S73: =+SUM(L73:M73)/Weights!$B$4 -> 0
A74: =WORKDAY.INTL(A73,1,,'Don''t Change'!$A$2:$A$7) -> 46216 | B74: =+WEEKNUM(A74) -> 29 | C74: =+TEXT(A74,"mmmm") -> July | D74: =370*225 -> 83250 | F74: 10080 | R74: =+SUM(I74:J74)/Weights!$B$3 -> 0 | S74: =+SUM(L74:M74)/Weights!$B$4 -> 0
A75: =WORKDAY.INTL(A74,1,,'Don''t Change'!$A$2:$A$7) -> 46217 | B75: =+WEEKNUM(A75) -> 29 | C75: =+TEXT(A75,"mmmm") -> July | D75: 0 | F75: 0 | R75: =+SUM(I75:J75)/Weights!$B$3 -> 0 | S75: =+SUM(L75:M75)/Weights!$B$4 -> 0
A76: =WORKDAY.INTL(A75,1,,'Don''t Change'!$A$2:$A$7) -> 46218 | B76: =+WEEKNUM(A76) -> 29 | C76: =+TEXT(A76,"mmmm") -> July | D76: 0 | F76: 0 | R76: =+SUM(I76:J76)/Weights!$B$3 -> 0 | S76: =+SUM(L76:M76)/Weights!$B$4 -> 0
A77: =WORKDAY.INTL(A76,1,,'Don''t Change'!$A$2:$A$7) -> 46219 | B77: =+WEEKNUM(A77) -> 29 | C77: =+TEXT(A77,"mmmm") -> July | D77: 0 | F77: =176*35 -> 6160 | R77: =+SUM(I77:J77)/Weights!$B$3 -> 0 | S77: =+SUM(L77:M77)/Weights!$B$4 -> 0
A78: =WORKDAY.INTL(A77,1,,'Don''t Change'!$A$2:$A$7) -> 46220 | B78: =+WEEKNUM(A78) -> 29 | C78: =+TEXT(A78,"mmmm") -> July | D78: 0 | F78: 0 | R78: =+SUM(I78:J78)/Weights!$B$3 -> 0 | S78: =+SUM(L78:M78)/Weights!$B$4 -> 0
A79: =WORKDAY.INTL(A78,1,,'Don''t Change'!$A$2:$A$7) -> 46223 | B79: =+WEEKNUM(A79) -> 30 | C79: =+TEXT(A79,"mmmm") -> July | D79: 0 | F79: 0 | R79: =+SUM(I79:J79)/Weights!$B$3 -> 0 | S79: =+SUM(L79:M79)/Weights!$B$4 -> 0
A80: =WORKDAY.INTL(A79,1,,'Don''t Change'!$A$2:$A$7) -> 46224 | B80: =+WEEKNUM(A80) -> 30 | C80: =+TEXT(A80,"mmmm") -> July | D80: 0 | F80: 21440 | L80: 100 | R80: =+SUM(I80:J80)/Weights!$B$3 -> 0 | S80: =+SUM(L80:M80)/Weights!$B$4 -> 640
A81: =WORKDAY.INTL(A80,1,,'Don''t Change'!$A$2:$A$7) -> 46225 | B81: =+WEEKNUM(A81) -> 30 | C81: =+TEXT(A81,"mmmm") -> July | D81: =630*60 -> 37800 | F81: =1022*32 -> 32704 | R81: =+SUM(I81:J81)/Weights!$B$3 -> 0 | S81: =+SUM(L81:M81)/Weights!$B$4 -> 0
A82: =WORKDAY.INTL(A81,1,,'Don''t Change'!$A$2:$A$7) -> 46226 | B82: =+WEEKNUM(A82) -> 30 | C82: =+TEXT(A82,"mmmm") -> July | D82: =1008*60 -> 60480 | F82: =759*32 -> 24288 | L82: 396 | R82: =+SUM(I82:J82)/Weights!$B$3 -> 0 | S82: =+SUM(L82:M82)/Weights!$B$4 -> 2534.4
A83: =WORKDAY.INTL(A82,1,,'Don''t Change'!$A$2:$A$7) -> 46227 | B83: =+WEEKNUM(A83) -> 30 | C83: =+TEXT(A83,"mmmm") -> July | D83: =526*60+247*225 -> 87135 | F83: =59*32 -> 1888 | I83: 147 | R83: =+SUM(I83:J83)/Weights!$B$3 -> 2322.963 | S83: =+SUM(L83:M83)/Weights!$B$4 -> 0
A84: =WORKDAY.INTL(A83,1,,'Don''t Change'!$A$2:$A$7) -> 46230 | B84: =+WEEKNUM(A84) -> 31 | C84: =+TEXT(A84,"mmmm") -> July | D84: =29*60+(126*5)*60+102*225 -> 62490 | F84: =606*32 -> 19392 | R84: =+SUM(I84:J84)/Weights!$B$3 -> 0 | S84: =+SUM(L84:M84)/Weights!$B$4 -> 0
A85: =WORKDAY.INTL(A84,1,,'Don''t Change'!$A$2:$A$7) -> 46231 | B85: =+WEEKNUM(A85) -> 31 | C85: =+TEXT(A85,"mmmm") -> July | D85: =231*225+880*60 -> 104775 | F85: =842*32 -> 26944 | I85: 198 | L85: 42 | R85: =+SUM(I85:J85)/Weights!$B$3 -> 3128.8889 | S85: =+SUM(L85:M85)/Weights!$B$4 -> 268.8
A86: =WORKDAY.INTL(A85,1,,'Don''t Change'!$A$2:$A$7) -> 46232 | B86: =+WEEKNUM(A86) -> 31 | C86: =+TEXT(A86,"mmmm") -> July | D86: =972*60 -> 58320 | F86: =705*32 -> 22560 | I86: =52+40+34+20 -> 146 | R86: =+SUM(I86:J86)/Weights!$B$3 -> 2307.1605 | S86: =+SUM(L86:M86)/Weights!$B$4 -> 0
A87: =WORKDAY.INTL(A86,1,,'Don''t Change'!$A$2:$A$7) -> 46233 | B87: =+WEEKNUM(A87) -> 31 | C87: =+TEXT(A87,"mmmm") -> July | D87: =756*60 -> 45360 | F87: =266*32 -> 8512 | L87: 431.25 | R87: =+SUM(I87:J87)/Weights!$B$3 -> 0 | S87: =+SUM(L87:M87)/Weights!$B$4 -> 2760
A88: =WORKDAY.INTL(A87,1,,'Don''t Change'!$A$2:$A$7) -> 46234 | B88: =+WEEKNUM(A88) -> 31 | C88: =+TEXT(A88,"mmmm") -> July | D88: 0 | F88: 0 | R88: =+SUM(I88:J88)/Weights!$B$3 -> 0 | S88: =+SUM(L88:M88)/Weights!$B$4 -> 0
A89: =WORKDAY.INTL(A88,1,,'Don''t Change'!$A$2:$A$7) -> 46237 | B89: =+WEEKNUM(A89) -> 32 | C89: =+TEXT(A89,"mmmm") -> August | D89: =753*60+246*60 -> 59940 | F89: =675*32 -> 21600 | I89: =36+18 -> 54 | L89: 256 | R89: =+SUM(I89:J89)/Weights!$B$3 -> 853.33333 | S89: =+SUM(L89:M89)/Weights!$B$4 -> 1638.4
A90: =WORKDAY.INTL(A89,1,,'Don''t Change'!$A$2:$A$7) -> 46238 | B90: =+WEEKNUM(A90) -> 32 | C90: =+TEXT(A90,"mmmm") -> August | D90: =1313*60 -> 78780 | F90: =810*32 -> 25920 | I90: 72 | L90: =50+60+62+92 -> 264 | R90: =+SUM(I90:J90)/Weights!$B$3 -> 1137.7778 | S90: =+SUM(L90:M90)/Weights!$B$4 -> 1689.6
A91: =WORKDAY.INTL(A90,1,,'Don''t Change'!$A$2:$A$7) -> 46239 | B91: =+WEEKNUM(A91) -> 32 | C91: =+TEXT(A91,"mmmm") -> August | D91: =882*60 -> 52920 | F91: =675*32 -> 21600 | I91: 32 | L91: =24+28+48+34 -> 134 | R91: =+SUM(I91:J91)/Weights!$B$3 -> 505.67901 | S91: =+SUM(L91:M91)/Weights!$B$4 -> 857.6
A92: =WORKDAY.INTL(A91,1,,'Don''t Change'!$A$2:$A$7) -> 46240 | B92: =+WEEKNUM(A92) -> 32 | C92: =+TEXT(A92,"mmmm") -> August | D92: =726*60 -> 43560 | F92: =945*32 -> 30240 | L92: =24+50+44 -> 118 | R92: =+SUM(I92:J92)/Weights!$B$3 -> 0 | S92: =+SUM(L92:M92)/Weights!$B$4 -> 755.2
A93: =WORKDAY.INTL(A92,1,,'Don''t Change'!$A$2:$A$7) -> 46241 | B93: =+WEEKNUM(A93) -> 32 | C93: =+TEXT(A93,"mmmm") -> August | D93: 0 | F93: 0 | R93: =+SUM(I93:J93)/Weights!$B$3 -> 0 | S93: =+SUM(L93:M93)/Weights!$B$4 -> 0
A94: =WORKDAY.INTL(A93,1,,'Don''t Change'!$A$2:$A$7) -> 46244 | B94: =+WEEKNUM(A94) -> 33 | C94: =+TEXT(A94,"mmmm") -> August | D94: =1063*60 -> 63780 | F94: =948*32 -> 30336 | I94: 42 | L94: =106+42+92 -> 240 | R94: =+SUM(I94:J94)/Weights!$B$3 -> 663.7037 | S94: =+SUM(L94:M94)/Weights!$B$4 -> 1536
A95: =WORKDAY.INTL(A94,1,,'Don''t Change'!$A$2:$A$7) -> 46245 | B95: =+WEEKNUM(A95) -> 33 | C95: =+TEXT(A95,"mmmm") -> August | D95: =801*60 -> 48060 | F95: =1125*32+91*50 -> 40550 | L95: 74 | R95: =+SUM(I95:J95)/Weights!$B$3 -> 0 | S95: =+SUM(L95:M95)/Weights!$B$4 -> 473.6
A96: =WORKDAY.INTL(A95,1,,'Don''t Change'!$A$2:$A$7) -> 46246 | B96: =+WEEKNUM(A96) -> 33 | C96: =+TEXT(A96,"mmmm") -> August | D96: =1008*60 -> 60480 | F96: =576*50 -> 28800 | I96: 56 | R96: =+SUM(I96:J96)/Weights!$B$3 -> 884.93827 | S96: =+SUM(L96:M96)/Weights!$B$4 -> 0
A97: =WORKDAY.INTL(A96,1,,'Don''t Change'!$A$2:$A$7) -> 46247 | B97: =+WEEKNUM(A97) -> 33 | C97: =+TEXT(A97,"mmmm") -> August | D97: =422*60 -> 25320 | F97: =401*32+110*50 -> 18332 | R97: =+SUM(I97:J97)/Weights!$B$3 -> 0 | S97: =+SUM(L97:M97)/Weights!$B$4 -> 0
A98: =WORKDAY.INTL(A97,1,,'Don''t Change'!$A$2:$A$7) -> 46248 | B98: =+WEEKNUM(A98) -> 33 | C98: =+TEXT(A98,"mmmm") -> August | D98: 0 | F98: 0 | R98: =+SUM(I98:J98)/Weights!$B$3 -> 0 | S98: =+SUM(L98:M98)/Weights!$B$4 -> 0
A99: =WORKDAY.INTL(A98,1,,'Don''t Change'!$A$2:$A$7) -> 46251 | B99: =+WEEKNUM(A99) -> 34 | C99: =+TEXT(A99,"mmmm") -> August | D99: 30240 | F99: 21600 | I99: 20 | R99: =+SUM(I99:J99)/Weights!$B$3 -> 316.04938 | S99: =+SUM(L99:M99)/Weights!$B$4 -> 0
A100: =WORKDAY.INTL(A99,1,,'Don''t Change'!$A$2:$A$7) -> 46252 | B100: =+WEEKNUM(A100) -> 34 | C100: =+TEXT(A100,"mmmm") -> August | D100: 15120 | F100: 22880 | R100: =+SUM(I100:J100)/Weights!$B$3 -> 0 | S100: =+SUM(L100:M100)/Weights!$B$4 -> 0
A101: =WORKDAY.INTL(A100,1,,'Don''t Change'!$A$2:$A$7) -> 46253 | B101: =+WEEKNUM(A101) -> 34 | C101: =+TEXT(A101,"mmmm") -> August | D101: 99300 | F101: 8576 | R101: =+SUM(I101:J101)/Weights!$B$3 -> 0 | S101: =+SUM(L101:M101)/Weights!$B$4 -> 0
A102: =WORKDAY.INTL(A101,1,,'Don''t Change'!$A$2:$A$7) -> 46254 | B102: =+WEEKNUM(A102) -> 34 | C102: =+TEXT(A102,"mmmm") -> August | D102: 0 | F102: 0 | R102: =+SUM(I102:J102)/Weights!$B$3 -> 0 | S102: =+SUM(L102:M102)/Weights!$B$4 -> 0
A103: =WORKDAY.INTL(A102,1,,'Don''t Change'!$A$2:$A$7) -> 46255 | B103: =+WEEKNUM(A103) -> 34 | C103: =+TEXT(A103,"mmmm") -> August | D103: 0 | F103: 0 | R103: =+SUM(I103:J103)/Weights!$B$3 -> 0 | S103: =+SUM(L103:M103)/Weights!$B$4 -> 0
A104: =WORKDAY.INTL(A103,1,,'Don''t Change'!$A$2:$A$7) -> 46258 | B104: =+WEEKNUM(A104) -> 35 | C104: =+TEXT(A104,"mmmm") -> August | D104: 0 | F104: =945*32 -> 30240 | R104: =+SUM(I104:J104)/Weights!$B$3 -> 0 | S104: =+SUM(L104:M104)/Weights!$B$4 -> 0
A105: =WORKDAY.INTL(A104,1,,'Don''t Change'!$A$2:$A$7) -> 46259 | B105: =+WEEKNUM(A105) -> 35 | C105: =+TEXT(A105,"mmmm") -> August | D105: =1554*60 -> 93240 | F105: =768*32 -> 24576 | L105: 388 | R105: =+SUM(I105:J105)/Weights!$B$3 -> 0 | S105: =+SUM(L105:M105)/Weights!$B$4 -> 2483.2
A106: =WORKDAY.INTL(A105,1,,'Don''t Change'!$A$2:$A$7) -> 46260 | B106: =+WEEKNUM(A106) -> 35 | C106: =+TEXT(A106,"mmmm") -> August | D106: =1442*60 -> 86520 | F106: =200*56 -> 11200 | I106: =194+232 -> 426 | R106: =+SUM(I106:J106)/Weights!$B$3 -> 6731.8519 | S106: =+SUM(L106:M106)/Weights!$B$4 -> 0
A107: =WORKDAY.INTL(A106,1,,'Don''t Change'!$A$2:$A$7) -> 46261 | B107: =+WEEKNUM(A107) -> 35 | C107: =+TEXT(A107,"mmmm") -> August | D107: =8*126*60 -> 60480 | F107: =607*56 -> 33992 | R107: =+SUM(I107:J107)/Weights!$B$3 -> 0 | S107: =+SUM(L107:M107)/Weights!$B$4 -> 0
A108: =WORKDAY.INTL(A107,1,,'Don''t Change'!$A$2:$A$7) -> 46262 | B108: =+WEEKNUM(A108) -> 35 | C108: =+TEXT(A108,"mmmm") -> August | D108: =823*60 -> 49380 | F108: =410*56 -> 22960 | L108: 70 | R108: =+SUM(I108:J108)/Weights!$B$3 -> 0 | S108: =+SUM(L108:M108)/Weights!$B$4 -> 448
A109: =WORKDAY.INTL(A108,1,,'Don''t Change'!$A$2:$A$7) -> 46265 | B109: =+WEEKNUM(A109) -> 36 | C109: =+TEXT(A109,"mmmm") -> August | D109: =95*250 -> 23750 | F109: =200*56 -> 11200 | I109: 230 | L109: 102 | R109: =+SUM(I109:J109)/Weights!$B$3 -> 3634.5679 | S109: =+SUM(L109:M109)/Weights!$B$4 -> 652.8
A110: =WORKDAY.INTL(A109,1,,'Don''t Change'!$A$2:$A$7) -> 46266 | B110: =+WEEKNUM(A110) -> 36 | C110: =+TEXT(A110,"mmmm") -> September | D110: =77*240+1008*60 -> 78960 | F110: =285*32+254*56 -> 23344 | I110: 110 | L110: 111 | R110: =+SUM(I110:J110)/Weights!$B$3 -> 1738.2716 | S110: =+SUM(L110:M110)/Weights!$B$4 -> 710.4
A111: =WORKDAY.INTL(A110,1,,'Don''t Change'!$A$2:$A$7) -> 46267 | B111: =+WEEKNUM(A111) -> 36 | C111: =+TEXT(A111,"mmmm") -> September | D111: =105*250+126*60 -> 33810 | F111: 0 | R111: =+SUM(I111:J111)/Weights!$B$3 -> 0 | S111: =+SUM(L111:M111)/Weights!$B$4 -> 0
A112: =WORKDAY.INTL(A111,1,,'Don''t Change'!$A$2:$A$7) -> 46268 | B112: =+WEEKNUM(A112) -> 36 | C112: =+TEXT(A112,"mmmm") -> September | D112: =780*240+132*250+123*60 -> 227580 | F112: =7560 -> 7560 | R112: =+SUM(I112:J112)/Weights!$B$3 -> 0 | S112: =+SUM(L112:M112)/Weights!$B$4 -> 0
A113: =WORKDAY.INTL(A112,1,,'Don''t Change'!$A$2:$A$7) -> 46269 | B113: =+WEEKNUM(A113) -> 36 | C113: =+TEXT(A113,"mmmm") -> September | D113: 0 | F113: 0 | R113: =+SUM(I113:J113)/Weights!$B$3 -> 0 | S113: =+SUM(L113:M113)/Weights!$B$4 -> 0
A114: =WORKDAY.INTL(A113,1,,'Don''t Change'!$A$2:$A$7) -> 46273 | B114: =+WEEKNUM(A114) -> 37 | C114: =+TEXT(A114,"mmmm") -> September | D114: 93360 | F114: 0 | I114: 78 | R114: =+SUM(I114:J114)/Weights!$B$3 -> 1232.5926 | S114: =+SUM(L114:M114)/Weights!$B$4 -> 0
A115: =WORKDAY.INTL(A114,1,,'Don''t Change'!$A$2:$A$7) -> 46274 | B115: =+WEEKNUM(A115) -> 37 | C115: =+TEXT(A115,"mmmm") -> September | D115: 0 | F115: 0 | R115: =+SUM(I115:J115)/Weights!$B$3 -> 0 | S115: =+SUM(L115:M115)/Weights!$B$4 -> 0
A116: =WORKDAY.INTL(A115,1,,'Don''t Change'!$A$2:$A$7) -> 46275 | B116: =+WEEKNUM(A116) -> 37 | C116: =+TEXT(A116,"mmmm") -> September | D116: 0 | F116: 0 | R116: =+SUM(I116:J116)/Weights!$B$3 -> 0 | S116: =+SUM(L116:M116)/Weights!$B$4 -> 0
...

Sheet Daily Summary Old
A1: Date | B1: Week | C1: Month | D1: Period | E1: SD Produced | F1: Bao Produced | G1: SD Waste LBS | H1: Bao Waste LBS | I1: SD Packed | J1: Bao Packed | L1: Running Unpacked SD | M1: Running Unpacked Bao | N1: SD Good Pounds Prod | O1: Bao Good Pounds Prod | Q1: Eaches Packed
A2: =+'Raw Data - Production'!A7 -> 46111 | B2: =+WEEKNUM(A2) -> 14 | C2: =+TEXT(A2,"mmmm") -> March | D2: P4 | E2: =+'Raw Data - Production'!D7+'Raw Data - Production'!E7+'Raw Data - Production'!F7 -> 34860 | F2: =+'Raw Data - Production'!G7+'Raw Data - Production'!H7+'Raw Data - Production'!I7 -> 0 | G2: =+'Raw Data - Production'!K7+'Raw Data - Production'!L7+'Raw Data - Packing'!I7 -> 0 | H2: =+'Raw Data - Production'!N7+'Raw Data - Production'!O7+'Raw Data - Production'!P7+'Raw Data - Packing'!L7 -> 0 | I2: =SUMIF('Raw Data - Packing'!A:A,A2,'Raw Data - Packing'!D:D) -> 34860 | J2: =SUMIF('Raw Data - Packing'!A:A,A2,'Raw Data - Packing'!F:F) -> 0 | N2: =+E2*Weights!$B$2 -> 2205.9844 | O2: =+F2*Weights!$B$4 -> 0 | Q2: =I2+J2 -> 34860 | R2: 14 | S2: =SUMIF(B:B,R2,Q:Q) -> 155040
A3: =+'Raw Data - Production'!A8 -> 46112 | B3: =+WEEKNUM(A3) -> 14 | C3: =+TEXT(A3,"mmmm") -> March | D3: P4 | E3: =+'Raw Data - Production'!D8+'Raw Data - Production'!E8+'Raw Data - Production'!F8 -> 33480 | F3: =+'Raw Data - Production'!G8+'Raw Data - Production'!H8+'Raw Data - Production'!I8 -> 0 | G3: =+'Raw Data - Production'!K8+'Raw Data - Production'!L8+'Raw Data - Packing'!I8 -> 0 | H3: =+'Raw Data - Production'!N8+'Raw Data - Production'!O8+'Raw Data - Production'!P8+'Raw Data - Packing'!L8 -> 0 | I3: =SUMIF('Raw Data - Packing'!A:A,A3,'Raw Data - Packing'!D:D) -> 33480 | J3: =SUMIF('Raw Data - Packing'!A:A,A3,'Raw Data - Packing'!F:F) -> 0 | N3: =+E3*Weights!$B$2 -> 2118.6562 | O3: =+F3*Weights!$B$4 -> 0 | Q3: =I3+J3 -> 33480 | R3: 15 | S3: =SUMIF(B:B,R3,Q:Q) -> 171840
A4: =+'Raw Data - Production'!A9 -> 46113 | B4: =+WEEKNUM(A4) -> 14 | C4: =+TEXT(A4,"mmmm") -> April | D4: P4 | E4: =+'Raw Data - Production'!D9+'Raw Data - Production'!E9+'Raw Data - Production'!F9 -> 52620 | F4: =+'Raw Data - Production'!G9+'Raw Data - Production'!H9+'Raw Data - Production'!I9 -> 0 | G4: =+'Raw Data - Production'!K9+'Raw Data - Production'!L9+'Raw Data - Packing'!I9 -> 0 | H4: =+'Raw Data - Production'!N9+'Raw Data - Production'!O9+'Raw Data - Production'!P9+'Raw Data - Packing'!L9 -> 0 | I4: =SUMIF('Raw Data - Packing'!A:A,A4,'Raw Data - Packing'!D:D) -> 52620 | J4: =SUMIF('Raw Data - Packing'!A:A,A4,'Raw Data - Packing'!F:F) -> 0 | N4: =+E4*Weights!$B$2 -> 3329.8594 | O4: =+F4*Weights!$B$4 -> 0 | Q4: =I4+J4 -> 52620 | R4: 16 | S4: =SUMIF(B:B,R4,Q:Q) -> 189960
A5: =+'Raw Data - Production'!A10 -> 46114 | B5: =+WEEKNUM(A5) -> 14 | C5: =+TEXT(A5,"mmmm") -> April | D5: P4 | E5: =+'Raw Data - Production'!D10+'Raw Data - Production'!E10+'Raw Data - Production'!F10 -> 34080 | F5: =+'Raw Data - Production'!G10+'Raw Data - Production'!H10+'Raw Data - Production'!I10 -> 0 | G5: =+'Raw Data - Production'!K10+'Raw Data - Production'!L10+'Raw Data - Packing'!I10 -> 0 | H5: =+'Raw Data - Production'!N10+'Raw Data - Production'!O10+'Raw Data - Production'!P10+'Raw Data - Packing'!L10 -> 0 | I5: =SUMIF('Raw Data - Packing'!A:A,A5,'Raw Data - Packing'!D:D) -> 34080 | J5: =SUMIF('Raw Data - Packing'!A:A,A5,'Raw Data - Packing'!F:F) -> 0 | N5: =+E5*Weights!$B$2 -> 2156.625 | O5: =+F5*Weights!$B$4 -> 0 | Q5: =I5+J5 -> 34080 | R5: 17 | S5: =SUMIF(B:B,R5,Q:Q) -> 246840
A6: =+'Raw Data - Production'!A11 -> 46118 | B6: =+WEEKNUM(A6) -> 15 | C6: =+TEXT(A6,"mmmm") -> April | D6: P4 | E6: =+'Raw Data - Production'!D11+'Raw Data - Production'!E11+'Raw Data - Production'!F11 -> 32220 | F6: =+'Raw Data - Production'!G11+'Raw Data - Production'!H11+'Raw Data - Production'!I11 -> 0 | G6: =+'Raw Data - Production'!K11+'Raw Data - Production'!L11+'Raw Data - Packing'!I11 -> 0 | H6: =+'Raw Data - Production'!N11+'Raw Data - Production'!O11+'Raw Data - Production'!P11+'Raw Data - Packing'!L11 -> 0 | I6: =SUMIF('Raw Data - Packing'!A:A,A6,'Raw Data - Packing'!D:D) -> 32220 | J6: =SUMIF('Raw Data - Packing'!A:A,A6,'Raw Data - Packing'!F:F) -> 0 | N6: =+E6*Weights!$B$2 -> 2038.9219 | O6: =+F6*Weights!$B$4 -> 0 | Q6: =I6+J6 -> 32220 | R6: 18 | S6: =SUMIF(B:B,R6,Q:Q) -> 232710
A7: =+'Raw Data - Production'!A12 -> 46119 | B7: =+WEEKNUM(A7) -> 15 | C7: =+TEXT(A7,"mmmm") -> April | D7: P4 | E7: =+'Raw Data - Production'!D12+'Raw Data - Production'!E12+'Raw Data - Production'!F12 -> 46380 | F7: =+'Raw Data - Production'!G12+'Raw Data - Production'!H12+'Raw Data - Production'!I12 -> 0 | G7: =+'Raw Data - Production'!K12+'Raw Data - Production'!L12+'Raw Data - Packing'!I12 -> 0 | H7: =+'Raw Data - Production'!N12+'Raw Data - Production'!O12+'Raw Data - Production'!P12+'Raw Data - Packing'!L12 -> 0 | I7: =SUMIF('Raw Data - Packing'!A:A,A7,'Raw Data - Packing'!D:D) -> 46380 | J7: =SUMIF('Raw Data - Packing'!A:A,A7,'Raw Data - Packing'!F:F) -> 0 | N7: =+E7*Weights!$B$2 -> 2934.9844 | O7: =+F7*Weights!$B$4 -> 0 | Q7: =I7+J7 -> 46380 | R7: 19 | S7: =SUMIF(B:B,R7,Q:Q) -> 235500
A8: =+'Raw Data - Production'!A13 -> 46120 | B8: =+WEEKNUM(A8) -> 15 | C8: =+TEXT(A8,"mmmm") -> April | D8: P4 | E8: =+'Raw Data - Production'!D13+'Raw Data - Production'!E13+'Raw Data - Production'!F13 -> 47220 | F8: =+'Raw Data - Production'!G13+'Raw Data - Production'!H13+'Raw Data - Production'!I13 -> 0 | G8: =+'Raw Data - Production'!K13+'Raw Data - Production'!L13+'Raw Data - Packing'!I13 -> 0 | H8: =+'Raw Data - Production'!N13+'Raw Data - Production'!O13+'Raw Data - Production'!P13+'Raw Data - Packing'!L13 -> 0 | I8: =SUMIF('Raw Data - Packing'!A:A,A8,'Raw Data - Packing'!D:D) -> 47220 | J8: =SUMIF('Raw Data - Packing'!A:A,A8,'Raw Data - Packing'!F:F) -> 0 | N8: =+E8*Weights!$B$2 -> 2988.1406 | O8: =+F8*Weights!$B$4 -> 0 | Q8: =I8+J8 -> 47220 | R8: 20 | S8: =SUMIF(B:B,R8,Q:Q) -> 229320
A9: =+'Raw Data - Production'!A14 -> 46121 | B9: =+WEEKNUM(A9) -> 15 | C9: =+TEXT(A9,"mmmm") -> April | D9: P4 | E9: =+'Raw Data - Production'!D14+'Raw Data - Production'!E14+'Raw Data - Production'!F14 -> 46020 | F9: =+'Raw Data - Production'!G14+'Raw Data - Production'!H14+'Raw Data - Production'!I14 -> 0 | G9: =+'Raw Data - Production'!K14+'Raw Data - Production'!L14+'Raw Data - Packing'!I14 -> 0 | H9: =+'Raw Data - Production'!N14+'Raw Data - Production'!O14+'Raw Data - Production'!P14+'Raw Data - Packing'!L14 -> 0 | I9: =SUMIF('Raw Data - Packing'!A:A,A9,'Raw Data - Packing'!D:D) -> 46020 | J9: =SUMIF('Raw Data - Packing'!A:A,A9,'Raw Data - Packing'!F:F) -> 0 | N9: =+E9*Weights!$B$2 -> 2912.2031 | O9: =+F9*Weights!$B$4 -> 0 | Q9: =I9+J9 -> 46020 | R9: 21 | S9: =SUMIF(B:B,R9,Q:Q) -> 183464
A10: =+'Raw Data - Production'!A15 -> 46125 | B10: =+WEEKNUM(A10) -> 16 | C10: =+TEXT(A10,"mmmm") -> April | D10: P4 | E10: =+'Raw Data - Production'!D15+'Raw Data - Production'!E15+'Raw Data - Production'!F15 -> 42240 | F10: =+'Raw Data - Production'!G15+'Raw Data - Production'!H15+'Raw Data - Production'!I15 -> 0 | G10: =+'Raw Data - Production'!K15+'Raw Data - Production'!L15+'Raw Data - Packing'!I15 -> 0 | H10: =+'Raw Data - Production'!N15+'Raw Data - Production'!O15+'Raw Data - Production'!P15+'Raw Data - Packing'!L15 -> 0 | I10: =SUMIF('Raw Data - Packing'!A:A,A10,'Raw Data - Packing'!D:D) -> 42240 | J10: =SUMIF('Raw Data - Packing'!A:A,A10,'Raw Data - Packing'!F:F) -> 0 | N10: =+E10*Weights!$B$2 -> 2673 | O10: =+F10*Weights!$B$4 -> 0 | Q10: =I10+J10 -> 42240 | R10: 22 | S10: =SUMIF(B:B,R10,Q:Q) -> 187868
A11: =+'Raw Data - Production'!A16 -> 46126 | B11: =+WEEKNUM(A11) -> 16 | C11: =+TEXT(A11,"mmmm") -> April | D11: P4 | E11: =+'Raw Data - Production'!D16+'Raw Data - Production'!E16+'Raw Data - Production'!F16 -> 57960 | F11: =+'Raw Data - Production'!G16+'Raw Data - Production'!H16+'Raw Data - Production'!I16 -> 0 | G11: =+'Raw Data - Production'!K16+'Raw Data - Production'!L16+'Raw Data - Packing'!I16 -> 190 | H11: =+'Raw Data - Production'!N16+'Raw Data - Production'!O16+'Raw Data - Production'!P16+'Raw Data - Packing'!L16 -> 0 | I11: =SUMIF('Raw Data - Packing'!A:A,A11,'Raw Data - Packing'!D:D) -> 57960 | J11: =SUMIF('Raw Data - Packing'!A:A,A11,'Raw Data - Packing'!F:F) -> 0 | N11: =+E11*Weights!$B$2 -> 3667.7812 | O11: =+F11*Weights!$B$4 -> 0 | Q11: =I11+J11 -> 57960 | R11: 23 | S11: =SUMIF(B:B,R11,Q:Q) -> 313946
A12: =+'Raw Data - Production'!A17 -> 46127 | B12: =+WEEKNUM(A12) -> 16 | C12: =+TEXT(A12,"mmmm") -> April | D12: P4 | E12: =+'Raw Data - Production'!D17+'Raw Data - Production'!E17+'Raw Data - Production'!F17 -> 54960 | F12: =+'Raw Data - Production'!G17+'Raw Data - Production'!H17+'Raw Data - Production'!I17 -> 0 | G12: =+'Raw Data - Production'!K17+'Raw Data - Production'!L17+'Raw Data - Packing'!I17 -> 1516 | H12: =+'Raw Data - Production'!N17+'Raw Data - Production'!O17+'Raw Data - Production'!P17+'Raw Data - Packing'!L17 -> 0 | I12: =SUMIF('Raw Data - Packing'!A:A,A12,'Raw Data - Packing'!D:D) -> 54960 | J12: =SUMIF('Raw Data - Packing'!A:A,A12,'Raw Data - Packing'!F:F) -> 0 | N12: =+E12*Weights!$B$2 -> 3477.9375 | O12: =+F12*Weights!$B$4 -> 0 | Q12: =I12+J12 -> 54960 | R12: 24 | S12: =SUMIF(B:B,R12,Q:Q) -> 211948
A13: =+'Raw Data - Production'!A18 -> 46128 | B13: =+WEEKNUM(A13) -> 16 | C13: =+TEXT(A13,"mmmm") -> April | D13: P4 | E13: =+'Raw Data - Production'!D18+'Raw Data - Production'!E18+'Raw Data - Production'!F18 -> 34800 | F13: =+'Raw Data - Production'!G18+'Raw Data - Production'!H18+'Raw Data - Production'!I18 -> 0 | G13: =+'Raw Data - Production'!K18+'Raw Data - Production'!L18+'Raw Data - Packing'!I18 -> 0 | H13: =+'Raw Data - Production'!N18+'Raw Data - Production'!O18+'Raw Data - Production'!P18+'Raw Data - Packing'!L18 -> 0 | I13: =SUMIF('Raw Data - Packing'!A:A,A13,'Raw Data - Packing'!D:D) -> 34800 | J13: =SUMIF('Raw Data - Packing'!A:A,A13,'Raw Data - Packing'!F:F) -> 0 | N13: =+E13*Weights!$B$2 -> 2202.1875 | O13: =+F13*Weights!$B$4 -> 0 | Q13: =I13+J13 -> 34800 | R13: 25 | S13: =SUMIF(B:B,R13,Q:Q) -> 319554
A14: =+'Raw Data - Production'!A19 -> 46132 | B14: =+WEEKNUM(A14) -> 17 | C14: =+TEXT(A14,"mmmm") -> April | D14: P4 | E14: =+'Raw Data - Production'!D19+'Raw Data - Production'!E19+'Raw Data - Production'!F19 -> 56280 | F14: =+'Raw Data - Production'!G19+'Raw Data - Production'!H19+'Raw Data - Production'!I19 -> 0 | G14: =+'Raw Data - Production'!K19+'Raw Data - Production'!L19+'Raw Data - Packing'!I19 -> 338 | H14: =+'Raw Data - Production'!N19+'Raw Data - Production'!O19+'Raw Data - Production'!P19+'Raw Data - Packing'!L19 -> 0 | I14: =SUMIF('Raw Data - Packing'!A:A,A14,'Raw Data - Packing'!D:D) -> 56280 | J14: =SUMIF('Raw Data - Packing'!A:A,A14,'Raw Data - Packing'!F:F) -> 0 | N14: =+E14*Weights!$B$2 -> 3561.4688 | O14: =+F14*Weights!$B$4 -> 0 | Q14: =I14+J14 -> 56280 | R14: 26 | S14: =SUMIF(B:B,R14,Q:Q) -> 331544 | W14: 33000
A15: =+'Raw Data - Production'!A20 -> 46133 | B15: =+WEEKNUM(A15) -> 17 | C15: =+TEXT(A15,"mmmm") -> April | D15: P4 | E15: =+'Raw Data - Production'!D20+'Raw Data - Production'!E20+'Raw Data - Production'!F20 -> 52680 | F15: =+'Raw Data - Production'!G20+'Raw Data - Production'!H20+'Raw Data - Production'!I20 -> 0 | G15: =+'Raw Data - Production'!K20+'Raw Data - Production'!L20+'Raw Data - Packing'!I20 -> 179 | H15: =+'Raw Data - Production'!N20+'Raw Data - Production'!O20+'Raw Data - Production'!P20+'Raw Data - Packing'!L20 -> 0 | I15: =SUMIF('Raw Data - Packing'!A:A,A15,'Raw Data - Packing'!D:D) -> 52680 | J15: =SUMIF('Raw Data - Packing'!A:A,A15,'Raw Data - Packing'!F:F) -> 0 | N15: =+E15*Weights!$B$2 -> 3333.6562 | O15: =+F15*Weights!$B$4 -> 0 | Q15: =I15+J15 -> 52680 | R15: 27 | S15: =SUMIF(B:B,R15,Q:Q) -> 367664 | W15: 100
A16: =+'Raw Data - Production'!A21 -> 46134 | B16: =+WEEKNUM(A16) -> 17 | C16: =+TEXT(A16,"mmmm") -> April | D16: P4 | E16: =+'Raw Data - Production'!D21+'Raw Data - Production'!E21+'Raw Data - Production'!F21 -> 67680 | F16: =+'Raw Data - Production'!G21+'Raw Data - Production'!H21+'Raw Data - Production'!I21 -> 0 | G16: =+'Raw Data - Production'!K21+'Raw Data - Production'!L21+'Raw Data - Packing'!I21 -> 308 | H16: =+'Raw Data - Production'!N21+'Raw Data - Production'!O21+'Raw Data - Production'!P21+'Raw Data - Packing'!L21 -> 0 | I16: =SUMIF('Raw Data - Packing'!A:A,A16,'Raw Data - Packing'!D:D) -> 67680 | J16: =SUMIF('Raw Data - Packing'!A:A,A16,'Raw Data - Packing'!F:F) -> 0 | N16: =+E16*Weights!$B$2 -> 4282.875 | O16: =+F16*Weights!$B$4 -> 0 | Q16: =I16+J16 -> 67680 | R16: 28 | S16: =SUMIF(B:B,R16,Q:Q) -> 203761 | W16: =+W14/W15 -> 330
A17: =+'Raw Data - Production'!A22 -> 46135 | B17: =+WEEKNUM(A17) -> 17 | C17: =+TEXT(A17,"mmmm") -> April | D17: P4 | E17: =+'Raw Data - Production'!D22+'Raw Data - Production'!E22+'Raw Data - Production'!F22 -> 70200 | F17: =+'Raw Data - Production'!G22+'Raw Data - Production'!H22+'Raw Data - Production'!I22 -> 0 | G17: =+'Raw Data - Production'!K22+'Raw Data - Production'!L22+'Raw Data - Packing'!I22 -> 0 | H17: =+'Raw Data - Production'!N22+'Raw Data - Production'!O22+'Raw Data - Production'!P22+'Raw Data - Packing'!L22 -> 0 | I17: =SUMIF('Raw Data - Packing'!A:A,A17,'Raw Data - Packing'!D:D) -> 70200 | J17: =SUMIF('Raw Data - Packing'!A:A,A17,'Raw Data - Packing'!F:F) -> 0 | N17: =+E17*Weights!$B$2 -> 4442.3438 | O17: =+F17*Weights!$B$4 -> 0 | Q17: =I17+J17 -> 70200 | R17: 29 | S17: =SUMIF(B:B,R17,Q:Q) -> 99490
A18: =+'Raw Data - Production'!A23 -> 46139 | B18: =+WEEKNUM(A18) -> 18 | C18: =+TEXT(A18,"mmmm") -> April | D18: P4 | E18: =+'Raw Data - Production'!D23+'Raw Data - Production'!E23+'Raw Data - Production'!F23 -> 66480 | F18: =+'Raw Data - Production'!G23+'Raw Data - Production'!H23+'Raw Data - Production'!I23 -> 0 | G18: =+'Raw Data - Production'!K23+'Raw Data - Production'!L23+'Raw Data - Packing'!I23 -> 326 | H18: =+'Raw Data - Production'!N23+'Raw Data - Production'!O23+'Raw Data - Production'!P23+'Raw Data - Packing'!L23 -> 0 | I18: =SUMIF('Raw Data - Packing'!A:A,A18,'Raw Data - Packing'!D:D) -> 66480 | J18: =SUMIF('Raw Data - Packing'!A:A,A18,'Raw Data - Packing'!F:F) -> 0 | N18: =+E18*Weights!$B$2 -> 4206.9375 | O18: =+F18*Weights!$B$4 -> 0 | Q18: =I18+J18 -> 66480
A19: =+'Raw Data - Production'!A24 -> 46140 | B19: =+WEEKNUM(A19) -> 18 | C19: =+TEXT(A19,"mmmm") -> April | D19: P4 | E19: =+'Raw Data - Production'!D24+'Raw Data - Production'!E24+'Raw Data - Production'!F24 -> 67140 | F19: =+'Raw Data - Production'!G24+'Raw Data - Production'!H24+'Raw Data - Production'!I24 -> 0 | G19: =+'Raw Data - Production'!K24+'Raw Data - Production'!L24+'Raw Data - Packing'!I24 -> 0 | H19: =+'Raw Data - Production'!N24+'Raw Data - Production'!O24+'Raw Data - Production'!P24+'Raw Data - Packing'!L24 -> 0 | I19: =SUMIF('Raw Data - Packing'!A:A,A19,'Raw Data - Packing'!D:D) -> 0 | J19: =SUMIF('Raw Data - Packing'!A:A,A19,'Raw Data - Packing'!F:F) -> 0 | N19: =+E19*Weights!$B$2 -> 4248.7031 | O19: =+F19*Weights!$B$4 -> 0 | Q19: =I19+J19 -> 0
A20: =+'Raw Data - Production'!A25 -> 46141 | B20: =+WEEKNUM(A20) -> 18 | C20: =+TEXT(A20,"mmmm") -> April | D20: P4 | E20: =+'Raw Data - Production'!D25+'Raw Data - Production'!E25+'Raw Data - Production'!F25 -> 75960 | F20: =+'Raw Data - Production'!G25+'Raw Data - Production'!H25+'Raw Data - Production'!I25 -> 0 | G20: =+'Raw Data - Production'!K25+'Raw Data - Production'!L25+'Raw Data - Packing'!I25 -> 538.5 | H20: =+'Raw Data - Production'!N25+'Raw Data - Production'!O25+'Raw Data - Production'!P25+'Raw Data - Packing'!L25 -> 0 | I20: =SUMIF('Raw Data - Packing'!A:A,A20,'Raw Data - Packing'!D:D) -> 75960 | J20: =SUMIF('Raw Data - Packing'!A:A,A20,'Raw Data - Packing'!F:F) -> 0 | N20: =+E20*Weights!$B$2 -> 4806.8438 | O20: =+F20*Weights!$B$4 -> 0 | Q20: =I20+J20 -> 75960
A21: =+'Raw Data - Production'!A26 -> 46142 | B21: =+WEEKNUM(A21) -> 18 | C21: =+TEXT(A21,"mmmm") -> April | D21: P4 | E21: =+'Raw Data - Production'!D26+'Raw Data - Production'!E26+'Raw Data - Production'!F26 -> 90270 | F21: =+'Raw Data - Production'!G26+'Raw Data - Production'!H26+'Raw Data - Production'!I26 -> 0 | G21: =+'Raw Data - Production'!K26+'Raw Data - Production'!L26+'Raw Data - Packing'!I26 -> 360 | H21: =+'Raw Data - Production'!N26+'Raw Data - Production'!O26+'Raw Data - Production'!P26+'Raw Data - Packing'!L26 -> 0 | I21: =SUMIF('Raw Data - Packing'!A:A,A21,'Raw Data - Packing'!D:D) -> 90270 | J21: =SUMIF('Raw Data - Packing'!A:A,A21,'Raw Data - Packing'!F:F) -> 0 | N21: =+E21*Weights!$B$2 -> 5712.3984 | O21: =+F21*Weights!$B$4 -> 0 | Q21: =I21+J21 -> 90270
A22: =+'Raw Data - Production'!A27 -> 46146 | B22: =+WEEKNUM(A22) -> 19 | C22: =+TEXT(A22,"mmmm") -> May | D22: P5 | E22: =+'Raw Data - Production'!D27+'Raw Data - Production'!E27+'Raw Data - Production'!F27 -> 0 | F22: =+'Raw Data - Production'!G27+'Raw Data - Production'!H27+'Raw Data - Production'!I27 -> 0 | G22: =+'Raw Data - Production'!K27+'Raw Data - Production'!L27+'Raw Data - Packing'!I27 -> 982 | H22: =+'Raw Data - Production'!N27+'Raw Data - Production'!O27+'Raw Data - Production'!P27+'Raw Data - Packing'!L27 -> 0 | I22: =SUMIF('Raw Data - Packing'!A:A,A22,'Raw Data - Packing'!D:D) -> 52920 | J22: =SUMIF('Raw Data - Packing'!A:A,A22,'Raw Data - Packing'!F:F) -> 0 | N22: =+E22*Weights!$B$2 -> 0 | O22: =+F22*Weights!$B$4 -> 0 | Q22: =I22+J22 -> 52920
A23: =+'Raw Data - Production'!A28 -> 46147 | B23: =+WEEKNUM(A23) -> 19 | C23: =+TEXT(A23,"mmmm") -> May | D23: P5 | E23: =+'Raw Data - Production'!D28+'Raw Data - Production'!E28+'Raw Data - Production'!F28 -> 50400 | F23: =+'Raw Data - Production'!G28+'Raw Data - Production'!H28+'Raw Data - Production'!I28 -> 0 | G23: =+'Raw Data - Production'!K28+'Raw Data - Production'!L28+'Raw Data - Packing'!I28 -> 280 | H23: =+'Raw Data - Production'!N28+'Raw Data - Production'!O28+'Raw Data - Production'!P28+'Raw Data - Packing'!L28 -> 0 | I23: =SUMIF('Raw Data - Packing'!A:A,A23,'Raw Data - Packing'!D:D) -> 108840 | J23: =SUMIF('Raw Data - Packing'!A:A,A23,'Raw Data - Packing'!F:F) -> 0 | N23: =+E23*Weights!$B$2 -> 3189.375 | O23: =+F23*Weights!$B$4 -> 0 | Q23: =I23+J23 -> 108840
A24: =+'Raw Data - Production'!A29 -> 46148 | B24: =+WEEKNUM(A24) -> 19 | C24: =+TEXT(A24,"mmmm") -> May | D24: P5 | E24: =+'Raw Data - Production'!D29+'Raw Data - Production'!E29+'Raw Data - Production'!F29 -> 72000 | F24: =+'Raw Data - Production'!G29+'Raw Data - Production'!H29+'Raw Data - Production'!I29 -> 0 | G24: =+'Raw Data - Production'!K29+'Raw Data - Production'!L29+'Raw Data - Packing'!I29 -> 26 | H24: =+'Raw Data - Production'!N29+'Raw Data - Production'!O29+'Raw Data - Production'!P29+'Raw Data - Packing'!L29 -> 0 | I24: =SUMIF('Raw Data - Packing'!A:A,A24,'Raw Data - Packing'!D:D) -> 73740 | J24: =SUMIF('Raw Data - Packing'!A:A,A24,'Raw Data - Packing'!F:F) -> 0 | N24: =+E24*Weights!$B$2 -> 4556.25 | O24: =+F24*Weights!$B$4 -> 0 | Q24: =I24+J24 -> 73740
A25: =+'Raw Data - Production'!A30 -> 46149 | B25: =+WEEKNUM(A25) -> 19 | C25: =+TEXT(A25,"mmmm") -> May | D25: P5 | E25: =+'Raw Data - Production'!D30+'Raw Data - Production'!E30+'Raw Data - Production'!F30 -> 103600 | F25: =+'Raw Data - Production'!G30+'Raw Data - Production'!H30+'Raw Data - Production'!I30 -> 0 | G25: =+'Raw Data - Production'!K30+'Raw Data - Production'!L30+'Raw Data - Packing'!I30 -> 320 | H25: =+'Raw Data - Production'!N30+'Raw Data - Production'!O30+'Raw Data - Production'!P30+'Raw Data - Packing'!L30 -> 30 | I25: =SUMIF('Raw Data - Packing'!A:A,A25,'Raw Data - Packing'!D:D) -> 0 | J25: =SUMIF('Raw Data - Packing'!A:A,A25,'Raw Data - Packing'!F:F) -> 0 | N25: =+E25*Weights!$B$2 -> 6555.9375 | O25: =+F25*Weights!$B$4 -> 0 | Q25: =I25+J25 -> 0
A26: =+'Raw Data - Production'!A31 -> 46153 | B26: =+WEEKNUM(A26) -> 20 | C26: =+TEXT(A26,"mmmm") -> May | D26: P5 | E26: =+'Raw Data - Production'!D31+'Raw Data - Production'!E31+'Raw Data - Production'!F31 -> 48960 | F26: =+'Raw Data - Production'!G31+'Raw Data - Production'!H31+'Raw Data - Production'!I31 -> 0 | G26: =+'Raw Data - Production'!K31+'Raw Data - Production'!L31+'Raw Data - Packing'!I31 -> 90 | H26: =+'Raw Data - Production'!N31+'Raw Data - Production'!O31+'Raw Data - Production'!P31+'Raw Data - Packing'!L31 -> 0 | I26: =SUMIF('Raw Data - Packing'!A:A,A26,'Raw Data - Packing'!D:D) -> 33060 | J26: =SUMIF('Raw Data - Packing'!A:A,A26,'Raw Data - Packing'!F:F) -> 0 | N26: =+E26*Weights!$B$2 -> 3098.25 | O26: =+F26*Weights!$B$4 -> 0 | Q26: =I26+J26 -> 33060
A27: =+'Raw Data - Production'!A32 -> 46154 | B27: =+WEEKNUM(A27) -> 20 | C27: =+TEXT(A27,"mmmm") -> May | D27: P5 | E27: =+'Raw Data - Production'!D32+'Raw Data - Production'!E32+'Raw Data - Production'!F32 -> 64320 | F27: =+'Raw Data - Production'!G32+'Raw Data - Production'!H32+'Raw Data - Production'!I32 -> 3800 | G27: =+'Raw Data - Production'!K32+'Raw Data - Production'!L32+'Raw Data - Packing'!I32 -> 150 | H27: =+'Raw Data - Production'!N32+'Raw Data - Production'!O32+'Raw Data - Production'!P32+'Raw Data - Packing'!L32 -> 50 | I27: =SUMIF('Raw Data - Packing'!A:A,A27,'Raw Data - Packing'!D:D) -> 64320 | J27: =SUMIF('Raw Data - Packing'!A:A,A27,'Raw Data - Packing'!F:F) -> 0 | N27: =+E27*Weights!$B$2 -> 4070.25 | O27: =+F27*Weights!$B$4 -> 593.75 | Q27: =I27+J27 -> 64320
A28: =+'Raw Data - Production'!A33 -> 46155 | B28: =+WEEKNUM(A28) -> 20 | C28: =+TEXT(A28,"mmmm") -> May | D28: P5 | E28: =+'Raw Data - Production'!D33+'Raw Data - Production'!E33+'Raw Data - Production'!F33 -> 68700 | F28: =+'Raw Data - Production'!G33+'Raw Data - Production'!H33+'Raw Data - Production'!I33 -> 13650 | G28: =+'Raw Data - Production'!K33+'Raw Data - Production'!L33+'Raw Data - Packing'!I33 -> 260 | H28: =+'Raw Data - Production'!N33+'Raw Data - Production'!O33+'Raw Data - Production'!P33+'Raw Data - Packing'!L33 -> 66 | I28: =SUMIF('Raw Data - Packing'!A:A,A28,'Raw Data - Packing'!D:D) -> 68700 | J28: =SUMIF('Raw Data - Packing'!A:A,A28,'Raw Data - Packing'!F:F) -> 0 | N28: =+E28*Weights!$B$2 -> 4347.4219 | O28: =+F28*Weights!$B$4 -> 2132.8125 | Q28: =I28+J28 -> 68700
A29: =+'Raw Data - Production'!A34 -> 46156 | B29: =+WEEKNUM(A29) -> 20 | C29: =+TEXT(A29,"mmmm") -> May | D29: P5 | E29: =+'Raw Data - Production'!D34+'Raw Data - Production'!E34+'Raw Data - Production'!F34 -> 65260 | F29: =+'Raw Data - Production'!G34+'Raw Data - Production'!H34+'Raw Data - Production'!I34 -> 0 | G29: =+'Raw Data - Production'!K34+'Raw Data - Production'!L34+'Raw Data - Packing'!I34 -> 704 | H29: =+'Raw Data - Production'!N34+'Raw Data - Production'!O34+'Raw Data - Production'!P34+'Raw Data - Packing'!L34 -> 0 | I29: =SUMIF('Raw Data - Packing'!A:A,A29,'Raw Data - Packing'!D:D) -> 63240 | J29: =SUMIF('Raw Data - Packing'!A:A,A29,'Raw Data - Packing'!F:F) -> 0 | N29: =+E29*Weights!$B$2 -> 4129.7344 | O29: =+F29*Weights!$B$4 -> 0 | Q29: =I29+J29 -> 63240
... A39: =+'Raw Data - Production'!A44 -> 46174 | B39: =+WEEKNUM(A39) -> 23 | C39: =+TEXT(A39,"mmmm") -> June | D39: P6 | E39: =+'Raw Data - Production'!D44+'Raw Data - Production'!E44+'Raw Data - Production'!F44 -> 76320 | F39: =+'Raw Data - Production'!G44+'Raw Data - Production'!H44+'Raw Data - Production'!I44 -> 0 | G39: =+'Raw Data - Production'!K44+'Raw Data - Production'!L44+'Raw Data - Packing'!I44 -> 326 | H39: =+'Raw Data - Production'!N44+'Raw Data - Production'!O44+'Raw Data - Production'!P44+'Raw Data - Packing'!L44 -> 0 | I39: =SUMIF('Raw Data - Packing'!A:A,A39,'Raw Data - Packing'!D:D) -> 96000 | J39: =SUMIF('Raw Data - Packing'!A:A,A39,'Raw Data - Packing'!F:F) -> 416 | N39: =+E39*Weights!$B$2 -> 4829.625 | O39: =+F39*Weights!$B$4 -> 0 | Q39: =I39+J39 -> 96416
A40: =+'Raw Data - Production'!A45 -> 46175 | B40: =+WEEKNUM(A40) -> 23 | C40: =+TEXT(A40,"mmmm") -> June | D40: P6 | E40: =+'Raw Data - Production'!D45+'Raw Data - Production'!E45+'Raw Data - Production'!F45 -> 89280 | F40: =+'Raw Data - Production'!G45+'Raw Data - Production'!H45+'Raw Data - Production'!I45 -> 0 | G40: =+'Raw Data - Production'!K45+'Raw Data - Production'!L45+'Raw Data - Packing'!I45 -> 168 | H40: =+'Raw Data - Production'!N45+'Raw Data - Production'!O45+'Raw Data - Production'!P45+'Raw Data - Packing'!L45 -> 0 | I40: =SUMIF('Raw Data - Packing'!A:A,A40,'Raw Data - Packing'!D:D) -> 54540 | J40: =SUMIF('Raw Data - Packing'!A:A,A40,'Raw Data - Packing'!F:F) -> 12100 | N40: =+E40*Weights!$B$2 -> 5649.75 | O40: =+F40*Weights!$B$4 -> 0 | Q40: =I40+J40 -> 66640 | X40: SD | Y40: Bao
A41: =+'Raw Data - Production'!A46 -> 46176 | B41: =+WEEKNUM(A41) -> 23 | C41: =+TEXT(A41,"mmmm") -> June | D41: P6 | E41: =+'Raw Data - Production'!D46+'Raw Data - Production'!E46+'Raw Data - Production'!F46 -> 55656 | F41: =+'Raw Data - Production'!G46+'Raw Data - Production'!H46+'Raw Data - Production'!I46 -> 0 | G41: =+'Raw Data - Production'!K46+'Raw Data - Production'!L46+'Raw Data - Packing'!I46 -> 166 | H41: =+'Raw Data - Production'!N46+'Raw Data - Production'!O46+'Raw Data - Production'!P46+'Raw Data - Packing'!L46 -> 60 | I41: =SUMIF('Raw Data - Packing'!A:A,A41,'Raw Data - Packing'!D:D) -> 47520 | J41: =SUMIF('Raw Data - Packing'!A:A,A41,'Raw Data - Packing'!F:F) -> 3650 | N41: =+E41*Weights!$B$2 -> 3521.9812 | O41: =+F41*Weights!$B$4 -> 0 | Q41: =I41+J41 -> 51170 | X41: =2871/Weights!B2 -> 45368.889 | Y41: =2042/Weights!B4 -> 13068.8
A42: =+'Raw Data - Production'!A47 -> 46177 | B42: =+WEEKNUM(A42) -> 23 | C42: =+TEXT(A42,"mmmm") -> June | D42: P6 | E42: =+'Raw Data - Production'!D47+'Raw Data - Production'!E47+'Raw Data - Production'!F47 -> 46320 | F42: =+'Raw Data - Production'!G47+'Raw Data - Production'!H47+'Raw Data - Production'!I47 -> 9380 | G42: =+'Raw Data - Production'!K47+'Raw Data - Production'!L47+'Raw Data - Packing'!I47 -> 73 | H42: =+'Raw Data - Production'!N47+'Raw Data - Production'!O47+'Raw Data - Production'!P47+'Raw Data - Packing'!L47 -> 132 | I42: =SUMIF('Raw Data - Packing'!A:A,A42,'Raw Data - Packing'!D:D) -> 37800 | J42: =SUMIF('Raw Data - Packing'!A:A,A42,'Raw Data - Packing'!F:F) -> 0 | N42: =+E42*Weights!$B$2 -> 2931.1875 | O42: =+F42*Weights!$B$4 -> 1465.625 | Q42: =I42+J42 -> 37800
A43: =+'Raw Data - Production'!A48 -> 46178 | B43: =+WEEKNUM(A43) -> 23 | C43: =+TEXT(A43,"mmmm") -> June | D43: P6 | E43: =+'Raw Data - Production'!D48+'Raw Data - Production'!E48+'Raw Data - Production'!F48 -> 0 | F43: =+'Raw Data - Production'!G48+'Raw Data - Production'!H48+'Raw Data - Production'!I48 -> 0 | G43: =+'Raw Data - Production'!K48+'Raw Data - Production'!L48+'Raw Data - Packing'!I48 -> 0 | H43: =+'Raw Data - Production'!N48+'Raw Data - Production'!O48+'Raw Data - Production'!P48+'Raw Data - Packing'!L48 -> 0 | I43: =SUMIF('Raw Data - Packing'!A:A,A43,'Raw Data - Packing'!D:D) -> 61920 | J43: =SUMIF('Raw Data - Packing'!A:A,A43,'Raw Data - Packing'!F:F) -> 0 | L43: 83340 | M43: 12250 | N43: =+E43*Weights!$B$2 -> 0 | O43: =+F43*Weights!$B$4 -> 0 | Q43: =I43+J43 -> 61920
A44: =+'Raw Data - Production'!A49 -> 46181 | B44: =+WEEKNUM(A44) -> 24 | C44: =+TEXT(A44,"mmmm") -> June | D44: P6 | E44: =+'Raw Data - Production'!D49+'Raw Data - Production'!E49+'Raw Data - Production'!F49 -> 0 | F44: =+'Raw Data - Production'!G49+'Raw Data - Production'!H49+'Raw Data - Production'!I49 -> 0 | G44: =+'Raw Data - Production'!K49+'Raw Data - Production'!L49+'Raw Data - Packing'!I49 -> 121 | H44: =+'Raw Data - Production'!N49+'Raw Data - Production'!O49+'Raw Data - Production'!P49+'Raw Data - Packing'!L49 -> 0 | I44: =SUMIF('Raw Data - Packing'!A:A,A44,'Raw Data - Packing'!D:D) -> 83340 | J44: =SUMIF('Raw Data - Packing'!A:A,A44,'Raw Data - Packing'!F:F) -> 0 | L44: 0 | M44: =+F44-J44+M43 -> 12250 | N44: =+E44*Weights!$B$2 -> 0 | O44: =+F44*Weights!$B$4 -> 0 | Q44: =I44+J44 -> 83340
A45: =+'Raw Data - Production'!A50 -> 46182 | B45: =+WEEKNUM(A45) -> 24 | C45: =+TEXT(A45,"mmmm") -> June | D45: P6 | E45: =+'Raw Data - Production'!D50+'Raw Data - Production'!E50+'Raw Data - Production'!F50 -> 83520 | F45: =+'Raw Data - Production'!G50+'Raw Data - Production'!H50+'Raw Data - Production'!I50 -> 7315 | G45: =+'Raw Data - Production'!K50+'Raw Data - Production'!L50+'Raw Data - Packing'!I50 -> 432 | H45: =+'Raw Data - Production'!N50+'Raw Data - Production'!O50+'Raw Data - Production'!P50+'Raw Data - Packing'!L50 -> 32 | I45: =SUMIF('Raw Data - Packing'!A:A,A45,'Raw Data - Packing'!D:D) -> 52680 | J45: =SUMIF('Raw Data - Packing'!A:A,A45,'Raw Data - Packing'!F:F) -> 0 | L45: =+E45-I45+L44 -> 30840 | M45: =+F45-J45+M44 -> 19565 | N45: =+E45*Weights!$B$2 -> 5285.25 | O45: =+F45*Weights!$B$4 -> 1142.9688 | Q45: =I45+J45 -> 52680
A46: =+'Raw Data - Production'!A51 -> 46183 | B46: =+WEEKNUM(A46) -> 24 | C46: =+TEXT(A46,"mmmm") -> June | D46: P6 | E46: =+'Raw Data - Production'!D51+'Raw Data - Production'!E51+'Raw Data - Production'!F51 -> 43920 | F46: =+'Raw Data - Production'!G51+'Raw Data - Production'!H51+'Raw Data - Production'!I51 -> 10500 | G46: =+'Raw Data - Production'!K51+'Raw Data - Production'!L51+'Raw Data - Packing'!I51 -> 98 | H46: =+'Raw Data - Production'!N51+'Raw Data - Production'!O51+'Raw Data - Production'!P51+'Raw Data - Packing'!L51 -> 62 | I46: =SUMIF('Raw Data - Packing'!A:A,A46,'Raw Data - Packing'!D:D) -> 50280 | J46: =SUMIF('Raw Data - Packing'!A:A,A46,'Raw Data - Packing'!F:F) -> 0 | L46: =+E46-I46+L45 -> 24480 | M46: =+F46-J46+M45 -> 30065 | N46: =+E46*Weights!$B$2 -> 2779.3125 | O46: =+F46*Weights!$B$4 -> 1640.625 | Q46: =I46+J46 -> 50280
A47: =+'Raw Data - Production'!A52 -> 46184 | B47: =+WEEKNUM(A47) -> 24 | C47: =+TEXT(A47,"mmmm") -> June | D47: P6 | E47: =+'Raw Data - Production'!D52+'Raw Data - Production'!E52+'Raw Data - Production'!F52 -> 64253 | F47: =+'Raw Data - Production'!G52+'Raw Data - Production'!H52+'Raw Data - Production'!I52 -> 9975 | G47: =+'Raw Data - Production'!K52+'Raw Data - Production'!L52+'Raw Data - Packing'!I52 -> 132 | H47: =+'Raw Data - Production'!N52+'Raw Data - Production'!O52+'Raw Data - Production'!P52+'Raw Data - Packing'!L52 -> 122 | I47: =SUMIF('Raw Data - Packing'!A:A,A47,'Raw Data - Packing'!D:D) -> 11760 | J47: =SUMIF('Raw Data - Packing'!A:A,A47,'Raw Data - Packing'!F:F) -> 13888 | L47: =+E47-I47+L46 -> 76973 | M47: =+F47-J47+M46 -> 26152 | N47: =+E47*Weights!$B$2 -> 4066.0102 | O47: =+F47*Weights!$B$4 -> 1558.5938 | Q47: =I47+J47 -> 25648
A48: =+'Raw Data - Production'!A53 -> 46185 | B48: =+WEEKNUM(A48) -> 24 | C48: =+TEXT(A48,"mmmm") -> June | D48: P6 | E48: =+'Raw Data - Production'!D53+'Raw Data - Production'!E53+'Raw Data - Production'!F53 -> 0 | F48: =+'Raw Data - Production'!G53+'Raw Data - Production'!H53+'Raw Data - Production'!I53 -> 0 | G48: =+'Raw Data - Production'!K53+'Raw Data - Production'!L53+'Raw Data - Packing'!I53 -> 0 | H48: =+'Raw Data - Production'!N53+'Raw Data - Production'!O53+'Raw Data - Production'!P53+'Raw Data - Packing'!L53 -> 0 | I48: =SUMIF('Raw Data - Packing'!A:A,A48,'Raw Data - Packing'!D:D) -> 0 | J48: =SUMIF('Raw Data - Packing'!A:A,A48,'Raw Data - Packing'!F:F) -> 0 | L48: 78136 | M48: 24150 | N48: =+E48*Weights!$B$2 -> 0 | O48: =+F48*Weights!$B$4 -> 0 | Q48: =I48+J48 -> 0
A49: =+'Raw Data - Production'!A54 -> 46188 | B49: =+WEEKNUM(A49) -> 25 | C49: =+TEXT(A49,"mmmm") -> June | D49: P6 | E49: =+'Raw Data - Production'!D54+'Raw Data - Production'!E54+'Raw Data - Production'!F54 -> 33120 | F49: =+'Raw Data - Production'!G54+'Raw Data - Production'!H54+'Raw Data - Production'!I54 -> 0 | G49: =+'Raw Data - Production'!K54+'Raw Data - Production'!L54+'Raw Data - Packing'!I54 -> 68 | H49: =+'Raw Data - Production'!N54+'Raw Data - Production'!O54+'Raw Data - Production'!P54+'Raw Data - Packing'!L54 -> 0 | I49: =SUMIF('Raw Data - Packing'!A:A,A49,'Raw Data - Packing'!D:D) -> 29100 | J49: =SUMIF('Raw Data - Packing'!A:A,A49,'Raw Data - Packing'!F:F) -> 12514 | L49: =+E49-I49+L48 -> 82156 | M49: =+F49-J49+M48 -> 11636 | N49: =+E49*Weights!$B$2 -> 2095.875 | O49: =+F49*Weights!$B$4 -> 0 | Q49: =I49+J49 -> 41614
A50: =+'Raw Data - Production'!A55 -> 46189 | B50: =+WEEKNUM(A50) -> 25 | C50: =+TEXT(A50,"mmmm") -> June | D50: P6 | E50: =+'Raw Data - Production'!D55+'Raw Data - Production'!E55+'Raw Data - Production'!F55 -> 67680 | F50: =+'Raw Data - Production'!G55+'Raw Data - Production'!H55+'Raw Data - Production'!I55 -> 0 | G50: =+'Raw Data - Production'!K55+'Raw Data - Production'!L55+'Raw Data - Packing'!I55 -> 109 | H50: =+'Raw Data - Production'!N55+'Raw Data - Production'!O55+'Raw Data - Production'!P55+'Raw Data - Packing'!L55 -> 0 | I50: =SUMIF('Raw Data - Packing'!A:A,A50,'Raw Data - Packing'!D:D) -> 105900 | J50: =SUMIF('Raw Data - Packing'!A:A,A50,'Raw Data - Packing'!F:F) -> 0 | L50: =+E50-I50+L49 -> 43936 | M50: =+F50-J50+M49 -> 11636 | N50: =+E50*Weights!$B$2 -> 4282.875 | O50: =+F50*Weights!$B$4 -> 0 | Q50: =I50+J50 -> 105900
A51: =+'Raw Data - Production'!A56 -> 46190 | B51: =+WEEKNUM(A51) -> 25 | C51: =+TEXT(A51,"mmmm") -> June | D51: P6 | E51: =+'Raw Data - Production'!D56+'Raw Data - Production'!E56+'Raw Data - Production'!F56 -> 54816 | F51: =+'Raw Data - Production'!G56+'Raw Data - Production'!H56+'Raw Data - Production'!I56 -> 1400 | G51: =+'Raw Data - Production'!K56+'Raw Data - Production'!L56+'Raw Data - Packing'!I56 -> 229 | H51: =+'Raw Data - Production'!N56+'Raw Data - Production'!O56+'Raw Data - Production'!P56+'Raw Data - Packing'!L56 -> 14 | I51: =SUMIF('Raw Data - Packing'!A:A,A51,'Raw Data - Packing'!D:D) -> 93720 | J51: =SUMIF('Raw Data - Packing'!A:A,A51,'Raw Data - Packing'!F:F) -> 1312 | L51: 0 | M51: =+F51-J51+M50 -> 11724 | N51: =+E51*Weights!$B$2 -> 3468.825 | O51: =+F51*Weights!$B$4 -> 218.75 | Q51: =I51+J51 -> 95032
A52: =+'Raw Data - Production'!A57 -> 46191 | B52: =+WEEKNUM(A52) -> 25 | C52: =+TEXT(A52,"mmmm") -> June | D52: P6 | E52: =+'Raw Data - Production'!D57+'Raw Data - Production'!E57+'Raw Data - Production'!F57 -> 62352 | F52: =+'Raw Data - Production'!G57+'Raw Data - Production'!H57+'Raw Data - Production'!I57 -> 6300 | G52: =+'Raw Data - Production'!K57+'Raw Data - Production'!L57+'Raw Data - Packing'!I57 -> 134 | H52: =+'Raw Data - Production'!N57+'Raw Data - Production'!O57+'Raw Data - Production'!P57+'Raw Data - Packing'!L57 -> 23 | I52: =SUMIF('Raw Data - Packing'!A:A,A52,'Raw Data - Packing'!D:D) -> 62352 | J52: =SUMIF('Raw Data - Packing'!A:A,A52,'Raw Data - Packing'!F:F) -> 10816 | L52: =+E52-I52+L51 -> 0 | M52: =+F52-J52+M51 -> 7208 | N52: =+E52*Weights!$B$2 -> 3945.7125 | O52: =+F52*Weights!$B$4 -> 984.375 | Q52: =I52+J52 -> 73168
A53: =+'Raw Data - Production'!A58 -> 46192 | B53: =+WEEKNUM(A53) -> 25 | C53: =+TEXT(A53,"mmmm") -> June | D53: P6 | E53: =+'Raw Data - Production'!D58+'Raw Data - Production'!E58+'Raw Data - Production'!F58 -> 0 | F53: =+'Raw Data - Production'!G58+'Raw Data - Production'!H58+'Raw Data - Production'!I58 -> 0 | G53: =+'Raw Data - Production'!K58+'Raw Data - Production'!L58+'Raw Data - Packing'!I58 -> 0 | H53: =+'Raw Data - Production'!N58+'Raw Data - Production'!O58+'Raw Data - Production'!P58+'Raw Data - Packing'!L58 -> 0 | I53: =SUMIF('Raw Data - Packing'!A:A,A53,'Raw Data - Packing'!D:D) -> 0 | J53: =SUMIF('Raw Data - Packing'!A:A,A53,'Raw Data - Packing'!F:F) -> 3840 | L53: =+E53-I53+L52 -> 0 | M53: 0 | N53: =+E53*Weights!$B$2 -> 0 | O53: =+F53*Weights!$B$4 -> 0 | Q53: =I53+J53 -> 3840
A54: =+'Raw Data - Production'!A59 -> 46195 | B54: =+WEEKNUM(A54) -> 26 | C54: =+TEXT(A54,"mmmm") -> June | D54: P6 | E54: =+'Raw Data - Production'!D59+'Raw Data - Production'!E59+'Raw Data - Production'!F59 -> 72420 | F54: =+'Raw Data - Production'!G59+'Raw Data - Production'!H59+'Raw Data - Production'!I59 -> 8313 | G54: =+'Raw Data - Production'!K59+'Raw Data - Production'!L59+'Raw Data - Packing'!I59 -> 137 | H54: =+'Raw Data - Production'!N59+'Raw Data - Production'!O59+'Raw Data - Production'!P59+'Raw Data - Packing'!L59 -> 279 | I54: =SUMIF('Raw Data - Packing'!A:A,A54,'Raw Data - Packing'!D:D) -> 72420 | J54: =SUMIF('Raw Data - Packing'!A:A,A54,'Raw Data - Packing'!F:F) -> 5920 | L54: =+E54-I54+L53 -> 0 | M54: 0 | N54: =+E54*Weights!$B$2 -> 4582.8281 | O54: =+F54*Weights!$B$4 -> 1298.9062 | Q54: =I54+J54 -> 78340
A55: =+'Raw Data - Production'!A60 -> 46196 | B55: =+WEEKNUM(A55) -> 26 | C55: =+TEXT(A55,"mmmm") -> June | D55: P6 | E55: =+'Raw Data - Production'!D60+'Raw Data - Production'!E60+'Raw Data - Production'!F60 -> 59095 | F55: =+'Raw Data - Production'!G60+'Raw Data - Production'!H60+'Raw Data - Production'!I60 -> 9450 | G55: =+'Raw Data - Production'!K60+'Raw Data - Production'!L60+'Raw Data - Packing'!I60 -> 343 | H55: =+'Raw Data - Production'!N60+'Raw Data - Production'!O60+'Raw Data - Production'!P60+'Raw Data - Packing'!L60 -> 526 | I55: =SUMIF('Raw Data - Packing'!A:A,A55,'Raw Data - Packing'!D:D) -> 56760 | J55: =SUMIF('Raw Data - Packing'!A:A,A55,'Raw Data - Packing'!F:F) -> 7712 | L55: 0 | M55: 0 | N55: =+E55*Weights!$B$2 -> 3739.6055 | O55: =+F55*Weights!$B$4 -> 1476.5625 | Q55: =I55+J55 -> 64472
A56: =+'Raw Data - Production'!A61 -> 46197 | B56: =+WEEKNUM(A56) -> 26 | C56: =+TEXT(A56,"mmmm") -> June | D56: P6 | E56: =+'Raw Data - Production'!D61+'Raw Data - Production'!E61+'Raw Data - Production'!F61 -> 78624 | F56: =+'Raw Data - Production'!G61+'Raw Data - Production'!H61+'Raw Data - Production'!I61 -> 15540 | G56: =+'Raw Data - Production'!K61+'Raw Data - Production'!L61+'Raw Data - Packing'!I61 -> 122 | H56: =+'Raw Data - Production'!N61+'Raw Data - Production'!O61+'Raw Data - Production'!P61+'Raw Data - Packing'!L61 -> 514 | I56: =SUMIF('Raw Data - Packing'!A:A,A56,'Raw Data - Packing'!D:D) -> 77340 | J56: =SUMIF('Raw Data - Packing'!A:A,A56,'Raw Data - Packing'!F:F) -> 12512 | L56: 0 | M56: 0 | N56: =+E56*Weights!$B$2 -> 4975.425 | O56: =+F56*Weights!$B$4 -> 2428.125 | Q56: =I56+J56 -> 89852
A57: =+'Raw Data - Production'!A62 -> 46198 | B57: =+WEEKNUM(A57) -> 26 | C57: =+TEXT(A57,"mmmm") -> June | D57: P6 | E57: =+'Raw Data - Production'!D62+'Raw Data - Production'!E62+'Raw Data - Production'!F62 -> 96732 | F57: =+'Raw Data - Production'!G62+'Raw Data - Production'!H62+'Raw Data - Production'!I62 -> 4515 | G57: =+'Raw Data - Production'!K62+'Raw Data - Production'!L62+'Raw Data - Packing'!I62 -> 213 | H57: =+'Raw Data - Production'!N62+'Raw Data - Production'!O62+'Raw Data - Production'!P62+'Raw Data - Packing'!L62 -> 278 | I57: =SUMIF('Raw Data - Packing'!A:A,A57,'Raw Data - Packing'!D:D) -> 96960 | J57: =SUMIF('Raw Data - Packing'!A:A,A57,'Raw Data - Packing'!F:F) -> 1920 | L57: 0 | M57: =+F57-J57+M56 -> 2595 | N57: =+E57*Weights!$B$2 -> 6121.3219 | O57: =+F57*Weights!$B$4 -> 705.46875 | Q57: =I57+J57 -> 98880
A58: =+'Raw Data - Production'!A63 -> 46199 | B58: =+WEEKNUM(A58) -> 26 | C58: =+TEXT(A58,"mmmm") -> June | D58: P6 | E58: =+'Raw Data - Production'!D63+'Raw Data - Production'!E63+'Raw Data - Production'!F63 -> 0 | F58: =+'Raw Data - Production'!G63+'Raw Data - Production'!H63+'Raw Data - Production'!I63 -> 0 | G58: =+'Raw Data - Production'!K63+'Raw Data - Production'!L63+'Raw Data - Packing'!I63 -> 0 | H58: =+'Raw Data - Production'!N63+'Raw Data - Production'!O63+'Raw Data - Production'!P63+'Raw Data - Packing'!L63 -> 0 | I58: =SUMIF('Raw Data - Packing'!A:A,A58,'Raw Data - Packing'!D:D) -> 0 | J58: =SUMIF('Raw Data - Packing'!A:A,A58,'Raw Data - Packing'!F:F) -> 0 | L58: =+E58-I58+L57 -> 0 | M58: =+F58-J58+M57 -> 2595 | N58: =+E58*Weights!$B$2 -> 0 | O58: =+F58*Weights!$B$4 -> 0 | Q58: =I58+J58 -> 0
A59: =+'Raw Data - Production'!A64 -> 46202 | B59: =+WEEKNUM(A59) -> 27 | C59: =+TEXT(A59,"mmmm") -> June | D59: P7 | E59: =+'Raw Data - Production'!D64+'Raw Data - Production'!E64+'Raw Data - Production'!F64 -> 79968 | F59: =+'Raw Data - Production'!G64+'Raw Data - Production'!H64+'Raw Data - Production'!I64 -> 13895 | G59: =+'Raw Data - Production'!K64+'Raw Data - Production'!L64+'Raw Data - Packing'!I64 -> 429 | H59: =+'Raw Data - Production'!N64+'Raw Data - Production'!O64+'Raw Data - Production'!P64+'Raw Data - Packing'!L64 -> 166 | I59: =SUMIF('Raw Data - Packing'!A:A,A59,'Raw Data - Packing'!D:D) -> 60480 | J59: =SUMIF('Raw Data - Packing'!A:A,A59,'Raw Data - Packing'!F:F) -> 14304 | L59: 9000 | M59: =+F59-J59+M58-(H59/Weights!$B$4) -> 1123.6 | N59: =+E59*Weights!$B$2 -> 5060.475 | O59: =+F59*Weights!$B$4 -> 2171.0938 | Q59: =I59+J59 -> 74784
A60: =+'Raw Data - Production'!A65 -> 46203 | B60: =+WEEKNUM(A60) -> 27 | C60: =+TEXT(A60,"mmmm") -> June | D60: P7 | E60: =+'Raw Data - Production'!D65+'Raw Data - Production'!E65+'Raw Data - Production'!F65 -> 81726 | F60: =+'Raw Data - Production'!G65+'Raw Data - Production'!H65+'Raw Data - Production'!I65 -> 15645 | G60: =+'Raw Data - Production'!K65+'Raw Data - Production'!L65+'Raw Data - Packing'!I65 -> 358 | H60: =+'Raw Data - Production'!N65+'Raw Data - Production'!O65+'Raw Data - Production'!P65+'Raw Data - Packing'!L65 -> 591 | I60: =SUMIF('Raw Data - Packing'!A:A,A60,'Raw Data - Packing'!D:D) -> 90780 | J60: =SUMIF('Raw Data - Packing'!A:A,A60,'Raw Data - Packing'!F:F) -> 15104 | L60: 0 | M60: 0 | N60: =+E60*Weights!$B$2 -> 5171.7234 | O60: =+F60*Weights!$B$4 -> 2444.5312 | Q60: =I60+J60 -> 105884
A61: =+'Raw Data - Production'!A66 -> 46204 | B61: =+WEEKNUM(A61) -> 27 | C61: =+TEXT(A61,"mmmm") -> July | D61: P7 | E61: =+'Raw Data - Production'!D66+'Raw Data - Production'!E66+'Raw Data - Production'!F66 -> 72000 | F61: =+'Raw Data - Production'!G66+'Raw Data - Production'!H66+'Raw Data - Production'!I66 -> 13405 | G61: =+'Raw Data - Production'!K66+'Raw Data - Production'!L66+'Raw Data - Packing'!I66 -> 185 | H61: =+'Raw Data - Production'!N66+'Raw Data - Production'!O66+'Raw Data - Production'!P66+'Raw Data - Packing'!L66 -> 184 | I61: =SUMIF('Raw Data - Packing'!A:A,A61,'Raw Data - Packing'!D:D) -> 68040 | J61: =SUMIF('Raw Data - Packing'!A:A,A61,'Raw Data - Packing'!F:F) -> 11392 | L61: 0 | M61: =12*150 -> 1800 | N61: =+E61*Weights!$B$2 -> 4556.25 | O61: =+F61*Weights!$B$4 -> 2094.5312 | Q61: =I61+J61 -> 79432
A62: =+'Raw Data - Production'!A67 -> 46205 | B62: =+WEEKNUM(A62) -> 27 | C62: =+TEXT(A62,"mmmm") -> July | D62: P7 | E62: =+'Raw Data - Production'!D67+'Raw Data - Production'!E67+'Raw Data - Production'!F67 -> 96096 | F62: =+'Raw Data - Production'!G67+'Raw Data - Production'!H67+'Raw Data - Production'!I67 -> 26565 | G62: =+'Raw Data - Production'!K67+'Raw Data - Production'!L67+'Raw Data - Packing'!I67 -> 360 | H62: =+'Raw Data - Production'!N67+'Raw Data - Production'!O67+'Raw Data - Production'!P67+'Raw Data - Packing'!L67 -> 112 | I62: =SUMIF('Raw Data - Packing'!A:A,A62,'Raw Data - Packing'!D:D) -> 90060 | J62: =SUMIF('Raw Data - Packing'!A:A,A62,'Raw Data - Packing'!F:F) -> 17504 | L62: 8400 | M62: 4650 | N62: =+E62*Weights!$B$2 -> 6081.075 | O62: =+F62*Weights!$B$4 -> 4150.7812 | Q62: =I62+J62 -> 107564
A63: =+'Raw Data - Production'!A68 -> 46206 | B63: =+WEEKNUM(A63) -> 27 | C63: =+TEXT(A63,"mmmm") -> July | D63: P7 | E63: =+'Raw Data - Production'!D68+'Raw Data - Production'!E68+'Raw Data - Production'!F68 -> 0 | F63: =+'Raw Data - Production'!G68+'Raw Data - Production'!H68+'Raw Data - Production'!I68 -> 0 | G63: =+'Raw Data - Production'!K68+'Raw Data - Production'!L68+'Raw Data - Packing'!I68 -> 0 | H63: =+'Raw Data - Production'!N68+'Raw Data - Production'!O68+'Raw Data - Production'!P68+'Raw Data - Packing'!L68 -> 0 | I63: =SUMIF('Raw Data - Packing'!A:A,A63,'Raw Data - Packing'!D:D) -> 0 | J63: =SUMIF('Raw Data - Packing'!A:A,A63,'Raw Data - Packing'!F:F) -> 0 | L63: =+E63-I63+L62-(G63/Weights!$B$2) -> 8400 | M63: =+F63-J63+M62-(H63/Weights!$B$4) -> 4650 | N63: =+E63*Weights!$B$2 -> 0 | O63: =+F63*Weights!$B$4 -> 0 | Q63: =I63+J63 -> 0
A64: =+'Raw Data - Production'!A69 -> 46209 | B64: =+WEEKNUM(A64) -> 28 | C64: =+TEXT(A64,"mmmm") -> July | D64: P7 | E64: =+'Raw Data - Production'!D69+'Raw Data - Production'!E69+'Raw Data - Production'!F69 -> 55680 | F64: =+'Raw Data - Production'!G69+'Raw Data - Production'!H69+'Raw Data - Production'!I69 -> 6090 | G64: =+'Raw Data - Production'!K69+'Raw Data - Production'!L69+'Raw Data - Packing'!I69 -> 1233.98 | H64: =+'Raw Data - Production'!N69+'Raw Data - Production'!O69+'Raw Data - Production'!P69+'Raw Data - Packing'!L69 -> 270 | I64: =SUMIF('Raw Data - Packing'!A:A,A64,'Raw Data - Packing'!D:D) -> 44580 | J64: =SUMIF('Raw Data - Packing'!A:A,A64,'Raw Data - Packing'!F:F) -> 8470 | L64: =+E64-I64+L63-(G64/Weights!$B$2) -> 0.069135802 | M64: =+F64-J64+M63-(H64/Weights!$B$4) -> 542 | N64: =+E64*Weights!$B$2 -> 3523.5 | O64: =+F64*Weights!$B$4 -> 951.5625 | Q64: =I64+J64 -> 53050
A65: =+'Raw Data - Production'!A70 -> 46210 | B65: =+WEEKNUM(A65) -> 28 | C65: =+TEXT(A65,"mmmm") -> July | D65: P7 | E65: =+'Raw Data - Production'!D70+'Raw Data - Production'!E70+'Raw Data - Production'!F70 -> 85824 | F65: =+'Raw Data - Production'!G70+'Raw Data - Production'!H70+'Raw Data - Production'!I70 -> 23415 | G65: =+'Raw Data - Production'!K70+'Raw Data - Production'!L70+'Raw Data - Packing'!I70 -> 426 | H65: =+'Raw Data - Production'!N70+'Raw Data - Production'!O70+'Raw Data - Production'!P70+'Raw Data - Packing'!L70 -> 221 | I65: =SUMIF('Raw Data - Packing'!A:A,A65,'Raw Data - Packing'!D:D) -> 75600 | J65: =SUMIF('Raw Data - Packing'!A:A,A65,'Raw Data - Packing'!F:F) -> 8640 | L65: =+E65-I65+L64-(G65/Weights!$B$2) -> 3492.2173 | M65: =+F65-J65+M64-(H65/Weights!$B$4) -> 13902.6 | N65: =+E65*Weights!$B$2 -> 5431.05 | O65: =+F65*Weights!$B$4 -> 3658.5938 | Q65: =I65+J65 -> 84240
A66: =+'Raw Data - Production'!A71 -> 46211 | B66: =+WEEKNUM(A66) -> 28 | C66: =+TEXT(A66,"mmmm") -> July | D66: P7 | E66: =+'Raw Data - Production'!D71+'Raw Data - Production'!E71+'Raw Data - Production'!F71 -> 62256 | F66: =+'Raw Data - Production'!G71+'Raw Data - Production'!H71+'Raw Data - Production'!I71 -> 20909 | G66: =+'Raw Data - Production'!K71+'Raw Data - Production'!L71+'Raw Data - Packing'!I71 -> 546 | H66: =+'Raw Data - Production'!N71+'Raw Data - Production'!O71+'Raw Data - Production'!P71+'Raw Data - Packing'!L71 -> 460 | I66: =SUMIF('Raw Data - Packing'!A:A,A66,'Raw Data - Packing'!D:D) -> 30480 | J66: =SUMIF('Raw Data - Packing'!A:A,A66,'Raw Data - Packing'!F:F) -> 9216 | L66: =+E66-I66+L65-(G66/Weights!$B$2) -> 26640.069 | M66: =+F66-J66+M65-(H66/Weights!$B$4) -> 22651.6 | N66: =+E66*Weights!$B$2 -> 3939.6375 | O66: =+F66*Weights!$B$4 -> 3267.0312 | Q66: =I66+J66 -> 39696
A67: =+'Raw Data - Production'!A72 -> 46212 | B67: =+WEEKNUM(A67) -> 28 | C67: =+TEXT(A67,"mmmm") -> July | D67: P7 | E67: =+'Raw Data - Production'!D72+'Raw Data - Production'!E72+'Raw Data - Production'!F72 -> 66816 | F67: =+'Raw Data - Production'!G72+'Raw Data - Production'!H72+'Raw Data - Production'!I72 -> 31710 | G67: =+'Raw Data - Production'!K72+'Raw Data - Production'!L72+'Raw Data - Packing'!I72 -> 342 | H67: =+'Raw Data - Production'!N72+'Raw Data - Production'!O72+'Raw Data - Production'!P72+'Raw Data - Packing'!L72 -> 211 | I67: =SUMIF('Raw Data - Packing'!A:A,A67,'Raw Data - Packing'!D:D) -> 0 | J67: =SUMIF('Raw Data - Packing'!A:A,A67,'Raw Data - Packing'!F:F) -> 26775 | L67: =+E67-I67+L66-(G67/Weights!$B$2) -> 88051.625 | M67: =+F67-J67+M66-(H67/Weights!$B$4) -> 26236.2 | N67: =+E67*Weights!$B$2 -> 4228.2 | O67: =+F67*Weights!$B$4 -> 4954.6875 | Q67: =I67+J67 -> 26775
A68: =+'Raw Data - Production'!A73 -> 46213 | B68: =+WEEKNUM(A68) -> 28 | C68: =+TEXT(A68,"mmmm") -> July | D68: P7 | E68: =+'Raw Data - Production'!D73+'Raw Data - Production'!E73+'Raw Data - Production'!F73 -> 0 | F68: =+'Raw Data - Production'!G73+'Raw Data - Production'!H73+'Raw Data - Production'!I73 -> 0 | G68: =+'Raw Data - Production'!K73+'Raw Data - Production'!L73+'Raw Data - Packing'!I73 -> 0 | H68: =+'Raw Data - Production'!N73+'Raw Data - Production'!O73+'Raw Data - Production'!P73+'Raw Data - Packing'!L73 -> 0 | I68: =SUMIF('Raw Data - Packing'!A:A,A68,'Raw Data - Packing'!D:D) -> 0 | J68: =SUMIF('Raw Data - Packing'!A:A,A68,'Raw Data - Packing'!F:F) -> 0 | L68: =+E68-I68+L67-(G68/Weights!$B$2) -> 88051.625 | M68: =+F68-J68+M67-(H68/Weights!$B$4) -> 26236.2 | N68: =+E68*Weights!$B$2 -> 0 | O68: =+F68*Weights!$B$4 -> 0 | Q68: =I68+J68 -> 0
A69: =+'Raw Data - Production'!A74 -> 46216 | B69: =+WEEKNUM(A69) -> 29 | C69: =+TEXT(A69,"mmmm") -> July | D69: P7 | E69: =+'Raw Data - Production'!D74+'Raw Data - Production'!E74+'Raw Data - Production'!F74 -> 0 | F69: =+'Raw Data - Production'!G74+'Raw Data - Production'!H74+'Raw Data - Production'!I74 -> 0 | G69: =+'Raw Data - Production'!K74+'Raw Data - Production'!L74+'Raw Data - Packing'!I74 -> 0 | H69: =+'Raw Data - Production'!N74+'Raw Data - Production'!O74+'Raw Data - Production'!P74+'Raw Data - Packing'!L74 -> 0 | I69: =SUMIF('Raw Data - Packing'!A:A,A69,'Raw Data - Packing'!D:D) -> 83250 | J69: =SUMIF('Raw Data - Packing'!A:A,A69,'Raw Data - Packing'!F:F) -> 10080 | L69: 0 | M69: =+F69-J69+M68-(H69/Weights!$B$4) -> 16156.2 | N69: =+E69*Weights!$B$2 -> 0 | O69: =+F69*Weights!$B$4 -> 0 | Q69: =I69+J69 -> 93330
A70: =+'Raw Data - Production'!A75 -> 46217 | B70: =+WEEKNUM(A70) -> 29 | C70: =+TEXT(A70,"mmmm") -> July | D70: P7 | E70: =+'Raw Data - Production'!D75+'Raw Data - Production'!E75+'Raw Data - Production'!F75 -> 0 | F70: =+'Raw Data - Production'!G75+'Raw Data - Production'!H75+'Raw Data - Production'!I75 -> 0 | G70: =+'Raw Data - Production'!K75+'Raw Data - Production'!L75+'Raw Data - Packing'!I75 -> 0 | H70: =+'Raw Data - Production'!N75+'Raw Data - Production'!O75+'Raw Data - Production'!P75+'Raw Data - Packing'!L75 -> 0 | I70: =SUMIF('Raw Data - Packing'!A:A,A70,'Raw Data - Packing'!D:D) -> 0 | J70: =SUMIF('Raw Data - Packing'!A:A,A70,'Raw Data - Packing'!F:F) -> 0 | L70: =+E70-I70+L69-(G70/Weights!$B$2) -> 0 | M70: =+F70-J70+M69-(H70/Weights!$B$4) -> 16156.2 | N70: =+E70*Weights!$B$2 -> 0 | O70: =+F70*Weights!$B$4 -> 0 | Q70: =I70+J70 -> 0
A71: =+'Raw Data - Production'!A76 -> 46218 | B71: =+WEEKNUM(A71) -> 29 | C71: =+TEXT(A71,"mmmm") -> July | D71: P7 | E71: =+'Raw Data - Production'!D76+'Raw Data - Production'!E76+'Raw Data - Production'!F76 -> 0 | F71: =+'Raw Data - Production'!G76+'Raw Data - Production'!H76+'Raw Data - Production'!I76 -> 0 | G71: =+'Raw Data - Production'!K76+'Raw Data - Production'!L76+'Raw Data - Packing'!I76 -> 0 | H71: =+'Raw Data - Production'!N76+'Raw Data - Production'!O76+'Raw Data - Production'!P76+'Raw Data - Packing'!L76 -> 0 | I71: =SUMIF('Raw Data - Packing'!A:A,A71,'Raw Data - Packing'!D:D) -> 0 | J71: =SUMIF('Raw Data - Packing'!A:A,A71,'Raw Data - Packing'!F:F) -> 0 | L71: =+E71-I71+L70-(G71/Weights!$B$2) -> 0 | M71: =+F71-J71+M70-(H71/Weights!$B$4) -> 16156.2 | N71: =+E71*Weights!$B$2 -> 0 | O71: =+F71*Weights!$B$4 -> 0 | Q71: =I71+J71 -> 0
A72: =+'Raw Data - Production'!A77 -> 46219 | B72: =+WEEKNUM(A72) -> 29 | C72: =+TEXT(A72,"mmmm") -> July | D72: P7 | E72: =+'Raw Data - Production'!D77+'Raw Data - Production'!E77+'Raw Data - Production'!F77 -> 0 | F72: =+'Raw Data - Production'!G77+'Raw Data - Production'!H77+'Raw Data - Production'!I77 -> 0 | G72: =+'Raw Data - Production'!K77+'Raw Data - Production'!L77+'Raw Data - Packing'!I77 -> 0 | H72: =+'Raw Data - Production'!N77+'Raw Data - Production'!O77+'Raw Data - Production'!P77+'Raw Data - Packing'!L77 -> 0 | I72: =SUMIF('Raw Data - Packing'!A:A,A72,'Raw Data - Packing'!D:D) -> 0 | J72: =SUMIF('Raw Data - Packing'!A:A,A72,'Raw Data - Packing'!F:F) -> 6160 | L72: =+E72-I72+L71-(G72/Weights!$B$2) -> 0 | M72: =+F72-J72+M71-(H72/Weights!$B$4) -> 9996.2 | N72: =+E72*Weights!$B$2 -> 0 | O72: =+F72*Weights!$B$4 -> 0 | Q72: =I72+J72 -> 6160
A73: =+'Raw Data - Production'!A78 -> 46220 | B73: =+WEEKNUM(A73) -> 29 | C73: =+TEXT(A73,"mmmm") -> July | D73: P7 | E73: =+'Raw Data - Production'!D78+'Raw Data - Production'!E78+'Raw Data - Production'!F78 -> 0 | F73: =+'Raw Data - Production'!G78+'Raw Data - Production'!H78+'Raw Data - Production'!I78 -> 0 | G73: =+'Raw Data - Production'!K78+'Raw Data - Production'!L78+'Raw Data - Packing'!I78 -> 0 | H73: =+'Raw Data - Production'!N78+'Raw Data - Production'!O78+'Raw Data - Production'!P78+'Raw Data - Packing'!L78 -> 0 | I73: =SUMIF('Raw Data - Packing'!A:A,A73,'Raw Data - Packing'!D:D) -> 0 | J73: =SUMIF('Raw Data - Packing'!A:A,A73,'Raw Data - Packing'!F:F) -> 0 | L73: =+E73-I73+L72-(G73/Weights!$B$2) -> 0 | M73: =+F73-J73+M72-(H73/Weights!$B$4) -> 9996.2 | N73: =+E73*Weights!$B$2 -> 0 | O73: =+F73*Weights!$B$4 -> 0 | Q73: =I73+J73 -> 0
A74: =+'Raw Data - Production'!A79 -> 46223 | B74: =+WEEKNUM(A74) -> 30 | C74: =+TEXT(A74,"mmmm") -> July | D74: P7 | E74: =+'Raw Data - Production'!D79+'Raw Data - Production'!E79+'Raw Data - Production'!F79 -> 52800 | F74: =+'Raw Data - Production'!G79+'Raw Data - Production'!H79+'Raw Data - Production'!I79 -> 0 | G74: =+'Raw Data - Production'!K79+'Raw Data - Production'!L79+'Raw Data - Packing'!I79 -> 200 | H74: =+'Raw Data - Production'!N79+'Raw Data - Production'!O79+'Raw Data - Production'!P79+'Raw Data - Packing'!L79 -> 0 | I74: =SUMIF('Raw Data - Packing'!A:A,A74,'Raw Data - Packing'!D:D) -> 0 | J74: =SUMIF('Raw Data - Packing'!A:A,A74,'Raw Data - Packing'!F:F) -> 0 | L74: =+E74-I74+L73-(G74/Weights!$B$2) -> 49639.506 | M74: =+F74-J74+M73-(H74/Weights!$B$4) -> 9996.2 | N74: =+E74*Weights!$B$2 -> 3341.25 | O74: =+F74*Weights!$B$4 -> 0 | Q74: =I74+J74 -> 0
A75: =+'Raw Data - Production'!A80 -> 46224 | B75: =+WEEKNUM(A75) -> 30 | C75: =+TEXT(A75,"mmmm") -> July | D75: P7 | E75: =+'Raw Data - Production'!D80+'Raw Data - Production'!E80+'Raw Data - Production'!F80 -> 82848 | F75: =+'Raw Data - Production'!G80+'Raw Data - Production'!H80+'Raw Data - Production'!I80 -> 29645 | G75: =+'Raw Data - Production'!K80+'Raw Data - Production'!L80+'Raw Data - Packing'!I80 -> 277 | H75: =+'Raw Data - Production'!N80+'Raw Data - Production'!O80+'Raw Data - Production'!P80+'Raw Data - Packing'!L80 -> 570 | I75: =SUMIF('Raw Data - Packing'!A:A,A75,'Raw Data - Packing'!D:D) -> 0 | J75: =SUMIF('Raw Data - Packing'!A:A,A75,'Raw Data - Packing'!F:F) -> 21440 | L75: =+E75-I75+L74-(G75/Weights!$B$2) -> 128110.22 | M75: =+F75-J75+M74-(H75/Weights!$B$4) -> 14553.2 | N75: =+E75*Weights!$B$2 -> 5242.725 | O75: =+F75*Weights!$B$4 -> 4632.0312 | Q75: =I75+J75 -> 21440
A76: =+'Raw Data - Production'!A81 -> 46225 | B76: =+WEEKNUM(A76) -> 30 | C76: =+TEXT(A76,"mmmm") -> July | D76: P7 | E76: =+'Raw Data - Production'!D81+'Raw Data - Production'!E81+'Raw Data - Production'!F81 -> 73296 | F76: =+'Raw Data - Production'!G81+'Raw Data - Production'!H81+'Raw Data - Production'!I81 -> 23800 | G76: =+'Raw Data - Production'!K81+'Raw Data - Production'!L81+'Raw Data - Packing'!I81 -> 510 | H76: =+'Raw Data - Production'!N81+'Raw Data - Production'!O81+'Raw Data - Production'!P81+'Raw Data - Packing'!L81 -> 512 | I76: =SUMIF('Raw Data - Packing'!A:A,A76,'Raw Data - Packing'!D:D) -> 37800 | J76: =SUMIF('Raw Data - Packing'!A:A,A76,'Raw Data - Packing'!F:F) -> 32704 | L76: =+E76-I76+L75-(G76/Weights!$B$2) -> 155546.96 | M76: =+F76-J76+M75-(H76/Weights!$B$4) -> 2372.4 | N76: =+E76*Weights!$B$2 -> 4638.2625 | O76: =+F76*Weights!$B$4 -> 3718.75 | Q76: =I76+J76 -> 70504
A77: =+'Raw Data - Production'!A82 -> 46226 | B77: =+WEEKNUM(A77) -> 30 | C77: =+TEXT(A77,"mmmm") -> July | D77: P7 | E77: =+'Raw Data - Production'!D82+'Raw Data - Production'!E82+'Raw Data - Production'!F82 -> 75264 | F77: =+'Raw Data - Production'!G82+'Raw Data - Production'!H82+'Raw Data - Production'!I82 -> 21542.5 | G77: =+'Raw Data - Production'!K82+'Raw Data - Production'!L82+'Raw Data - Packing'!I82 -> 373 | H77: =+'Raw Data - Production'!N82+'Raw Data - Production'!O82+'Raw Data - Production'!P82+'Raw Data - Packing'!L82 -> 573 | I77: =SUMIF('Raw Data - Packing'!A:A,A77,'Raw Data - Packing'!D:D) -> 60480 | J77: =SUMIF('Raw Data - Packing'!A:A,A77,'Raw Data - Packing'!F:F) -> 24288 | L77: =+E77-I77+L76-(G77/Weights!$B$2) -> 164436.64 | M77: =13*150 -> 1950 | N77: =+E77*Weights!$B$2 -> 4762.8 | O77: =+F77*Weights!$B$4 -> 3366.0156 | Q77: =I77+J77 -> 84768
A78: =+'Raw Data - Production'!A83 -> 46227 | B78: =+WEEKNUM(A78) -> 30 | C78: =+TEXT(A78,"mmmm") -> July | D78: P7 | E78: =+'Raw Data - Production'!D83+'Raw Data - Production'!E83+'Raw Data - Production'!F83 -> 0 | F78: =+'Raw Data - Production'!G83+'Raw Data - Production'!H83+'Raw Data - Production'!I83 -> 0 | G78: =+'Raw Data - Production'!K83+'Raw Data - Production'!L83+'Raw Data - Packing'!I83 -> 147 | H78: =+'Raw Data - Production'!N83+'Raw Data - Production'!O83+'Raw Data - Production'!P83+'Raw Data - Packing'!L83 -> 0 | I78: =SUMIF('Raw Data - Packing'!A:A,A78,'Raw Data - Packing'!D:D) -> 87135 | J78: =SUMIF('Raw Data - Packing'!A:A,A78,'Raw Data - Packing'!F:F) -> 1888 | L78: =+E78-I78+L77-(G78/Weights!$B$2) -> 74978.679 | M78: 0 | N78: =+E78*Weights!$B$2 -> 0 | O78: =+F78*Weights!$B$4 -> 0 | Q78: =I78+J78 -> 89023
A79: =+'Raw Data - Production'!A84 -> 46230 | B79: =+WEEKNUM(A79) -> 31 | C79: =+TEXT(A79,"mmmm") -> July | D79: P7 | E79: =+'Raw Data - Production'!D84+'Raw Data - Production'!E84+'Raw Data - Production'!F84 -> 56448 | F79: =+'Raw Data - Production'!G84+'Raw Data - Production'!H84+'Raw Data - Production'!I84 -> 25392.5 | G79: =+'Raw Data - Production'!K84+'Raw Data - Production'!L84+'Raw Data - Packing'!I84 -> 424 | H79: =+'Raw Data - Production'!N84+'Raw Data - Production'!O84+'Raw Data - Production'!P84+'Raw Data - Packing'!L84 -> 183 | I79: =SUMIF('Raw Data - Packing'!A:A,A79,'Raw Data - Packing'!D:D) -> 62490 | J79: =SUMIF('Raw Data - Packing'!A:A,A79,'Raw Data - Packing'!F:F) -> 19392 | L79: =+E79-I79+L78-(G79/Weights!$B$2) -> 62236.432 | M79: =+F79-J79+M78-(H79/Weights!$B$4) -> 4829.3 | N79: =+E79*Weights!$B$2 -> 3572.1 | O79: =+F79*Weights!$B$4 -> 3967.5781 | Q79: =I79+J79 -> 81882
A80: =+'Raw Data - Production'!A85 -> 46231 | B80: =+WEEKNUM(A80) -> 31 | C80: =+TEXT(A80,"mmmm") -> July | D80: P7 | E80: =+'Raw Data - Production'!D85+'Raw Data - Production'!E85+'Raw Data - Production'!F85 -> 48888 | F80: =+'Raw Data - Production'!G85+'Raw Data - Production'!H85+'Raw Data - Production'!I85 -> 29662 | G80: =+'Raw Data - Production'!K85+'Raw Data - Production'!L85+'Raw Data - Packing'!I85 -> 198 | H80: =+'Raw Data - Production'!N85+'Raw Data - Production'!O85+'Raw Data - Production'!P85+'Raw Data - Packing'!L85 -> 154 | I80: =SUMIF('Raw Data - Packing'!A:A,A80,'Raw Data - Packing'!D:D) -> 104775 | J80: =SUMIF('Raw Data - Packing'!A:A,A80,'Raw Data - Packing'!F:F) -> 26944 | L80: =+E80-I80+L79-(G80/Weights!$B$2) -> 3220.5432 | M80: =+F80-J80+M79-(H80/Weights!$B$4) -> 6561.7 | N80: =+E80*Weights!$B$2 -> 3093.6937 | O80: =+F80*Weights!$B$4 -> 4634.6875 | Q80: =I80+J80 -> 131719
A81: =+'Raw Data - Production'!A86 -> 46232 | B81: =+WEEKNUM(A81) -> 31 | C81: =+TEXT(A81,"mmmm") -> July | D81: P7 | E81: =+'Raw Data - Production'!D86+'Raw Data - Production'!E86+'Raw Data - Production'!F86 -> 69080 | F81: =+'Raw Data - Production'!G86+'Raw Data - Production'!H86+'Raw Data - Production'!I86 -> 34527.5 | G81: =+'Raw Data - Production'!K86+'Raw Data - Production'!L86+'Raw Data - Packing'!I86 -> 516.85 | H81: =+'Raw Data - Production'!N86+'Raw Data - Production'!O86+'Raw Data - Production'!P86+'Raw Data - Packing'!L86 -> 1134 | I81: =SUMIF('Raw Data - Packing'!A:A,A81,'Raw Data - Packing'!D:D) -> 58320 | J81: =SUMIF('Raw Data - Packing'!A:A,A81,'Raw Data - Packing'!F:F) -> 22560 | L81: =+E81-I81+L80-(G81/Weights!$B$2) -> 5813.037 | M81: =+F81-J81+M80-(H81/Weights!$B$4) -> 11271.6 | N81: =+E81*Weights!$B$2 -> 4371.4688 | O81: =+F81*Weights!$B$4 -> 5394.9219 | Q81: =I81+J81 -> 80880
A82: =+'Raw Data - Production'!A87 -> 46233 | B82: =+WEEKNUM(A82) -> 31 | C82: =+TEXT(A82,"mmmm") -> July | D82: P7 | E82: =+'Raw Data - Production'!D87+'Raw Data - Production'!E87+'Raw Data - Production'!F87 -> 41664 | F82: =+'Raw Data - Production'!G87+'Raw Data - Production'!H87+'Raw Data - Production'!I87 -> 0 | G82: =+'Raw Data - Production'!K87+'Raw Data - Production'!L87+'Raw Data - Packing'!I87 -> 280 | H82: =+'Raw Data - Production'!N87+'Raw Data - Production'!O87+'Raw Data - Production'!P87+'Raw Data - Packing'!L87 -> 431.25 | I82: =SUMIF('Raw Data - Packing'!A:A,A82,'Raw Data - Packing'!D:D) -> 45360 | J82: =SUMIF('Raw Data - Packing'!A:A,A82,'Raw Data - Packing'!F:F) -> 8512 | L82: =+E82-I82+L81-(G82/Weights!$B$2) -> -2307.6543 | M82: =+F82-J82+M81-(H82/Weights!$B$4) -> -0.4 | N82: =+E82*Weights!$B$2 -> 2636.55 | O82: =+F82*Weights!$B$4 -> 0 | Q82: =I82+J82 -> 53872
A83: =+'Raw Data - Production'!A88 -> 46234 | B83: =+WEEKNUM(A83) -> 31 | C83: =+TEXT(A83,"mmmm") -> July | D83: P7 | E83: =+'Raw Data - Production'!D88+'Raw Data - Production'!E88+'Raw Data - Production'!F88 -> 0 | F83: =+'Raw Data - Production'!G88+'Raw Data - Production'!H88+'Raw Data - Production'!I88 -> 0 | G83: =+'Raw Data - Production'!K88+'Raw Data - Production'!L88+'Raw Data - Packing'!I88 -> 0 | H83: =+'Raw Data - Production'!N88+'Raw Data - Production'!O88+'Raw Data - Production'!P88+'Raw Data - Packing'!L88 -> 0 | I83: =SUMIF('Raw Data - Packing'!A:A,A83,'Raw Data - Packing'!D:D) -> 0 | J83: =SUMIF('Raw Data - Packing'!A:A,A83,'Raw Data - Packing'!F:F) -> 0 | L83: =+E83-I83+L82-(G83/Weights!$B$2) -> -2307.6543 | M83: =+F83-J83+M82-(H83/Weights!$B$4) -> -0.4 | N83: =+E83*Weights!$B$2 -> 0 | O83: =+F83*Weights!$B$4 -> 0 | Q83: =I83+J83 -> 0
A84: =+'Raw Data - Production'!A89 -> 46237 | B84: =+WEEKNUM(A84) -> 32 | C84: =+TEXT(A84,"mmmm") -> August | D84: P8 | E84: =+'Raw Data - Production'!D89+'Raw Data - Production'!E89+'Raw Data - Production'!F89 -> 69792 | F84: =+'Raw Data - Production'!G89+'Raw Data - Production'!H89+'Raw Data - Production'!I89 -> 44765 | G84: =+'Raw Data - Production'!K89+'Raw Data - Production'!L89+'Raw Data - Packing'!I89 -> 411 | H84: =+'Raw Data - Production'!N89+'Raw Data - Production'!O89+'Raw Data - Production'!P89+'Raw Data - Packing'!L89 -> 1024 | I84: =SUMIF('Raw Data - Packing'!A:A,A84,'Raw Data - Packing'!D:D) -> 59940 | J84: =SUMIF('Raw Data - Packing'!A:A,A84,'Raw Data - Packing'!F:F) -> 21600 | L84: =+E84-I84+L83-(G84/Weights!$B$2) -> 1049.5309 | M84: =+F84-J84+M83-(H84/Weights!$B$4) -> 16611 | N84: =+E84*Weights!$B$2 -> 4416.525 | O84: =+F84*Weights!$B$4 -> 6994.5312 | Q84: =I84+J84 -> 81540
A85: =+'Raw Data - Production'!A90 -> 46238 | B85: =+WEEKNUM(A85) -> 32 | C85: =+TEXT(A85,"mmmm") -> August | D85: P8 | E85: =+'Raw Data - Production'!D90+'Raw Data - Production'!E90+'Raw Data - Production'!F90 -> 87648 | F85: =+'Raw Data - Production'!G90+'Raw Data - Production'!H90+'Raw Data - Production'!I90 -> 35560 | G85: =+'Raw Data - Production'!K90+'Raw Data - Production'!L90+'Raw Data - Packing'!I90 -> 762 | H85: =+'Raw Data - Production'!N90+'Raw Data - Production'!O90+'Raw Data - Production'!P90+'Raw Data - Packing'!L90 -> 524 | I85: =SUMIF('Raw Data - Packing'!A:A,A85,'Raw Data - Packing'!D:D) -> 78780 | J85: =SUMIF('Raw Data - Packing'!A:A,A85,'Raw Data - Packing'!F:F) -> 25920 | L85: =+E85-I85+L84-(G85/Weights!$B$2) -> -2123.9506 | M85: =+F85-J85+M84-(H85/Weights!$B$4) -> 22897.4 | N85: =+E85*Weights!$B$2 -> 5546.475 | O85: =+F85*Weights!$B$4 -> 5556.25 | Q85: =I85+J85 -> 104700
A86: =+'Raw Data - Production'!A91 -> 46239 | B86: =+WEEKNUM(A86) -> 32 | C86: =+TEXT(A86,"mmmm") -> August | D86: P8 | E86: =+'Raw Data - Production'!D91+'Raw Data - Production'!E91+'Raw Data - Production'!F91 -> 80592 | F86: =+'Raw Data - Production'!G91+'Raw Data - Production'!H91+'Raw Data - Production'!I91 -> 32830 | G86: =+'Raw Data - Production'!K91+'Raw Data - Production'!L91+'Raw Data - Packing'!I91 -> 735 | H86: =+'Raw Data - Production'!N91+'Raw Data - Production'!O91+'Raw Data - Production'!P91+'Raw Data - Packing'!L91 -> 984 | I86: =SUMIF('Raw Data - Packing'!A:A,A86,'Raw Data - Packing'!D:D) -> 52920 | J86: =SUMIF('Raw Data - Packing'!A:A,A86,'Raw Data - Packing'!F:F) -> 21600 | L86: =+E86-I86+L85-(G86/Weights!$B$2) -> 13933.235 | M86: =+F86-J86+M85-(H86/Weights!$B$4) -> 27829.8 | N86: =+E86*Weights!$B$2 -> 5099.9625 | O86: =+F86*Weights!$B$4 -> 5129.6875 | Q86: =I86+J86 -> 74520
A87: =+'Raw Data - Production'!A92 -> 46240 | B87: =+WEEKNUM(A87) -> 32 | C87: =+TEXT(A87,"mmmm") -> August | D87: P8 | E87: =+'Raw Data - Production'!D92+'Raw Data - Production'!E92+'Raw Data - Production'!F92 -> 50400 | F87: =+'Raw Data - Production'!G92+'Raw Data - Production'!H92+'Raw Data - Production'!I92 -> 35105 | G87: =+'Raw Data - Production'!K92+'Raw Data - Production'!L92+'Raw Data - Packing'!I92 -> 509 | H87: =+'Raw Data - Production'!N92+'Raw Data - Production'!O92+'Raw Data - Production'!P92+'Raw Data - Packing'!L92 -> 604 | I87: =SUMIF('Raw Data - Packing'!A:A,A87,'Raw Data - Packing'!D:D) -> 43560 | J87: =SUMIF('Raw Data - Packing'!A:A,A87,'Raw Data - Packing'!F:F) -> 30240 | L87: =+E87-I87+L86-(G87/Weights!$B$2) -> 12729.778 | M87: =+F87-J87+M86-(H87/Weights!$B$4) -> 28829.2 | N87: =+E87*Weights!$B$2 -> 3189.375 | O87: =+F87*Weights!$B$4 -> 5485.1562 | Q87: =I87+J87 -> 73800
A88: =+'Raw Data - Production'!A93 -> 46241 | B88: =+WEEKNUM(A88) -> 32 | C88: =+TEXT(A88,"mmmm") -> August | D88: P8 | E88: =+'Raw Data - Production'!D93+'Raw Data - Production'!E93+'Raw Data - Production'!F93 -> 0 | F88: =+'Raw Data - Production'!G93+'Raw Data - Production'!H93+'Raw Data - Production'!I93 -> 0 | G88: =+'Raw Data - Production'!K93+'Raw Data - Production'!L93+'Raw Data - Packing'!I93 -> 0 | H88: =+'Raw Data - Production'!N93+'Raw Data - Production'!O93+'Raw Data - Production'!P93+'Raw Data - Packing'!L93 -> 0 | I88: =SUMIF('Raw Data - Packing'!A:A,A88,'Raw Data - Packing'!D:D) -> 0 | J88: =SUMIF('Raw Data - Packing'!A:A,A88,'Raw Data - Packing'!F:F) -> 0 | L88: =+E88-I88+L87-(G88/Weights!$B$2) -> 12729.778 | M88: =+F88-J88+M87-(H88/Weights!$B$4) -> 28829.2 | N88: =+E88*Weights!$B$2 -> 0 | O88: =+F88*Weights!$B$4 -> 0 | Q88: =I88+J88 -> 0
A89: =+'Raw Data - Production'!A94 -> 46244 | B89: =+WEEKNUM(A89) -> 33 | C89: =+TEXT(A89,"mmmm") -> August | D89: P8 | E89: =+'Raw Data - Production'!D94+'Raw Data - Production'!E94+'Raw Data - Production'!F94 -> 68736 | F89: =+'Raw Data - Production'!G94+'Raw Data - Production'!H94+'Raw Data - Production'!I94 -> 46690 | G89: =+'Raw Data - Production'!K94+'Raw Data - Production'!L94+'Raw Data - Packing'!I94 -> 250 | H89: =+'Raw Data - Production'!N94+'Raw Data - Production'!O94+'Raw Data - Production'!P94+'Raw Data - Packing'!L94 -> 1060 | I89: =SUMIF('Raw Data - Packing'!A:A,A89,'Raw Data - Packing'!D:D) -> 63780 | J89: =SUMIF('Raw Data - Packing'!A:A,A89,'Raw Data - Packing'!F:F) -> 30336 | L89: =+E89-I89+L88-(G89/Weights!$B$2) -> 13735.16 | M89: =+F89-J89+M88-(H89/Weights!$B$4) -> 38399.2 | N89: =+E89*Weights!$B$2 -> 4349.7 | O89: =+F89*Weights!$B$4 -> 7295.3125 | Q89: =I89+J89 -> 94116 | S89: =+E89-(G89*Weights!$B$2) -> 68720.18 | T89: =+F89-(H89*Weights!$B$4) -> 46524.375
A90: =+'Raw Data - Production'!A95 -> 46245 | B90: =+WEEKNUM(A90) -> 33 | C90: =+TEXT(A90,"mmmm") -> August | D90: P8 | E90: =+'Raw Data - Production'!D95+'Raw Data - Production'!E95+'Raw Data - Production'!F95 -> 84960 | F90: =+'Raw Data - Production'!G95+'Raw Data - Production'!H95+'Raw Data - Production'!I95 -> 40425 | G90: =+'Raw Data - Production'!K95+'Raw Data - Production'!L95+'Raw Data - Packing'!I95 -> 336 | H90: =+'Raw Data - Production'!N95+'Raw Data - Production'!O95+'Raw Data - Production'!P95+'Raw Data - Packing'!L95 -> 862 | I90: =SUMIF('Raw Data - Packing'!A:A,A90,'Raw Data - Packing'!D:D) -> 48060 | J90: =SUMIF('Raw Data - Packing'!A:A,A90,'Raw Data - Packing'!F:F) -> 40550 | L90: =+E90-I90+L89-(G90/Weights!$B$2) -> 45325.531 | M90: =+F90-J90+M89-(H90/Weights!$B$4) -> 32757.4 | N90: =+E90*Weights!$B$2 -> 5376.375 | O90: =+F90*Weights!$B$4 -> 6316.4062 | Q90: =I90+J90 -> 88610 | S90: =+E90-(G90*Weights!$B$2) -> 84938.738 | T90: =+F90-(H90*Weights!$B$4) -> 40290.312
A91: =+'Raw Data - Production'!A96 -> 46246 | B91: =+WEEKNUM(A91) -> 33 | C91: =+TEXT(A91,"mmmm") -> August | D91: P8 | E91: =+'Raw Data - Production'!D96+'Raw Data - Production'!E96+'Raw Data - Production'!F96 -> 90720 | F91: =+'Raw Data - Production'!G96+'Raw Data - Production'!H96+'Raw Data - Production'!I96 -> 40565 | G91: =+'Raw Data - Production'!K96+'Raw Data - Production'!L96+'Raw Data - Packing'!I96 -> 306 | H91: =+'Raw Data - Production'!N96+'Raw Data - Production'!O96+'Raw Data - Production'!P96+'Raw Data - Packing'!L96 -> 189 | I91: =SUMIF('Raw Data - Packing'!A:A,A91,'Raw Data - Packing'!D:D) -> 60480 | J91: =SUMIF('Raw Data - Packing'!A:A,A91,'Raw Data - Packing'!F:F) -> 28800 | L91: =+E91-I91+L90-(G91/Weights!$B$2) -> 70729.975 | M91: =+F91-J91+M90-(H91/Weights!$B$4) -> 43312.8 | N91: =+E91*Weights!$B$2 -> 5740.875 | O91: =+F91*Weights!$B$4 -> 6338.2812 | Q91: =I91+J91 -> 89280 | S91: =+E91-(G91*Weights!$B$2) -> 90700.636 | T91: =+F91-(H91*Weights!$B$4) -> 40535.469
A92: =+'Raw Data - Production'!A97 -> 46247 | B92: =+WEEKNUM(A92) -> 33 | C92: =+TEXT(A92,"mmmm") -> August | D92: P8 | E92: =+'Raw Data - Production'!D97+'Raw Data - Production'!E97+'Raw Data - Production'!F97 -> 0 | F92: =+'Raw Data - Production'!G97+'Raw Data - Production'!H97+'Raw Data - Production'!I97 -> 0 | G92: =+'Raw Data - Production'!K97+'Raw Data - Production'!L97+'Raw Data - Packing'!I97 -> 0 | H92: =+'Raw Data - Production'!N97+'Raw Data - Production'!O97+'Raw Data - Production'!P97+'Raw Data - Packing'!L97 -> 0 | I92: =SUMIF('Raw Data - Packing'!A:A,A92,'Raw Data - Packing'!D:D) -> 25320 | J92: =SUMIF('Raw Data - Packing'!A:A,A92,'Raw Data - Packing'!F:F) -> 18332 | L92: =+E92-I92+L91-(G92/Weights!$B$2) -> 45409.975 | M92: =+F92-J92+M91-(H92/Weights!$B$4) -> 24980.8 | N92: =+E92*Weights!$B$2 -> 0 | O92: =+F92*Weights!$B$4 -> 0 | Q92: =I92+J92 -> 43652 | S92: =+E92-(G92*Weights!$B$2) -> 0 | T92: =+F92-(H92*Weights!$B$4) -> 0
A93: =+'Raw Data - Production'!A98 -> 46248 | B93: =+WEEKNUM(A93) -> 33 | C93: =+TEXT(A93,"mmmm") -> August | D93: P8 | E93: =+'Raw Data - Production'!D98+'Raw Data - Production'!E98+'Raw Data - Production'!F98 -> 0 | F93: =+'Raw Data - Production'!G98+'Raw Data - Production'!H98+'Raw Data - Production'!I98 -> 0 | G93: =+'Raw Data - Production'!K98+'Raw Data - Production'!L98+'Raw Data - Packing'!I98 -> 0 | H93: =+'Raw Data - Production'!N98+'Raw Data - Production'!O98+'Raw Data - Production'!P98+'Raw Data - Packing'!L98 -> 0 | I93: =SUMIF('Raw Data - Packing'!A:A,A93,'Raw Data - Packing'!D:D) -> 0 | J93: =SUMIF('Raw Data - Packing'!A:A,A93,'Raw Data - Packing'!F:F) -> 0 | L93: =+E93-I93+L92-(G93/Weights!$B$2) -> 45409.975 | M93: =+F93-J93+M92-(H93/Weights!$B$4) -> 24980.8 | N93: =+E93*Weights!$B$2 -> 0 | O93: =+F93*Weights!$B$4 -> 0 | Q93: =I93+J93 -> 0 | S93: =+E93-(G93*Weights!$B$2) -> 0 | T93: =+F93-(H93*Weights!$B$4) -> 0
A94: =+'Raw Data - Production'!A99 -> 46251 | B94: =+WEEKNUM(A94) -> 34 | C94: =+TEXT(A94,"mmmm") -> August | D94: P8 | E94: =+'Raw Data - Production'!D99+'Raw Data - Production'!E99+'Raw Data - Production'!F99 -> 0 | F94: =+'Raw Data - Production'!G99+'Raw Data - Production'!H99+'Raw Data - Production'!I99 -> 47005 | G94: =+'Raw Data - Production'!K99+'Raw Data - Production'!L99+'Raw Data - Packing'!I99 -> 20 | H94: =+'Raw Data - Production'!N99+'Raw Data - Production'!O99+'Raw Data - Production'!P99+'Raw Data - Packing'!L99 -> 158 | I94: =SUMIF('Raw Data - Packing'!A:A,A94,'Raw Data - Packing'!D:D) -> 30240 | J94: =SUMIF('Raw Data - Packing'!A:A,A94,'Raw Data - Packing'!F:F) -> 21600 | L94: =+E94-I94+L93-(G94/Weights!$B$2) -> 14853.926 | M94: =+F94-J94+M93-(H94/Weights!$B$4) -> 49374.6 | N94: =+E94*Weights!$B$2 -> 0 | O94: =+F94*Weights!$B$4 -> 7344.5312 | Q94: =I94+J94 -> 51840 | S94: =+E94-(G94*Weights!$B$2) -> -1.265625 | T94: =+F94-(H94*Weights!$B$4) -> 46980.312
A95: =+'Raw Data - Production'!A100 -> 46252 | B95: =+WEEKNUM(A95) -> 34 | C95: =+TEXT(A95,"mmmm") -> August | D95: P8 | E95: =+'Raw Data - Production'!D100+'Raw Data - Production'!E100+'Raw Data - Production'!F100 -> 109824 | F95: =+'Raw Data - Production'!G100+'Raw Data - Production'!H100+'Raw Data - Production'!I100 -> 5775 | G95: =+'Raw Data - Production'!K100+'Raw Data - Production'!L100+'Raw Data - Packing'!I100 -> 329 | H95: =+'Raw Data - Production'!N100+'Raw Data - Production'!O100+'Raw Data - Production'!P100+'Raw Data - Packing'!L100 -> 28 | I95: =SUMIF('Raw Data - Packing'!A:A,A95,'Raw Data - Packing'!D:D) -> 15120 | J95: =SUMIF('Raw Data - Packing'!A:A,A95,'Raw Data - Packing'!F:F) -> 22880 | L95: =+E95-I95+L94-(G95/Weights!$B$2) -> 104358.91 | M95: =+F95-J95+M94-(H95/Weights!$B$4) -> 32090.4 | N95: =+E95*Weights!$B$2 -> 6949.8 | O95: =+F95*Weights!$B$4 -> 902.34375 | Q95: =I95+J95 -> 38000 | S95: =+E95-(G95*Weights!$B$2) -> 109803.18 | T95: =+F95-(H95*Weights!$B$4) -> 5770.625
A96: =+'Raw Data - Production'!A101 -> 46253 | B96: =+WEEKNUM(A96) -> 34 | C96: =+TEXT(A96,"mmmm") -> August | D96: P8 | E96: =+'Raw Data - Production'!D101+'Raw Data - Production'!E101+'Raw Data - Production'!F101 -> 0 | F96: =+'Raw Data - Production'!G101+'Raw Data - Production'!H101+'Raw Data - Production'!I101 -> 0 | G96: =+'Raw Data - Production'!K101+'Raw Data - Production'!L101+'Raw Data - Packing'!I101 -> 0 | H96: =+'Raw Data - Production'!N101+'Raw Data - Production'!O101+'Raw Data - Production'!P101+'Raw Data - Packing'!L101 -> 0 | I96: =SUMIF('Raw Data - Packing'!A:A,A96,'Raw Data - Packing'!D:D) -> 99300 | J96: =SUMIF('Raw Data - Packing'!A:A,A96,'Raw Data - Packing'!F:F) -> 8576 | L96: 0 | M96: =+F96-J96+M95-(H96/Weights!$B$4) -> 23514.4 | N96: =+E96*Weights!$B$2 -> 0 | O96: =+F96*Weights!$B$4 -> 0 | Q96: =I96+J96 -> 107876 | S96: =+E96-(G96*Weights!$B$2) -> 0 | T96: =+F96-(H96*Weights!$B$4) -> 0
A97: =+'Raw Data - Production'!A102 -> 46254 | B97: =+WEEKNUM(A97) -> 34 | C97: =+TEXT(A97,"mmmm") -> August | D97: P8 | E97: =+'Raw Data - Production'!D102+'Raw Data - Production'!E102+'Raw Data - Production'!F102 -> 0 | F97: =+'Raw Data - Production'!G102+'Raw Data - Production'!H102+'Raw Data - Production'!I102 -> 0 | G97: =+'Raw Data - Production'!K102+'Raw Data - Production'!L102+'Raw Data - Packing'!I102 -> 0 | H97: =+'Raw Data - Production'!N102+'Raw Data - Production'!O102+'Raw Data - Production'!P102+'Raw Data - Packing'!L102 -> 0 | I97: =SUMIF('Raw Data - Packing'!A:A,A97,'Raw Data - Packing'!D:D) -> 0 | J97: =SUMIF('Raw Data - Packing'!A:A,A97,'Raw Data - Packing'!F:F) -> 0 | L97: =+E97-I97+L96-(G97/Weights!$B$2) -> 0 | M97: =+F97-J97+M96-(H97/Weights!$B$4) -> 23514.4 | N97: =+E97*Weights!$B$2 -> 0 | O97: =+F97*Weights!$B$4 -> 0 | Q97: =I97+J97 -> 0 | S97: =+E97-(G97*Weights!$B$2) -> 0 | T97: =+F97-(H97*Weights!$B$4) -> 0
A98: =+'Raw Data - Production'!A103 -> 46255 | B98: =+WEEKNUM(A98) -> 34 | C98: =+TEXT(A98,"mmmm") -> August | D98: P8 | E98: =+'Raw Data - Production'!D103+'Raw Data - Production'!E103+'Raw Data - Production'!F103 -> 0 | F98: =+'Raw Data - Production'!G103+'Raw Data - Production'!H103+'Raw Data - Production'!I103 -> 0 | G98: =+'Raw Data - Production'!K103+'Raw Data - Production'!L103+'Raw Data - Packing'!I103 -> 0 | H98: =+'Raw Data - Production'!N103+'Raw Data - Production'!O103+'Raw Data - Production'!P103+'Raw Data - Packing'!L103 -> 0 | I98: =SUMIF('Raw Data - Packing'!A:A,A98,'Raw Data - Packing'!D:D) -> 0 | J98: =SUMIF('Raw Data - Packing'!A:A,A98,'Raw Data - Packing'!F:F) -> 0 | L98: =+E98-I98+L97-(G98/Weights!$B$2) -> 0 | M98: 2750 | N98: =+E98*Weights!$B$2 -> 0 | O98: =+F98*Weights!$B$4 -> 0 | Q98: =I98+J98 -> 0 | S98: =+E98-(G98*Weights!$B$2) -> 0 | T98: =+F98-(H98*Weights!$B$4) -> 0
A99: =+'Raw Data - Production'!A104 -> 46258 | B99: =+WEEKNUM(A99) -> 35 | C99: =+TEXT(A99,"mmmm") -> August | D99: P8 | E99: =+'Raw Data - Production'!D104+'Raw Data - Production'!E104+'Raw Data - Production'!F104 -> 0 | F99: =+'Raw Data - Production'!G104+'Raw Data - Production'!H104+'Raw Data - Production'!I104 -> 57015 | G99: =+'Raw Data - Production'!K104+'Raw Data - Production'!L104+'Raw Data - Packing'!I104 -> 0 | H99: =+'Raw Data - Production'!N104+'Raw Data - Production'!O104+'Raw Data - Production'!P104+'Raw Data - Packing'!L104 -> 776 | I99: =SUMIF('Raw Data - Packing'!A:A,A99,'Raw Data - Packing'!D:D) -> 0 | J99: =SUMIF('Raw Data - Packing'!A:A,A99,'Raw Data - Packing'!F:F) -> 30240 | L99: =+E99-I99+L98-(G99/Weights!$B$2) -> 0 | M99: =+F99-J99+M98-(H99/Weights!$B$4) -> 24558.6 | N99: =+E99*Weights!$B$2 -> 0 | O99: =+F99*Weights!$B$4 -> 8908.5938 | Q99: =I99+J99 -> 30240
A100: =+'Raw Data - Production'!A105 -> 46259 | B100: =+WEEKNUM(A100) -> 35 | C100: =+TEXT(A100,"mmmm") -> August | D100: P8 | E100: =+'Raw Data - Production'!D105+'Raw Data - Production'!E105+'Raw Data - Production'!F105 -> 101856 | F100: =+'Raw Data - Production'!G105+'Raw Data - Production'!H105+'Raw Data - Production'!I105 -> 38972.5 | G100: =+'Raw Data - Production'!K105+'Raw Data - Production'!L105+'Raw Data - Packing'!I105 -> 339 | H100: =+'Raw Data - Production'!N105+'Raw Data - Production'!O105+'Raw Data - Production'!P105+'Raw Data - Packing'!L105 -> 406 | I100: =SUMIF('Raw Data - Packing'!A:A,A100,'Raw Data - Packing'!D:D) -> 93240 | J100: =SUMIF('Raw Data - Packing'!A:A,A100,'Raw Data - Packing'!F:F) -> 24576 | L100: 0 | M100: =+F100-J100+M99-(H100/Weights!$B$4) -> 36356.7 | N100: =+E100*Weights!$B$2 -> 6445.575 | O100: =+F100*Weights!$B$4 -> 6089.4531 | Q100: =I100+J100 -> 117816
A101: =+'Raw Data - Production'!A106 -> 46260 | B101: =+WEEKNUM(A101) -> 35 | C101: =+TEXT(A101,"mmmm") -> August | D101: P8 | E101: =+'Raw Data - Production'!D106+'Raw Data - Production'!E106+'Raw Data - Production'!F106 -> 135456 | F101: =+'Raw Data - Production'!G106+'Raw Data - Production'!H106+'Raw Data - Production'!I106 -> 40425 | G101: =+'Raw Data - Production'!K106+'Raw Data - Production'!L106+'Raw Data - Packing'!I106 -> 871 | H101: =+'Raw Data - Production'!N106+'Raw Data - Production'!O106+'Raw Data - Production'!P106+'Raw Data - Packing'!L106 -> 203 | I101: =SUMIF('Raw Data - Packing'!A:A,A101,'Raw Data - Packing'!D:D) -> 86520 | J101: =SUMIF('Raw Data - Packing'!A:A,A101,'Raw Data - Packing'!F:F) -> 11200 | L101: =+E101-I101+L100-(G101/Weights!$B$2) -> 35172.049 | M101: =+F101-J101+M100-(H101/Weights!$B$4) -> 64282.5 | N101: =+E101*Weights!$B$2 -> 8571.825 | O101: =+F101*Weights!$B$4 -> 6316.4062 | Q101: =I101+J101 -> 97720
A102: =+'Raw Data - Production'!A107 -> 46261 | B102: =+WEEKNUM(A102) -> 35 | C102: =+TEXT(A102,"mmmm") -> August | D102: P8 | E102: =+'Raw Data - Production'!D107+'Raw Data - Production'!E107+'Raw Data - Production'!F107 -> 102912 | F102: =+'Raw Data - Production'!G107+'Raw Data - Production'!H107+'Raw Data - Production'!I107 -> 7805 | G102: =+'Raw Data - Production'!K107+'Raw Data - Production'!L107+'Raw Data - Packing'!I107 -> 318 | H102: =+'Raw Data - Production'!N107+'Raw Data - Production'!O107+'Raw Data - Production'!P107+'Raw Data - Packing'!L107 -> 38 | I102: =SUMIF('Raw Data - Packing'!A:A,A102,'Raw Data - Packing'!D:D) -> 60480 | J102: =SUMIF('Raw Data - Packing'!A:A,A102,'Raw Data - Packing'!F:F) -> 33992 | L102: =+E102-I102+L101-(G102/Weights!$B$2) -> 72578.864 | M102: =+F102-J102+M101-(H102/Weights!$B$4) -> 37852.3 | N102: =+E102*Weights!$B$2 -> 6512.4 | O102: =+F102*Weights!$B$4 -> 1219.5312 | Q102: =I102+J102 -> 94472
A103: =+'Raw Data - Production'!A108 -> 46262 | B103: =+WEEKNUM(A103) -> 35 | C103: =+TEXT(A103,"mmmm") -> August | D103: P8 | E103: =+'Raw Data - Production'!D108+'Raw Data - Production'!E108+'Raw Data - Production'!F108 -> 0 | F103: =+'Raw Data - Production'!G108+'Raw Data - Production'!H108+'Raw Data - Production'!I108 -> 0 | G103: =+'Raw Data - Production'!K108+'Raw Data - Production'!L108+'Raw Data - Packing'!I108 -> 0 | H103: =+'Raw Data - Production'!N108+'Raw Data - Production'!O108+'Raw Data - Production'!P108+'Raw Data - Packing'!L108 -> 70 | I103: =SUMIF('Raw Data - Packing'!A:A,A103,'Raw Data - Packing'!D:D) -> 49380 | J103: =SUMIF('Raw Data - Packing'!A:A,A103,'Raw Data - Packing'!F:F) -> 22960 | L103: 80000 | M103: =+F103-J103+M102-(H103/Weights!$B$4) -> 14444.3 | N103: =+E103*Weights!$B$2 -> 0 | O103: =+F103*Weights!$B$4 -> 0 | Q103: =I103+J103 -> 72340
A104: =+'Raw Data - Production'!A109 -> 46265 | B104: =+WEEKNUM(A104) -> 36 | C104: =+TEXT(A104,"mmmm") -> August | E104: =+'Raw Data - Production'!D109+'Raw Data - Production'!E109+'Raw Data - Production'!F109 -> 108624 | F104: =+'Raw Data - Production'!G109+'Raw Data - Production'!H109+'Raw Data - Production'!I109 -> 48090 | G104: =+'Raw Data - Production'!K109+'Raw Data - Production'!L109+'Raw Data - Packing'!I109 -> 490 | H104: =+'Raw Data - Production'!N109+'Raw Data - Production'!O109+'Raw Data - Production'!P109+'Raw Data - Packing'!L109 -> 392 | I104: =SUMIF('Raw Data - Packing'!A:A,A104,'Raw Data - Packing'!D:D) -> 23750 | J104: =SUMIF('Raw Data - Packing'!A:A,A104,'Raw Data - Packing'!F:F) -> 11200 | L104: =+E104-I104+L103-(G104/Weights!$B$2) -> 157130.79 | M104: =+F104-J104+M103-(H104/Weights!$B$4) -> 48825.5 | N104: =+E104*Weights!$B$2 -> 6873.8625 | O104: =+F104*Weights!$B$4 -> 7514.0625 | Q104: =I104+J104 -> 34950
A105: =+'Raw Data - Production'!A110 -> 46266 | B105: =+WEEKNUM(A105) -> 36 | C105: =+TEXT(A105,"mmmm") -> September | E105: =+'Raw Data - Production'!D110+'Raw Data - Production'!E110+'Raw Data - Production'!F110 -> 117744 | F105: =+'Raw Data - Production'!G110+'Raw Data - Production'!H110+'Raw Data - Production'!I110 -> 29470 | G105: =+'Raw Data - Production'!K110+'Raw Data - Production'!L110+'Raw Data - Packing'!I110 -> 447 | H105: =+'Raw Data - Production'!N110+'Raw Data - Production'!O110+'Raw Data - Production'!P110+'Raw Data - Packing'!L110 -> 2260 | I105: =SUMIF('Raw Data - Packing'!A:A,A105,'Raw Data - Packing'!D:D) -> 78960 | J105: =SUMIF('Raw Data - Packing'!A:A,A105,'Raw Data - Packing'!F:F) -> 23344 | L105: =+E105-I105+L104-(G105/Weights!$B$2) -> 188851.09 | M105: =+F105-J105+M104-(H105/Weights!$B$4) -> 40487.5 | N105: =+E105*Weights!$B$2 -> 7450.9875 | O105: =+F105*Weights!$B$4 -> 4604.6875 | Q105: =I105+J105 -> 102304
A106: =+'Raw Data - Production'!A111 -> 46267 | B106: =+WEEKNUM(A106) -> 36 | C106: =+TEXT(A106,"mmmm") -> September | E106: =+'Raw Data - Production'!D111+'Raw Data - Production'!E111+'Raw Data - Production'!F111 -> 40800 | F106: =+'Raw Data - Production'!G111+'Raw Data - Production'!H111+'Raw Data - Production'!I111 -> 1995 | G106: =+'Raw Data - Production'!K111+'Raw Data - Production'!L111+'Raw Data - Packing'!I111 -> 552 | H106: =+'Raw Data - Production'!N111+'Raw Data - Production'!O111+'Raw Data - Production'!P111+'Raw Data - Packing'!L111 -> 0 | I106: =SUMIF('Raw Data - Packing'!A:A,A106,'Raw Data - Packing'!D:D) -> 33810 | J106: =SUMIF('Raw Data - Packing'!A:A,A106,'Raw Data - Packing'!F:F) -> 0 | L106: =+E106-I106+L105-(G106/Weights!$B$2) -> 187118.12 | M106: =+F106-J106+M105-(H106/Weights!$B$4) -> 42482.5 | N106: =+E106*Weights!$B$2 -> 2581.875 | O106: =+F106*Weights!$B$4 -> 311.71875 | Q106: =I106+J106 -> 33810
A107: =+'Raw Data - Production'!A112 -> 46268 | B107: =+WEEKNUM(A107) -> 36 | C107: =+TEXT(A107,"mmmm") -> September | E107: =+'Raw Data - Production'!D112+'Raw Data - Production'!E112+'Raw Data - Production'!F112 -> 168387 | F107: =+'Raw Data - Production'!G112+'Raw Data - Production'!H112+'Raw Data - Production'!I112 -> 0 | G107: =+'Raw Data - Production'!K112+'Raw Data - Production'!L112+'Raw Data - Packing'!I112 -> 540 | H107: =+'Raw Data - Production'!N112+'Raw Data - Production'!O112+'Raw Data - Production'!P112+'Raw Data - Packing'!L112 -> 0 | I107: =SUMIF('Raw Data - Packing'!A:A,A107,'Raw Data - Packing'!D:D) -> 227580 | J107: =SUMIF('Raw Data - Packing'!A:A,A107,'Raw Data - Packing'!F:F) -> 7560 | L107: =+E107-I107+L106-(G107/Weights!$B$2) -> 119391.79 | M107: =+F107-J107+M106-(H107/Weights!$B$4) -> 34922.5 | N107: =+E107*Weights!$B$2 -> 10655.74 | O107: =+F107*Weights!$B$4 -> 0 | Q107: =I107+J107 -> 235140
A108: =+'Raw Data - Production'!A113 -> 46269 | B108: =+WEEKNUM(A108) -> 36 | C108: =+TEXT(A108,"mmmm") -> September | E108: =+'Raw Data - Production'!D113+'Raw Data - Production'!E113+'Raw Data - Production'!F113 -> 0 | F108: =+'Raw Data - Production'!G113+'Raw Data - Production'!H113+'Raw Data - Production'!I113 -> 0 | G108: =+'Raw Data - Production'!K113+'Raw Data - Production'!L113+'Raw Data - Packing'!I113 -> 0 | H108: =+'Raw Data - Production'!N113+'Raw Data - Production'!O113+'Raw Data - Production'!P113+'Raw Data - Packing'!L113 -> 0 | I108: =SUMIF('Raw Data - Packing'!A:A,A108,'Raw Data - Packing'!D:D) -> 0 | J108: =SUMIF('Raw Data - Packing'!A:A,A108,'Raw Data - Packing'!F:F) -> 0 | L108: =+E108-I108+L107-(G108/Weights!$B$2) -> 119391.79 | M108: =+F108-J108+M107-(H108/Weights!$B$4) -> 34922.5 | N108: =+E108*Weights!$B$2 -> 0 | O108: =+F108*Weights!$B$4 -> 0 | Q108: =I108+J108 -> 0
